{
	"scenario_text":[
		{
			"key":"EP07_S1331_0001",
			"value":"なあタクマ、カイトのヤツ\nなんでミウのそばに行かないんだろうな"
		},
		{
			"key":"EP07_S1331_0002",
			"value":"あんなにミウのことを心配してるくせに\nこういう時べったりにはならねーんだよな"
		},
		{
			"key":"EP07_S1331_0003",
			"value":"あんまりべったりくっつきすぎると\nミウが嫌がるからじゃない？"
		},
		{
			"key":"EP07_S1331_0004",
			"value":"そーなのかね"
		},
		{
			"key":"EP07_S1331_0005",
			"value":"どうもカイトは、ただの過保護なオニイチャンとは\n違うような気がするんだよな……"
		},
		{
			"key":"EP07_S1331_0006",
			"value":"（そうなのかな？　まだよくわからないな）"
		},
		{
			"key":"EP07_S1331_0007",
			"value":"この辺りには危険なモンはなさそーだ\nどこを探せばいいのやら"
		}
	]
}
