{
	"scenario_text":[
		{
			"key":"EP01_S0326_0101",
			"value":"ラブラモン、大丈夫……？"
		},
		{
			"key":"EP01_S0326_0102",
			"value":"だ、大丈夫よ……\n見た目ほど、酷くない、から……"
		},
		{
			"key":"EP01_S0326_0103",
			"value":"うぅっ！　痛た……"
		},
		{
			"key":"EP01_S0326_0104",
			"value":"酷くないなんて、そんなことなさそうだけど……"
		},
		{
			"key":"EP01_S0326_0105",
			"value":"放っておいて治る傷じゃなさそうだわ"
		},
		{
			"key":"EP01_S0326_0106",
			"value":"タクマくん、急いで治療道具を見つけましょう"
		},
		{
			"key":"EP01_S0326_0107",
			"value":"うん！"
		},
		{
			"key":"EP01_S0326_0108",
			"value":"急いで治療道具を見つけましょう"
		},
		{
			"key":"EP01_S0326_0110",
			"value":"（救急箱を持って早くラブラモンのところへ行こう！）"
		},
		{
			"key":"EP01_S0326_0001",
			"value":"ミノル！　見つかったよ！"
		},
		{
			"key":"EP01_S0326_0002",
			"value":"お、タクマ！　それにアオイさんも！\nアオイさんが持っているの、救急箱か！"
		},
		{
			"key":"EP01_S0326_0003",
			"value":"ええ、タクマくんが見つけてくれたの"
		},
		{
			"key":"EP01_S0326_0004",
			"value":"ラブラモン！\n待っててね、すぐに手当てするから！"
		},
		{
			"key":"EP01_S0326_0005",
			"value":"しっかし、よく見つけられたな\nどこにあったんだ？"
		},
		{
			"key":"EP01_S0326_0006",
			"value":"職員室だよ\n棚の奥に……"
		},
		{
			"key":"EP01_S0326_0007",
			"value":"ね、ねえ……どういう事かしら？"
		},
		{
			"key":"EP01_S0326_0008",
			"value":"救急箱の中を今、確認したんだけど……"
		},
		{
			"key":"EP01_S0326_0009",
			"value":"こんなに校舎がボロボロなんですよ\n薬も、腐ってないですか？"
		},
		{
			"key":"EP01_S0326_0010",
			"value":"それが……見た限り、包帯も綺麗だし、\n消毒薬も問題なさそうなの"
		},
		{
			"key":"EP01_S0326_0011",
			"value":"まるで新品みたいだわ……\n何か変だけど、これで手当てを……"
		},
		{
			"key":"EP01_S0326_0012",
			"value":"……"
		},
		{
			"key":"EP01_S0326_0013",
			"value":"……さあ、ラブラモン\nこれでどうかしら？"
		},
		{
			"key":"EP01_S0326_0014",
			"value":"わぁ、ちゃんと手当してくれたんだ！\nありがとう、アオイ！"
		},
		{
			"key":"EP01_S0326_0015",
			"value":"（ラブラモン、あんなにしっぽを振って喜んでる\n　すっかりアオイさんに懐いたみたいだな）"
		},
		{
			"key":"EP01_S0326_0016",
			"value":"何か変わったところとかなかった？\n人とか……って、誰かいたら一緒にいるか……"
		},
		{
			"key":"EP01_S0326_0017",
			"value":"変わったところ……\nうーん……何て言えばいいか……"
		},
		{
			"key":"EP01_S0326_0018",
			"value":"見た限り、校内にも人影はなかったわね……\n奥まで調べたわけじゃないけど……"
		},
		{
			"key":"EP01_S0326_0019",
			"value":"そういえば\nトイレもなんだか古めかしい感じだったな"
		},
		{
			"key":"EP01_S0326_0020",
			"value":"か～っ、ますますわかんねー！"
		},
		{
			"key":"EP01_S0326_0021",
			"value":"オレ、今の今まで、もしかして\nタイムスリップしたんじゃねーかって思ってたのに！"
		},
		{
			"key":"EP01_S0326_0022",
			"value":"何だよ、タイムカプセルに入れてたわけでもないのに\nなんで救急キットが新品なんだよ！？"
		},
		{
			"key":"EP01_S0326_0023",
			"value":"校舎だけが風化した……なんて\nそんなはずはないか……"
		},
		{
			"key":"EP01_S0326_0024",
			"value":"わからないわ……\n私たち以外に誰か会えればいいんだけど……"
		},
		{
			"key":"EP01_S0326_0025",
			"value":"……なあ、タクマ\nオレ、やっぱ悪い夢みてんのかなあ"
		},
		{
			"key":"EP01_S0326_0026",
			"value":"それは僕も同感だけど、でも……\n夢かどうかなんて、醒めるまでわかんないよ"
		},
		{
			"key":"EP01_S0326_0027",
			"value":"だよなあ、頬をツネったって\n痛ッ！　てなってるのが夢かも知んねーし……"
		},
		{
			"key":"EP01_S0326_0028",
			"value":"でも、変な生き物が出てきたり\n学校がこんなワケわかんねー事になってたり……"
		},
		{
			"key":"EP01_S0326_0029",
			"value":"いったい何が起きたっていうんだ……\nなぁ、アグモンたちは何か知らないか？"
		},
		{
			"key":"EP01_S0326_0030",
			"value":"う～、ボクもわかんないよ……\n最初からこうだったよ？"
		},
		{
			"key":"EP01_S0326_0031",
			"value":"最初からってなんだよ？\nそんなわけないだろ！？"
		},
		{
			"key":"EP01_S0326_0032",
			"value":"いや、アグモンの言う通りだ"
		},
		{
			"key":"EP01_S0326_0033",
			"value":"俺たちは生まれた時からここにいるが\nずっとこれが当たり前だった"
		},
		{
			"key":"EP01_S0326_0034",
			"value":"今お前たちがなぜ疑問に思っているか\n俺たちにはわからないんだ"
		},
		{
			"key":"EP01_S0326_0035",
			"value":"（ずっと、って言ったか？　そんなはずはない\n　僕たちは綺麗な校舎をこの目で見てたんだ）"
		},
		{
			"key":"EP01_S0326_0036",
			"value":"（ここは、僕たちの知ってる校舎とは違うのか？\n　いったいここは何なんだ？）"
		},
		{
			"key":"EP01_S0326_0037",
			"value":"そんな……なんなの、これ……"
		},
		{
			"key":"EP01_S0326_0038",
			"value":"アオイ、元気出して……"
		},
		{
			"key":"EP01_S0326_0039",
			"value":"うぅ～……ごめんな、タクマ"
		},
		{
			"key":"EP01_S0326_0040",
			"value":"……"
		},
		{
			"key":"EP01_S0326_0041",
			"value":"う、うわぁああああああああああ！"
		},
		{
			"key":"EP01_S0326_0042",
			"value":"今の！？\nリョウの声だ！"
		},
		{
			"key":"EP01_S0326_0043",
			"value":"あいつも……ここに居るのか！？"
		},
		{
			"key":"EP01_S0326_0044",
			"value":"今の声……\n二階からだわ！"
		},
		{
			"key":"EP01_S0326_0045",
			"value":"……今度こそ、ヒーローに……"
		},
		{
			"key":"EP01_S0326_0046",
			"value":"……ミノル？"
		},
		{
			"key":"EP01_S0326_0047",
			"value":"……オレ、今度は逃げないぜ\nリョウを助けに行く"
		},
		{
			"key":"EP01_S0326_0048",
			"value":"うむ、ならば俺も手を貸そう"
		},
		{
			"key":"EP01_S0326_0049",
			"value":"アオイは私が守るからね！\n安心して行きましょ！"
		},
		{
			"key":"EP01_S0326_0050",
			"value":"ありがとう、ラブラモン！\nでも、手当てしたばかりだから無理はしないでね……"
		},
		{
			"key":"EP01_S0326_0051",
			"value":"（わからないことだらけで不安だけど\n　考えるのは後だ）"
		},
		{
			"key":"EP01_S0326_0052",
			"value":"（目の前のことに集中していれば\n　その間だけでも、気はまぎれる……）"
		},
		{
			"key":"EP01_S0326_0053",
			"value":"行こう、タクマ！"
		},
		{
			"key":"EP01_S0326_0054",
			"value":"ああ！"
		},
		{
			"key":"EP01_S0326_0055",
			"value":"（あった！　救急箱だ\n　やっぱり保健室だからな、意外に早く見つかったな）"
		}
	]
}
