{
	"scenario_text":[
		{
			"key":"EP10_S1140_0001",
			"value":"レナモン……僕たちの勝ちだ"
		},
		{
			"key":"EP10_S1140_0002",
			"value":"まだだ！　まだ……ぐっ！？"
		},
		{
			"key":"EP10_S1140_0003",
			"value":"もうやめて！\nこれ以上は無理よ！"
		},
		{
			"key":"EP10_S1140_0004",
			"value":"まだ私は負けていない\n負けて、いない……！"
		},
		{
			"key":"EP10_S1140_0005",
			"value":"たす、け……るから……\n……かならず、私が……"
		},
		{
			"key":"EP10_S1140_0006",
			"value":"レナモン……\n君とミユキの間に、強い絆があるのはわかっている"
		},
		{
			"key":"EP10_S1140_0007",
			"value":"私は君からミユキを奪ったりはしない"
		},
		{
			"key":"EP10_S1140_0008",
			"value":"嘘、だ……\nだってお前は……ミユキを見捨てて……！"
		},
		{
			"key":"EP10_S1140_0009",
			"value":"嘘などつくものか\n……私は感謝しているのだ"
		},
		{
			"key":"EP10_S1140_0010",
			"value":"君が辛い思いをしたことはよくわかった\n私の存在が君をどれだけ苦しめたかも"
		},
		{
			"key":"EP10_S1140_0011",
			"value":"どれだけ私を恨んでもらっても構わない\nしかし、今は協力してほしい"
		},
		{
			"key":"EP10_S1140_0012",
			"value":"主の言葉を信じたところで\n君に待つのは更なる忍耐の日々だけだろうから"
		},
		{
			"key":"EP10_S1140_0013",
			"value":"な……何を言う……？"
		},
		{
			"key":"EP10_S1140_0014",
			"value":"私は君にこれ以上の苦しみを与えたくない\nそして、ミユキにも"
		},
		{
			"key":"EP10_S1140_0015",
			"value":"……だから、お前がミユキを語るな、と……！"
		},
		{
			"key":"EP10_S1140_0016",
			"value":"主が約束を守る保証などない\n賢い君なら、わかっているはずだ"
		},
		{
			"key":"EP10_S1140_0017",
			"value":"それでも約束に縋ってしまったのは\n他に方法がなかったからなのだろう"
		},
		{
			"key":"EP10_S1140_0018",
			"value":"だが、そもそも最初にミユキを脅かしたのは主だ"
		},
		{
			"key":"EP10_S1140_0019",
			"value":"そして今度は君が主に騙され\n苦しめられたと知ったら……"
		},
		{
			"key":"EP10_S1140_0020",
			"value":"その時、一番悲しむのは……"
		},
		{
			"key":"EP10_S1140_0021",
			"value":"ミユキ……だよな"
		},
		{
			"key":"EP10_S1140_0022",
			"value":"！！！"
		},
		{
			"key":"EP10_S1140_0023",
			"value":"レナモン、姉さんを……ミユキを\n主の手から取り戻そう"
		},
		{
			"key":"EP10_S1140_0024",
			"value":"あの日、私たちがするべきだったことを\n今、成し遂げるんだ"
		},
		{
			"key":"EP10_S1140_0025",
			"value":"は……る……"
		},
		{
			"key":"EP10_S1140_0026",
			"value":"…………私は……"
		},
		{
			"key":"EP10_S1140_0027",
			"value":"アア……ヤハリ"
		},
		{
			"key":"EP10_S1140_0028",
			"value":"――！！！"
		},
		{
			"key":"EP10_S1140_0029",
			"value":"誰っ！？"
		},
		{
			"key":"EP10_S1140_0030",
			"value":"ヤハリ……思イ隔ツ、フタ心アリシ\nオ前モマタ、力ナキ、タダノ獣デアッタカ"
		},
		{
			"key":"EP10_S1140_0031",
			"value":"ミユキ……い、いや……主！\n違う、これは！"
		},
		{
			"key":"EP10_S1140_0032",
			"value":"み、見て！\nミユキさんの後ろ、敵の配下がいっぱい……！"
		},
		{
			"key":"EP10_S1140_0033",
			"value":"愚カナリシ裏切リ者ニ天誅ヲ！"
		},
		{
			"key":"EP10_S1140_0034",
			"value":"来るぞ、気を付けろ！"
		}
	]
}
