{
	"scenario_text":[
		{
			"key":"EP08_S0090_0001",
			"value":"ここなら、誰かに聞かれる心配はなさそうだな"
		},
		{
			"key":"EP08_S0090_0002",
			"value":"うん、それじゃ早速話すね\nといっても……"
		},
		{
			"key":"EP08_S0090_0003",
			"value":"これは全部、私の推測なんだけど"
		},
		{
			"key":"EP08_S0090_0004",
			"value":"…………"
		},
		{
			"key":"EP08_S0090_0005",
			"value":"私たちがいる『この世界』と\n私たちが呑み込まれた『あっちの世界』は"
		},
		{
			"key":"EP08_S0090_0006",
			"value":"繋がってるんだと思う"
		},
		{
			"key":"EP08_S0090_0007",
			"value":"それはそうだよね\nでなきゃ、行ったり来たりできないよ"
		},
		{
			"key":"EP08_S0090_0008",
			"value":"そういうことじゃないの\n『あっちの世界』で何か事件が起きると──"
		},
		{
			"key":"EP08_S0090_0009",
			"value":"それと対応するように\n『この世界』でも何かが起こる"
		},
		{
			"key":"EP08_S0090_0010",
			"value":"え……？"
		},
		{
			"key":"EP08_S0090_0011",
			"value":"さっき、テレビのニュースで言ってた事故……\nあれも、きっとそう"
		},
		{
			"key":"EP08_S0090_0012",
			"value":"それって……"
		},
		{
			"key":"EP08_S0090_0013",
			"value":"思い出してタクマさん\nロープウェイや廃工場で何があったか"
		},
		{
			"key":"EP08_S0090_0014",
			"value":"（ロープウェイ……それから廃工場……\n　あの時、僕らの身に起きたことは……）"
		},
		{
			"key":"EP08_S0090_0015",
			"value":"（そうか……そういうことか！）"
		},
		{
			"key":"EP08_S0090_0016",
			"value":"（ロープウェイの事故……\n　あの現場は、リョウが死んだ場所）"
		},
		{
			"key":"EP08_S0090_0017",
			"value":"（ロープウェイの事故……あの現場は\n　リョウが霧に呑まれそうになった場所）"
		},
		{
			"key":"EP08_S0090_0018",
			"value":"（そして、地滑りが起きたのは\n　ピエモンのいた廃工場だ）"
		},
		{
			"key":"EP08_S0090_0019",
			"value":"つまり、２つの世界は重なり合うように\n影響しあってる……？"
		},
		{
			"key":"EP08_S0090_0020",
			"value":"正確に言えば、あっちの世界の出来事が\nこっちの世界に影響を与えてるんだと思う"
		},
		{
			"key":"EP08_S0090_0021",
			"value":"その証拠に……といえるかわからないけど\n二つの場所には共通点もあったの"
		},
		{
			"key":"EP08_S0090_0022",
			"value":"（共通点？\n　そんなのあったっけ？）"
		},
		{
			"key":"EP08_S0090_0023",
			"value":"（場所以外に、重なるもの……？\n　２つの世界で共通する何かって……）"
		},
		{
			"key":"EP08_S0090_0024",
			"value":"もしかして……霧？"
		},
		{
			"key":"EP08_S0090_0025",
			"value":"そう。どちらにも……霧が立ち込めてた"
		},
		{
			"key":"EP08_S0090_0026",
			"value":"何かが起きるときは、必ず霧が辺りを覆ってたの"
		},
		{
			"key":"EP08_S0090_0027",
			"value":"ということは……"
		},
		{
			"key":"EP08_S0090_0028",
			"value":"あっちの世界で、霧が出ているところには\n悪いことが起きて"
		},
		{
			"key":"EP08_S0090_0029",
			"value":"そのうち、この世界にも影響が出る\n……そういうことなのか？"
		},
		{
			"key":"EP08_S0090_0030",
			"value":"たぶん"
		},
		{
			"key":"EP08_S0090_0031",
			"value":"それ、ヤバいじゃないか！\nあっちじゃ、この校舎にも霧が出てた"
		},
		{
			"key":"EP08_S0090_0032",
			"value":"あそこには、まだみんないるかもしれない！"
		},
		{
			"key":"EP08_S0090_0033",
			"value":"あっちにいるみんなに、もしものことがあったら……！"
		},
		{
			"key":"EP08_S0090_0034",
			"value":"このことを知っているのは\n私とタクマさんだけ……つまり"
		},
		{
			"key":"EP08_S0090_0035",
			"value":"止められるのは\n私たちだけしかいないの"
		},
		{
			"key":"EP08_S0090_0036",
			"value":"え、それってつまり……！？\nいや待って、冗談……だよね？？"
		},
		{
			"key":"EP08_S0090_0037",
			"value":"そう。みんなを助けられるのも……\n私とあなた――タクマさんだけ"
		},
		{
			"key":"EP08_S0090_0038",
			"value":"私たちが、あっちの世界に戻って\nみんなを助けないといけないの！"
		},
		{
			"key":"EP08_S0090_0039",
			"value":"だからって、僕らに何ができるんだ？"
		},
		{
			"key":"EP08_S0090_0040",
			"value":"現に、僕らはあっちの世界に戻る方法さえ\nわからないんだよ？"
		},
		{
			"key":"EP08_S0090_0041",
			"value":"戻る方法ならあるよ！"
		},
		{
			"key":"EP08_S0090_0042",
			"value":"えっ？"
		},
		{
			"key":"EP08_S0090_0043",
			"value":"私の歌で、２つの世界が繋がるのを\nタクマさんも見たでしょ？"
		},
		{
			"key":"EP08_S0090_0044",
			"value":"あれは、水無瀬家に代々伝わる力なの\n私なら、もう一度２つの世界を繋げられる！"
		},
		{
			"key":"EP08_S0090_0045",
			"value":"水無瀬家に代々伝わる……って"
		},
		{
			"key":"EP08_S0090_0046",
			"value":"それじゃあ……あのおばあさんが言ってた\n集団失踪事件で消えた、水無瀬家のお嬢さんって……！"
		},
		{
			"key":"EP08_S0090_0047",
			"value":"うん、私のこと"
		},
		{
			"key":"EP08_S0090_0048",
			"value":"やっぱり！　それじゃあミユキとハルが\nあっちの世界に行ったのは、５０年も前！？"
		},
		{
			"key":"EP08_S0090_0049",
			"value":"そういうことになるね"
		},
		{
			"key":"EP08_S0090_0050",
			"value":"（５０年も、たった２人で……！？\n　そ、そんなことって……！）"
		},
		{
			"key":"EP08_S0090_0051",
			"value":"（ああ……また頭がこんがらがりそうだ\n　けど、今大事なのは……）"
		},
		{
			"key":"EP08_S0090_0052",
			"value":"み、ミユキの受継いだ不思議な力っていうので\nあっちの世界に戻れるかもしれないのはわかったけど……"
		},
		{
			"key":"EP08_S0090_0053",
			"value":"もし仮に、またあっちに行けたところで\n霧が相手じゃ……"
		},
		{
			"key":"EP08_S0090_0054",
			"value":"あの霧を操っているのは、主なの"
		},
		{
			"key":"EP08_S0090_0055",
			"value":"主って……？"
		},
		{
			"key":"EP08_S0090_0056",
			"value":"私から魂を半分奪っていた、主"
		},
		{
			"key":"EP08_S0090_0057",
			"value":"あっちの世界で、子供たちを\n呑み込んでるのも、その主なの"
		},
		{
			"key":"EP08_S0090_0058",
			"value":"（そういえば、アルケニモンやピエモンも\n　主に生け贄を、とか言ってた……）"
		},
		{
			"key":"EP08_S0090_0059",
			"value":"だけど、どうして\nその主はミユキの魂を奪ったりなんてしてたんだ？"
		},
		{
			"key":"EP08_S0090_0060",
			"value":"５０年前、私が『あっちの世界』に\nさらわれた時……"
		},
		{
			"key":"EP08_S0090_0061",
			"value":"他にもたくさんの子どもが、同じように\nさらわれたの"
		},
		{
			"key":"EP08_S0090_0062",
			"value":"だから、私も最初はただの偶然なんだと\n思ってた"
		},
		{
			"key":"EP08_S0090_0063",
			"value":"けど、違ったの\n主の狙いは『巫女の血脈』"
		},
		{
			"key":"EP08_S0090_0064",
			"value":"巫女……？\nもしかして、ミユキのことなのか？"
		},
		{
			"key":"EP08_S0090_0065",
			"value":"うん。私が……水無瀬家が受け継いできた\n聖なる力……"
		},
		{
			"key":"EP08_S0090_0066",
			"value":"それが欲しい主は、何百年も待ち続けていたの\n怨みを晴らすために……！"
		},
		{
			"key":"EP08_S0090_0067",
			"value":"（怨み？　それに何百年も待ってたって……\n　そんな途方もない話……）"
		},
		{
			"key":"EP08_S0090_0068",
			"value":"タクマさん、お願い\n私、主の因縁を断ち切りたい"
		},
		{
			"key":"EP08_S0090_0069",
			"value":"あの子……ハルを救うためにも\n主を止めたいの……！"
		},
		{
			"key":"EP08_S0090_0070",
			"value":"止めるったって、一体どうすれば！？"
		},
		{
			"key":"EP08_S0090_0071",
			"value":"私にもわからない\nでも、何もしないわけにはいかない……"
		},
		{
			"key":"EP08_S0090_0072",
			"value":"何より私……\nハルをひとりぼっちにはさせられないから"
		},
		{
			"key":"EP08_S0090_0073",
			"value":"ミユキ……"
		},
		{
			"key":"EP08_S0090_0074",
			"value":"それに、あっちの世界が壊れていけば\nこの世界だって無事じゃ済まないと思うの"
		},
		{
			"key":"EP08_S0090_0075",
			"value":"ミユキの言う通りだ。けど……"
		},
		{
			"key":"EP08_S0090_0076",
			"value":"（一体、どうしたらいいんだ……）"
		},
		{
			"key":"EP08_S0090_0077",
			"value":"（この世界が終わりかねない\n　とんでもないことが起きてるのに）"
		},
		{
			"key":"EP08_S0090_0078",
			"value":"（正直、怖い\n　僕なんかに何かできるとは、到底思えない）"
		},
		{
			"key":"EP08_S0090_0079",
			"value":"（だけど、ミユキは戻る気でいる\n　弟を見捨ててはおけないから）"
		},
		{
			"key":"EP08_S0090_0080",
			"value":"（僕だって、向こうにいるみんなを助けたい\n　見捨てたくなんてない）"
		},
		{
			"key":"EP08_S0090_0081",
			"value":"（けど、僕には……そんな力なんてない）"
		},
		{
			"key":"EP08_S0090_0082",
			"value":"（僕はただの中学生で……特別な力もなくて……\n　そんな僕に世界を救うことなんてできると思えない）"
		},
		{
			"key":"EP08_S0090_0083",
			"value":"（僕は、ミユキを見捨ててもいいのか？\n　でも、どうしたら……）"
		},
		{
			"key":"EP08_S0090_Q1",
			"value":"（今の僕の正直な気持ちは……）"
		},
		{
			"key":"EP08_S0090_Q1_A1",
			"value":"みんなを見捨てたくない"
		},
		{
			"key":"EP08_S0090_Q1_A2",
			"value":"怖い"
		},
		{
			"key":"EP08_S0090_Q1_A3",
			"value":"世界を救うなんて僕には難しい"
		},
		{
			"key":"EP08_S0090_0084",
			"value":"みんなを見捨てたくない"
		},
		{
			"key":"EP08_S0090_0085",
			"value":"僕だって……\n僕だって、みんなを見捨てたくなんかない！"
		},
		{
			"key":"EP08_S0090_0086",
			"value":"タクマさん……それじゃあ……！"
		},
		{
			"key":"EP08_S0090_0087",
			"value":"だけど、僕なんかに\n何が出来るって言うんだ？"
		},
		{
			"key":"EP08_S0090_0088",
			"value":"僕は……ただの中学生で\nミユキみたいな特別な力もない"
		},
		{
			"key":"EP08_S0090_0089",
			"value":"あっちの世界で、必死に戦ってきたけど\n本当は……本当は……"
		},
		{
			"key":"EP08_S0090_0090",
			"value":"アグモンがいるじゃない！"
		},
		{
			"key":"EP08_S0090_0091",
			"value":"今までだって、タクマさんは\nアグモンと一緒に、危機を乗り越えてきたでしょ？"
		},
		{
			"key":"EP08_S0090_0092",
			"value":"怖い"
		},
		{
			"key":"EP08_S0090_0093",
			"value":"ミユキの言ってることはわかるけど……\n正直、僕はもう……怖いんだ"
		},
		{
			"key":"EP08_S0090_0094",
			"value":"タクマさん……"
		},
		{
			"key":"EP08_S0090_0095",
			"value":"今までだって、何度も危険な目に遭ってきたけど……"
		},
		{
			"key":"EP08_S0090_0096",
			"value":"それが、何百年も続く怨みだとか\n世界がどうなるか分からないって言われたら"
		},
		{
			"key":"EP08_S0090_0097",
			"value":"僕の手には負えないっていうか\n僕ひとりじゃ、どうしていいか……"
		},
		{
			"key":"EP08_S0090_0098",
			"value":"そうだよね……\nこんな話、驚くなって言う方が無理だし……"
		},
		{
			"key":"EP08_S0090_0099",
			"value":"でも、こんな時のために\n私たちには、大切な相手がいるんだと思う"
		},
		{
			"key":"EP08_S0090_0100",
			"value":"（大切な相手って……）"
		},
		{
			"key":"EP08_S0090_0101",
			"value":"アグモンの……こと？"
		},
		{
			"key":"EP08_S0090_0102",
			"value":"アグモンがいれば、どんなことも乗り越えられる……\nタクマさんは、そう思ったこと……ない？"
		},
		{
			"key":"EP08_S0090_0103",
			"value":"僕には難しい"
		},
		{
			"key":"EP08_S0090_0104",
			"value":"僕には、世界を救うなんて……難しすぎるよ\n僕にできることなんて、ないんじゃないかな……？"
		},
		{
			"key":"EP08_S0090_0105",
			"value":"そんな……そんなことない！"
		},
		{
			"key":"EP08_S0090_0106",
			"value":"タクマさんは、私やハルのそばに\nずっといてくれた！"
		},
		{
			"key":"EP08_S0090_0107",
			"value":"主に呑み込まれそうになった時だって\n真っ先に駆けつけてくれたのは、タクマさんだよ？"
		},
		{
			"key":"EP08_S0090_0108",
			"value":"今度だって！"
		},
		{
			"key":"EP08_S0090_0109",
			"value":"これ以上は、僕の手にあまるっていうか……\n他に方法がないかを考えたいっていうか……"
		},
		{
			"key":"EP08_S0090_0110",
			"value":"僕みたいな子供じゃどうしようもないよ\nせめて信頼できる大人に相談を……"
		},
		{
			"key":"EP08_S0090_0111",
			"value":"それが難しいことは、タクマさんだって\nわかってるでしょ？"
		},
		{
			"key":"EP08_S0090_0112",
			"value":"それは……"
		},
		{
			"key":"EP08_S0090_0113",
			"value":"それに……信頼できる相手なら\nアグモンがいるよ"
		},
		{
			"key":"EP08_S0090_0114",
			"value":"タクマさんとアグモンは\n強い絆で結ばれてる……そうでしょ？"
		},
		{
			"key":"EP08_S0090_0115",
			"value":"（ミユキの言う通りだ……）"
		},
		{
			"key":"EP08_S0090_0116",
			"value":"（これまでだって、アグモンと一緒に\n　危機に立ち向かい、苦難を乗り越えてきた）"
		},
		{
			"key":"EP08_S0090_0117",
			"value":"（だったら、今度だって……！）"
		},
		{
			"key":"EP08_S0090_0118",
			"value":"（そうは……思う。思うんだ……けど……！）"
		},
		{
			"key":"EP08_S0090_0119",
			"value":"（元の世界に戻ってきたという事実が\n　僕を、臆病にさせているような気がした）"
		},
		{
			"key":"EP08_S0090_0120",
			"value":"タクマさん……お願い……！"
		}
	]
}
