{
	"scenario_text":[
		{
			"key":"EP06_S2224_0001",
			"value":"ここの団地、あんまり日当たりが\nよくなさそうに思えるのよね"
		},
		{
			"key":"EP06_S2224_0002",
			"value":"やっぱり日当たりとか気になるんだ\nフローラモンは植物っぽいケモノだから？"
		},
		{
			"key":"EP06_S2224_0003",
			"value":"まあ、確かに身体全体で\n光を受けるのは気持ちがいいわよ？"
		},
		{
			"key":"EP06_S2224_0004",
			"value":"でも私の身体は、完全に\n植物ってわけでもないんだから"
		},
		{
			"key":"EP06_S2224_0005",
			"value":"ふーん……ケモノに関しては\nわかんないことがいっぱいだね"
		},
		{
			"key":"EP06_S2224_0006",
			"value":"（それぞれの生態に応じて、好きなこととか\n　苦手なこととかあるんだろうな）"
		},
		{
			"key":"EP06_S2224_0007",
			"value":"（悪い進化のことなんかは、教授に言われるまで\n　本人たちも知らなかったみたいし……）"
		},
		{
			"key":"EP06_S2224_0008",
			"value":"（僕たちはケモノについて、もっと\n　知らなきゃいけないのかもな）"
		},
		{
			"key":"EP06_S2224_0009",
			"value":"ファルコモンったら、自分の気持ちに\n素直になったらいいのにね"
		}
	]
}
