{
	"scenario_text":[
		{
			"key":"EP12_S9551_0001",
			"value":"はぁ……おかしなことは起きるのに\n肝心の彼の姿は見当たらない"
		},
		{
			"key":"EP12_S9551_0002",
			"value":"どうしようか、アグモン？"
		},
		{
			"key":"EP12_S9551_0003",
			"value":"…………"
		},
		{
			"key":"EP12_S9551_0004",
			"value":"アグモン……？"
		},
		{
			"key":"EP12_S9551_0005",
			"value":"ちょっと待て、どこに行くんだよアグモン\nどうしたんだよ……！"
		},
		{
			"key":"EP12_S9551_0006",
			"value":"……"
		},
		{
			"key":"EP12_S9551_0007",
			"value":"アグモン、どこ行く気だ……？\n廊下に出るのか？"
		},
		{
			"key":"EP12_S9551_0008",
			"value":"……"
		},
		{
			"key":"EP12_S9551_0009",
			"value":"アグモンってば……！\nちょっと待てって！"
		},
		{
			"key":"EP12_S9551_0010",
			"value":"（いったい……アグモンは\n　どうしちゃったんだよ……！）"
		}
	]
}
