{
	"scenario_text":[
		{
			"key":"EP07_S0021_0001",
			"value":"あれ？　教授がいない？"
		},
		{
			"key":"EP07_S0021_0002",
			"value":"どこ行っちゃったんだろう……？"
		},
		{
			"key":"EP07_S0021_0003",
			"value":"～♪"
		},
		{
			"key":"EP07_S0021_0004",
			"value":"（なんだろう……鼻歌？）"
		},
		{
			"key":"EP07_S0021_0005",
			"value":"（あれ……この歌、どこかで\n　聞いたことがあるような……）"
		},
		{
			"key":"EP07_S0021_0006",
			"value":"タクマ、あそこ！\n奥の方に何かあるぞ！"
		},
		{
			"key":"EP07_S0021_0007",
			"value":"これ、地下に向かう階段じゃないか\nこんなものがあったんだ……"
		},
		{
			"key":"EP07_S0021_0008",
			"value":"教授はこの奥かな\n行ってみよう"
		},
		{
			"key":"EP07_S0021_0009",
			"value":"～♪"
		},
		{
			"key":"EP07_S0021_0010",
			"value":"ん……？\nああ、君たちか"
		},
		{
			"key":"EP07_S0021_0011",
			"value":"もしかして、もう集合時間だったか？\nいや、すまない"
		},
		{
			"key":"EP07_S0021_0012",
			"value":"祠の中に入ったら、階段があることに気づいてね"
		},
		{
			"key":"EP07_S0021_0013",
			"value":"つい中を覗いてしまって……\n結果、これに夢中になっていた"
		},
		{
			"key":"EP07_S0021_0014",
			"value":"これは……壁画ですか？"
		},
		{
			"key":"EP07_S0021_0143",
			"value":"これは……\nこの階にも壁画があるんですね"
		},
		{
			"key":"EP07_S0021_0144",
			"value":"ああ、こんな新しい発見をしてしまっては\n学者の血が疼いてね"
		},
		{
			"key":"EP07_S0021_0145",
			"value":"上の階の壁画よりも抽象的なので、まだ\n解説できるほど読み解けてはいないのだが……いやはや"
		},
		{
			"key":"EP07_S0021_0146",
			"value":"（教授、本当にワクワクしてるんだろうな\n　悩んでいる風だけど、同時にどこか楽しそうだ）"
		},
		{
			"key":"EP07_S0021_0015",
			"value":"そうだ……見事だろう\nこんな状況だが学者の血が疼いてね"
		},
		{
			"key":"EP07_S0021_0016",
			"value":"確かに、これだけの壁画があれば\n気になるでしょうね"
		},
		{
			"key":"EP07_S0021_0017",
			"value":"でも、どうして今になって\n階段が見つかったりしたんでしょうか"
		},
		{
			"key":"EP07_S0021_0018",
			"value":"さてな、単に見落としていただけか\nそれとも誰かが道を開けたのか"
		},
		{
			"key":"EP07_S0021_0019",
			"value":"ここ最近の出来事とは\nどう関係しているのかも気になるが……"
		},
		{
			"key":"EP07_S0021_0020",
			"value":"教授、また考え込んじゃったぞ"
		},
		{
			"key":"EP07_S0021_0021",
			"value":"あはは……弱ったな\nもう行こうって言いに来たのに"
		},
		{
			"key":"EP07_S0021_0022",
			"value":"あれ、でも……待てよ"
		},
		{
			"key":"EP07_S0021_0023",
			"value":"教授、そういえばさっきの考え事は\nまとまったんですか？"
		},
		{
			"key":"EP07_S0021_0024",
			"value":"ん？　ああ……ある程度は、だが"
		},
		{
			"key":"EP07_S0021_0025",
			"value":"（今ここには、僕とアグモンと教授しかいない）"
		},
		{
			"key":"EP07_S0021_0026",
			"value":"（ハルやみんなの前では言いづらいことも\n　今なら聞けるかもしれないな）"
		},
		{
			"key":"EP07_S0021_0027",
			"value":"（まず気になるのはハルとの謎のやりとり\n　団地でのあの会話は何だったんだ？）"
		},
		{
			"key":"EP07_S0021_0028",
			"value":"（ガルルモンとも因縁がありそうだったことも\n　気になる……ガルルモンはみんなの敵なのに）"
		},
		{
			"key":"EP07_S0021_0029",
			"value":"（それに、今の鼻歌も……\n　何故ミユキの歌っていた歌を？）"
		},
		{
			"key":"EP07_S0021_0030",
			"value":"（……聞きたいことが山積みだ\n　何から聞こうかな）"
		},
		{
			"key":"EP07_S0021_Q1",
			"value":"（教授に聞きたいことは……）"
		},
		{
			"key":"EP07_S0021_Q1_A1",
			"value":"ハルと何かあったんですか？"
		},
		{
			"key":"EP07_S0021_Q1_A2",
			"value":"ガルルモンとはどんな関係？"
		},
		{
			"key":"EP07_S0021_Q1_A3",
			"value":"今の鼻歌はなんですか？"
		},
		{
			"key":"EP07_S0021_0031",
			"value":"ハルと何かあったんですか？"
		},
		{
			"key":"EP07_S0021_0032",
			"value":"教授……昨日ハルと話していたことが\nどういう意味か、教えてください"
		},
		{
			"key":"EP07_S0021_0033",
			"value":"ハルくんと……？\n何のことだ？"
		},
		{
			"key":"EP07_S0021_0034",
			"value":"すみません。昨日、団地の部屋で\n二人で話しているのを見てしまったんです"
		},
		{
			"key":"EP07_S0021_0035",
			"value":"ああ、そういうことか……\n答えてあげたいのは山々なんだが"
		},
		{
			"key":"EP07_S0021_0036",
			"value":"そもそも、彼が何者なのかを\n知りたいのは私の方なんだ"
		},
		{
			"key":"EP07_S0021_0037",
			"value":"どういうこと？"
		},
		{
			"key":"EP07_S0021_0038",
			"value":"何ぶん、だいぶ昔のことだ\nはっきりと思い出せるわけではない"
		},
		{
			"key":"EP07_S0021_0039",
			"value":"だが、彼の姿かたちは……\n私と……"
		},
		{
			"key":"EP07_S0021_0040",
			"value":"……教授？\n何の話ですか？"
		},
		{
			"key":"EP07_S0021_0041",
			"value":"ああ、いや……すまない\n上手く言葉にできない"
		},
		{
			"key":"EP07_S0021_0042",
			"value":"若い頃はすらすらと言葉が出てきたものだが\n年は取りたくないものだな"
		},
		{
			"key":"EP07_S0021_0043",
			"value":"（うーん……教授自身も\n　戸惑っているように見えるな）"
		},
		{
			"key":"EP07_S0021_0044",
			"value":"（これは何か隠してるんじゃなくて\n　本当にわからないのかも……）"
		},
		{
			"key":"EP07_S0021_0045",
			"value":"ガルルモンとはどんな関係？"
		},
		{
			"key":"EP07_S0021_0046",
			"value":"教授はガルルモンと面識があったんですか？"
		},
		{
			"key":"EP07_S0021_0047",
			"value":"昨日のガルルモンは\nやけに教授を気にしていました"
		},
		{
			"key":"EP07_S0021_0048",
			"value":"……私を疑っているのかね？\n敵と通じていると思っているのだろうか？"
		},
		{
			"key":"EP07_S0021_0049",
			"value":"え？　ち、違います！\nただ気になったというか……"
		},
		{
			"key":"EP07_S0021_0050",
			"value":"いや、いいんだ\nすまない、意地の悪い聞き方をした"
		},
		{
			"key":"EP07_S0021_0051",
			"value":"別に隠し立てをするわけでも\n誤魔化そうというわけでもないんだ……ただ"
		},
		{
			"key":"EP07_S0021_0052",
			"value":"曖昧な記憶で、確信が持てないことが\n幾つもあってね……"
		},
		{
			"key":"EP07_S0021_0053",
			"value":"確信が持てないって……\nほんのちょっと前のことなのに？"
		},
		{
			"key":"EP07_S0021_0054",
			"value":"いいや、ガルルモンと私が出会ったのは\nもっとずっと幼い頃だった……と思う"
		},
		{
			"key":"EP07_S0021_0055",
			"value":"ん～？　教授はコドモの頃に\nガルルモンに会ってるってこと？"
		},
		{
			"key":"EP07_S0021_0056",
			"value":"そうだ、その記憶の中では\n怯える私のそばに彼がいた……気がする"
		},
		{
			"key":"EP07_S0021_0057",
			"value":"それは今と同じように敵としてですか？\nそれともアグモンみたいに、味方として？"
		},
		{
			"key":"EP07_S0021_0058",
			"value":"どうだったか……すまない、思い出せない\n……だが"
		},
		{
			"key":"EP07_S0021_0059",
			"value":"そう、確かに私は彼を知っている……"
		},
		{
			"key":"EP07_S0021_0060",
			"value":"あのガルルモンは、教授に明らかな\n敵意を向けていましたよね……"
		},
		{
			"key":"EP07_S0021_0061",
			"value":"もしかしたら、何かガルルモンに\n恨みを買うようなことをしてしまった……とか？"
		},
		{
			"key":"EP07_S0021_0062",
			"value":"……わからん\nそれが思い出せれば苦労はないんだが……"
		},
		{
			"key":"EP07_S0021_0063",
			"value":"（教授、困った顔をしてる\n　本当に思い出せないみたいだ）"
		},
		{
			"key":"EP07_S0021_0064",
			"value":"（一体、ガルルモンと何があったんだろう）"
		},
		{
			"key":"EP07_S0021_0065",
			"value":"今の鼻歌は？"
		},
		{
			"key":"EP07_S0021_0066",
			"value":"今の鼻歌は……\nなんという名前の歌なんですか？"
		},
		{
			"key":"EP07_S0021_0067",
			"value":"……さあ\n私にもわからないんだよ……"
		},
		{
			"key":"EP07_S0021_0068",
			"value":"えー、自分で歌ってたじゃないか"
		},
		{
			"key":"EP07_S0021_0069",
			"value":"知っている曲じゃないんですか？"
		},
		{
			"key":"EP07_S0021_0070",
			"value":"知っているはずなんだがな\nどこで覚えたのかまるで思い出せんのだ"
		},
		{
			"key":"EP07_S0021_0071",
			"value":"音楽には、その時々の情景を脳に刻む\n効果があるというが……"
		},
		{
			"key":"EP07_S0021_0072",
			"value":"私の老いさらばえた脳には\nこの歌のメロディしか残っていないようだ"
		},
		{
			"key":"EP07_S0021_0073",
			"value":"……ハァ"
		},
		{
			"key":"EP07_S0021_0074",
			"value":"でも、年を重ねて忘れてしまったってことは\nずいぶん前に覚えたってことなんでしょうか"
		},
		{
			"key":"EP07_S0021_0075",
			"value":"昔といえば昔のはずだが……もしかしたら\n忘れたのは、年月のせいではないかもしれない"
		},
		{
			"key":"EP07_S0021_0076",
			"value":"どういうことですか？"
		},
		{
			"key":"EP07_S0021_0077",
			"value":"私は幼い頃、姉を喪っていてね"
		},
		{
			"key":"EP07_S0021_0078",
			"value":"え……"
		},
		{
			"key":"EP07_S0021_0079",
			"value":"喪うといっても、姉は死んだわけではない\n『神隠し』に遭ったのだ"
		},
		{
			"key":"EP07_S0021_0080",
			"value":"その時、私も姉と一緒にいたらしいのだが\n私は全く覚えていない"
		},
		{
			"key":"EP07_S0021_0081",
			"value":"人は恐ろしい事態に直面すると、自己防衛のため\n記憶を封じることがあるそうだ"
		},
		{
			"key":"EP07_S0021_0082",
			"value":"私はこう思うのだ\nこの歌は、私の姉に関わるもので……"
		},
		{
			"key":"EP07_S0021_0083",
			"value":"封じ込められた記憶を思い出すための\n微かな手がかりなのかもしれない、と"
		},
		{
			"key":"EP07_S0021_0084",
			"value":"これは推理と言うよりは願望だがね"
		},
		{
			"key":"EP07_S0021_0085",
			"value":"失った記憶の手がかり……か"
		},
		{
			"key":"EP07_S0021_0086",
			"value":"（教授にとってこの歌は、ただの歌じゃなくて\n　大きな意味を持っているかもしれないんだな）"
		},
		{
			"key":"EP07_S0021_0087",
			"value":"（聞きたいことはまだあるかな？）"
		},
		{
			"key":"EP07_S0021_0088",
			"value":"聞きたいことはもうない"
		},
		{
			"key":"EP07_S0021_0089",
			"value":"まだあると思う"
		},
		{
			"key":"EP07_S0021_0090",
			"value":"（多分聞きたいことは聞けたと思うけど……）"
		},
		{
			"key":"EP07_S0021_0091",
			"value":"タクマ\n教授にアレを見せてみたらどうだろう"
		},
		{
			"key":"EP07_S0021_0092",
			"value":"アレ……？"
		},
		{
			"key":"EP07_S0021_0093",
			"value":"あ、あの写真のことか！"
		},
		{
			"key":"EP07_S0021_0094",
			"value":"写真？"
		},
		{
			"key":"EP07_S0021_0095",
			"value":"ハルと教授が話していたあの部屋で\n偶然見つけたんです"
		},
		{
			"key":"EP07_S0021_0096",
			"value":"気になって持ってきたんですけど\n教授の意見を聞かせてください"
		},
		{
			"key":"EP07_S0021_0097",
			"value":"これなんですけど……"
		},
		{
			"key":"EP07_S0021_0098",
			"value":"こ、これは……\nハルくんと、ミユキくん……？"
		},
		{
			"key":"EP07_S0021_0099",
			"value":"いや……あ、ああ\nそうだ……そうなのか……？"
		},
		{
			"key":"EP07_S0021_0100",
			"value":"教授？　だ、大丈夫ですか？"
		},
		{
			"key":"EP07_S0021_0101",
			"value":"ああ、すまない\n断片的な記憶が、湧き出て……"
		},
		{
			"key":"EP07_S0021_0102",
			"value":"（教授……この写真を見て、失っていた記憶を\n　少しずつ取り戻しているんだ……！）"
		},
		{
			"key":"EP07_S0021_0103",
			"value":"これは……この写真に写っているのは"
		},
		{
			"key":"EP07_S0021_0104",
			"value":"幼い頃の私と……姉だ\n……そのはずだ"
		},
		{
			"key":"EP07_S0021_0105",
			"value":"……え？"
		},
		{
			"key":"EP07_S0021_0106",
			"value":"信じてもらえるかはわからないが……\nハルくんは幼い頃の私にそっくりなんだ"
		},
		{
			"key":"EP07_S0021_0107",
			"value":"それに、ハルというのは幼い頃の私の愛称だ\n姉が……私をそう呼んでいたらしい"
		},
		{
			"key":"EP07_S0021_0108",
			"value":"姉？　えっ？\n教授のお姉さん……！？"
		},
		{
			"key":"EP07_S0021_0109",
			"value":"姉の名は……ミユキ\nそうだ、思い出してきた……"
		},
		{
			"key":"EP07_S0021_0110",
			"value":"あの団地は、そしてあの部屋は記憶にある\n私と姉が、幼い頃に住んでいた場所だ"
		},
		{
			"key":"EP07_S0021_0111",
			"value":"（え？　え！？　それって……\n　いったい、どういうことなんだ……？）"
		},
		{
			"key":"EP07_S0021_0112",
			"value":"私にも、何が起きているのか\nさっぱりわからない"
		},
		{
			"key":"EP07_S0021_0113",
			"value":"……この記憶が何を示すのか\nもう少し何か思い出せればいいのだが"
		},
		{
			"key":"EP07_S0021_0114",
			"value":"私は……何故だ？　わからない\n私と姉にそっくりな二人……彼らは一体？"
		},
		{
			"key":"EP07_S0021_0115",
			"value":"教授……"
		},
		{
			"key":"EP07_S0021_0116",
			"value":"（教授が子供の頃っていったら、ずいぶん前だ\n　他人の空似かもしれない）"
		},
		{
			"key":"EP07_S0021_0117",
			"value":"（でも……ハルがわざわざあの部屋で\n　教授と話していたのは、本当に偶然なのか？）"
		},
		{
			"key":"EP07_S0021_0118",
			"value":"…………"
		},
		{
			"key":"EP07_S0021_0119",
			"value":"（教授、顔が真っ青だ\n　これ以上の質問は教授を追い詰めるかもしれない）"
		},
		{
			"key":"EP07_S0021_0120",
			"value":"（本人にわからないことで詰め寄っても仕方ない\n　この話題は打ち切った方がいいかな）"
		},
		{
			"key":"EP07_S0021_0121",
			"value":"（代わりに何か提案できることはあるかな……？）"
		},
		{
			"key":"EP07_S0021_Q2",
			"value":"（教授に何て言おう）"
		},
		{
			"key":"EP07_S0021_Q2_A1",
			"value":"無理はしないでください"
		},
		{
			"key":"EP07_S0021_Q2_A2",
			"value":"ハルと話しましょう"
		},
		{
			"key":"EP07_S0021_Q2_A3",
			"value":"もう一度団地へ行きましょう"
		},
		{
			"key":"EP07_S0021_0122",
			"value":"無理はしないでください"
		},
		{
			"key":"EP07_S0021_0123",
			"value":"教授、無理はしないでください\nもう十分です"
		},
		{
			"key":"EP07_S0021_0124",
			"value":"タクマくん……すまない"
		},
		{
			"key":"EP07_S0021_0125",
			"value":"いいんです\nまた落ち着いてから話しましょう"
		},
		{
			"key":"EP07_S0021_0126",
			"value":"ハルと話しましょう"
		},
		{
			"key":"EP07_S0021_0127",
			"value":"ハルに直接話を聞いてみましょう"
		},
		{
			"key":"EP07_S0021_0128",
			"value":"君も見たのだろう\n団地の部屋で私とハルくんが話しているところを"
		},
		{
			"key":"EP07_S0021_0129",
			"value":"あの様子では、ただ質問をしたところで\nマトモに答えてもらえるとは思えない……"
		},
		{
			"key":"EP07_S0021_0130",
			"value":"（確かに、そうかもしれない\n　手っ取り早いと思ったんだけどな）"
		},
		{
			"key":"EP07_S0021_0131",
			"value":"もう一度団地へ行きましょう"
		},
		{
			"key":"EP07_S0021_0132",
			"value":"これから西の工場へ向かう時に\n団地を通ることができるはず"
		},
		{
			"key":"EP07_S0021_0133",
			"value":"もう一度団地を確認しましょう\nそうすれば何か思い出せるかもしれない"
		},
		{
			"key":"EP07_S0021_0134",
			"value":"ああ……そうかもしれない\n何か記憶に刺激が与えられれば……"
		},
		{
			"key":"EP07_S0021_0135",
			"value":"（……ハルとミユキ\n　そして教授を知っている様子のガルルモン）"
		},
		{
			"key":"EP07_S0021_0136",
			"value":"（彼らはきっと、大きな秘密を抱えてる\n　そんな気がする……）"
		},
		{
			"key":"EP07_S0021_0137",
			"value":"……みんなを待たせているかもしれない\nもう行こうじゃないか"
		},
		{
			"key":"EP07_S0021_0138",
			"value":"はい。教授、歩けますか？"
		},
		{
			"key":"EP07_S0021_0139",
			"value":"問題ない"
		},
		{
			"key":"EP07_S0021_0140",
			"value":"……大人の私が醜態を晒して申し訳ない"
		},
		{
			"key":"EP07_S0021_0141",
			"value":"記憶がはっきりしたなら、その時には\n君に全てを話そう"
		},
		{
			"key":"EP07_S0021_0142",
			"value":"……はい\nどうか、無理はしないでください"
		}
	]
}
