{
    "scenario_text": [
        {
            "key": "EP12_S9000_0001",
            "value": "――この力……この力ぞ……！"
        },
        {
            "key": "EP12_S9000_0002",
            "value": "この力があれば、我を捨てた一族どもに……！"
        },
        {
            "key": "EP12_S9000_0003",
            "value": "そんな、まさか……！！\n何たること……"
        },
        {
            "key": "EP12_S9000_0004",
            "value": "いけませぬ、そんな――\nハルチカ殿！！"
        },
        {
            "key": "EP12_S9000_0005",
            "value": "彼奴を止めるのです、ハルチカ殿！！！"
        },
        {
            "key": "EP12_S9000_0006",
            "value": "……もはや遅し！"
        },
        {
            "key": "EP12_S9000_0007",
            "value": "おぬしら……"
        },
        {
            "key": "EP12_S9000_0008",
            "value": "お願いです、ハルチカ様！\nお気をお鎮めくだされ！"
        },
        {
            "key": "EP12_S9000_0009",
            "value": "このままでは……\n我らとて、黙って見てるだけとはいきませぬぞ？"
        },
        {
            "key": "EP12_S9000_0010",
            "value": "フン……\n今更、貴様らの言葉など詮なきこと……"
        },
        {
            "key": "EP12_S9000_0011",
            "value": "ほうれ……我が同胞<space=-2em><voffset=1em><size=50%><mspace=1em>はらから</mspace></size></voffset><space=0em>は\n既に斯様なものよ"
        },
        {
            "key": "EP12_S9000_0012",
            "value": "グォオオオオオオオオオオッ！！！！"
        },
        {
            "key": "EP12_S9000_0013",
            "value": "なんたる……なんたることを……！"
        },
        {
            "key": "EP12_S9000_0014",
            "value": "……喰らえ、喰らいつくし\n暗黒が力……その身に宿すべし！"
        },
        {
            "key": "EP12_S9000_0015",
            "value": "この――我の肉を喰らうのだ！！！！"
        },
        {
            "key": "EP12_S9000_0016",
            "value": "グォオオオオオオオオオオオオオオオッ！！！！"
        },
        {
            "key": "EP12_S9000_0017",
            "value": "ああ……ハルチカ殿……！！！"
        },
        {
            "key": "EP12_S9000_0018",
            "value": "皆の者……どうする！？\nこのままだと彼奴は……！！！"
        },
        {
            "key": "EP12_S9000_0019",
            "value": "や、やるしかないのか……！？"
        },
        {
            "key": "EP12_S9000_0020",
            "value": "うむ……如何にハルチカ様と合一しようと\n邪悪な者など放っておけぬ！！"
        },
        {
            "key": "EP12_S9000_0021",
            "value": "グォオオオオオオオオオオオオオオオッ！！！！"
        },
        {
            "key": "EP12_S9000_0022",
            "value": "フシュルルルルル……！！！"
        },
        {
            "key": "EP12_S9000_0023",
            "value": "ククク……ハハハハハハハハハハ……！\n我ヲ生ケ贄ヘト追イ落トシタ姉上トソノ一族……！"
        },
        {
            "key": "EP12_S9000_0024",
            "value": "否、世界そのものを……この手で！"
        },
        {
            "key": "EP12_S9000_0025",
            "value": "この怒りと憎しみの尽きるまで\n灰燼にせん……！"
        },
        {
            "key": "EP12_S9000_0026",
            "value": "グォオオオオオオオオオオオオオオオッ！！！！"
        }
    ]
}