{
	"scenario_text":[
		{
			"key":"EP11_S7031_0001",
			"value":"く……うう…………"
		},
		{
			"key":"EP11_S7031_0002",
			"value":"た、タクマ……だいじょ……ぶ……？"
		},
		{
			"key":"EP11_S7031_0003",
			"value":"くっ……一瞬過ぎて……わからねぇ……\nなあ、一体何が起きたってんだよ……"
		},
		{
			"key":"EP11_S7031_0004",
			"value":"ちっ……なんてやべー強さだよ……！"
		},
		{
			"key":"EP11_S7031_0005",
			"value":"いてて……たぶんだけど……アオイさんが\nオレらを一瞬で吹き飛ばしたんだと思う……"
		},
		{
			"key":"EP11_S7031_0006",
			"value":"嘘、こんなの……\nどうしてアオイさんが、こんなこと……"
		},
		{
			"key":"EP11_S7031_0007",
			"value":"くぅ……と、ともかく、これでハッキリした……"
		},
		{
			"key":"EP11_S7031_0008",
			"value":"ええ……認めたくはないけれど\nアオイは……"
		},
		{
			"key":"EP11_S7031_0009",
			"value":"僕たちの……敵……なのか！"
		},
		{
			"key":"EP11_S7031_0010",
			"value":"敵……？　いいえ、私は導きたいだけよ\nあなたたちの間違いを、正してあげたいの。でも……"
		},
		{
			"key":"EP11_S7031_0011",
			"value":"君たちは一回目だものね……\nだから、手加減してあげたの"
		},
		{
			"key":"EP11_S7031_0012",
			"value":"間違いは誰でもあるもの\nだから最初の一回は許してあげる"
		},
		{
			"key":"EP11_S7031_0013",
			"value":"でないと、何が悪かったのか\n何が間違っていたのか、気づくこともできないものね"
		},
		{
			"key":"EP11_S7031_0014",
			"value":"でも、これでわかったでしょ？\n二回目は――"
		},
		{
			"key":"EP11_S7031_0015",
			"value":"ぜっっっっっっっっったいに\n許されないってことも……！！！"
		},
		{
			"key":"EP11_S7031_0016",
			"value":"いい？　もう一度、自分勝手なことをしたら\n本気を出すからね？"
		},
		{
			"key":"EP11_S7031_0017",
			"value":"私が導く平和に、私の邪魔をする\n悪い子は……いらないのよ？"
		},
		{
			"key":"EP11_S7031_0018",
			"value":"……こんな、こんなアオイさん嫌っ！\n正気に戻って……お願い！"
		},
		{
			"key":"EP11_S7031_0019",
			"value":"あら……"
		},
		{
			"key":"EP11_S7031_0020",
			"value":"ミウちゃん、何か言った？\nそれって『二回目』になっちゃうけど？"
		},
		{
			"key":"EP11_S7031_0021",
			"value":"バカ、やめろ！　黙っとけ！！"
		},
		{
			"key":"EP11_S7031_0022",
			"value":"そう、そんな感じ。兄妹だって仲良くが一番\nわかるでしょ？　調和と規律が大事なのよ"
		},
		{
			"key":"EP11_S7031_0023",
			"value":"（な、なんて威圧感なんだ……！\n　怖くて……何も言えないなんて……！）"
		},
		{
			"key":"EP11_S7031_0024",
			"value":"ふふ……静かになったわね\nいい子たち……"
		},
		{
			"key":"EP11_S7031_0025",
			"value":"さて……！　もう行かなきゃ……\n感じるのよ……力を……"
		},
		{
			"key":"EP11_S7031_0026",
			"value":"あいつはすぐそばにいるわ……！\nサキさんを殺した、あいつらが……！！"
		},
		{
			"key":"EP11_S7031_0027",
			"value":"消えた……"
		},
		{
			"key":"EP11_S7031_0028",
			"value":"……なんだ、あれって……"
		},
		{
			"key":"EP11_S7031_0029",
			"value":"僕にわかるもんか……！"
		},
		{
			"key":"EP11_S7031_0030",
			"value":"（いや、誰にだって\n　この状況が一体何なのか、わかるわけない……！）"
		},
		{
			"key":"EP11_S7031_0031",
			"value":"けど……このままにしておいたら\n絶対にやばいことだけは……わかる"
		},
		{
			"key":"EP11_S7031_0032",
			"value":"アオイさんは、どこに行っちゃったの？"
		},
		{
			"key":"EP11_S7031_0033",
			"value":"……おそらく、絶大な力を手に入れるために\n主のもとに向かったんだと思う"
		},
		{
			"key":"EP11_S7031_0034",
			"value":"主がどこにいるか、わかるのか？"
		},
		{
			"key":"EP11_S7031_0035",
			"value":"そういえば、レナモンはミユキがいるところも\n知ってるって言ってたよね……！"
		},
		{
			"key":"EP11_S7031_0036",
			"value":"ああ。神社だ\nあそこの祠の地下に、主とミユキはいる"
		},
		{
			"key":"EP11_S7031_0037",
			"value":"まずいな……あの口ぶりだと、アオイくんは\nミユキくん共々、ヤツを倒すつもりだぞ"
		},
		{
			"key":"EP11_S7031_0038",
			"value":"ミユキ共々って……"
		},
		{
			"key":"EP11_S7031_0039",
			"value":"それってつまり……\nオレたちは元の世界に戻れなくなるってことか！？"
		},
		{
			"key":"EP11_S7031_0040",
			"value":"うそっ！？"
		},
		{
			"key":"EP11_S7031_0041",
			"value":"こうしちゃいられねえ！\nすぐにプルートモンを追わねーと！"
		},
		{
			"key":"EP11_S7031_0042",
			"value":"う、うん……"
		},
		{
			"key":"EP11_S7031_0043",
			"value":"（まだ、心の準備なんてできていないけど……\n　決戦の場に突入するしかないみたいだ）"
		},
		{
			"key":"EP11_S7031_0044",
			"value":"いよいよ……最後の戦いになるかもしれないね"
		},
		{
			"key":"EP11_S7031_0045",
			"value":"ああ。ミユキを助け出せるかどうかも\nプルートモンを止められるかどうかにかかってる……！"
		},
		{
			"key":"EP11_S7031_0046",
			"value":"あ……ねえ！　ジジモンたちはどうするの？\nこのまま放ってはおけないよ？"
		},
		{
			"key":"EP11_S7031_0047",
			"value":"そうよね……\n一度校舎に戻って、態勢を整えたらどうかしら？"
		},
		{
			"key":"EP11_S7031_0048",
			"value":"ああ、そうしたほうがいいかもしれん\n少し、気持ちの整理も必要だろうしな"
		},
		{
			"key":"EP11_S7031_0049",
			"value":"チビ共の様子も、見といたほうがいいだろうしな"
		},
		{
			"key":"EP11_S7031_0050",
			"value":"うん……！\nタクマも、それでいいよね？"
		},
		{
			"key":"EP11_S7031_0051",
			"value":"あ、ああ……そうしよう"
		},
		{
			"key":"EP11_S7031_0052",
			"value":"（正直、僕はまだ戸惑っていた）"
		},
		{
			"key":"EP11_S7031_0053",
			"value":"（突然立ちふさがったアオイさんを\n　どうすればいいのか……）"
		},
		{
			"key":"EP11_S7031_0054",
			"value":"（次に会った時、本当に倒すのか？　倒せるのか？\n　プルートモン――いいや、アオイさんを！）"
		},
		{
			"key":"EP11_S7031_0055",
			"value":"（僕らは、いったい……！）"
		}
	]
}
