{
	"scenario_text":[
		{
			"key":"EP10_S7610_0002",
			"value":"うん……僕たちも、シュウジさんやリョウの\n 幻を見せられて、すごく動揺した"
		},
		{
			"key":"EP10_S7610_0003",
			"value":"だから、ミウやシャコモンの気持ちはわかるよ\n 幻だってわかってても、嫌だったよね"
		},
		{
			"key":"EP10_S7610_0004",
			"value":"だからこそ、シャコモンはミウのそばにいてよ\n 僕もアグモンがいてくれて本当に助かったから"
		},
		{
			"key":"EP10_S7610_0005",
			"value":"それは……もちろんよ！\n ミウのことは、私が見てるから……！"
		},
		{
			"key":"EP10_S7610_0006",
			"value":"だから、皆を探すのはタクマたちに任せるわね"
		},
		{
			"key":"EP10_S7610_0007",
			"value":"ミウが落ち着くまで、私たちはここにいるわ\n だから皆を探すのはタクマたちに任せるわね"
		}
	]
}
