{
	"scenario_text":[
		{
			"key":"EP01_S0324_0001",
			"value":"タクマ……なんか空気が重いよ～\nここは何だ？？"
		},
		{
			"key":"EP01_S0324_0002",
			"value":"ここはトイレだよ\n用を足したり……って、今はそれよりも……"
		},
		{
			"key":"EP01_S0324_0003",
			"value":"さすがに救急箱は\nこんなところにはないか……"
		},
		{
			"key":"EP01_S0324_0004",
			"value":"同じのがいくつもあるんだな～"
		},
		{
			"key":"EP01_S0324_0005",
			"value":"それにしても、この便器とか……\n古めかしい感じがする"
		},
		{
			"key":"EP01_S0324_0006",
			"value":"これ、どうやって使うんだ？"
		},
		{
			"key":"EP01_S0324_0007",
			"value":"ああ、用が済んだら水を流すんだよ"
		},
		{
			"key":"EP01_S0324_0008",
			"value":"……"
		},
		{
			"key":"EP01_S0324_0009",
			"value":"あ！　水が流れた！"
		},
		{
			"key":"EP01_S0324_0010",
			"value":"……大丈夫そうだね\nトイレは問題なく使えるかな"
		},
		{
			"key":"EP01_S0324_0011",
			"value":"だけど……学校がこんなにボロボロなのに\nどうして使えるんだろう……"
		},
		{
			"key":"EP01_S0324_0012",
			"value":"（掃除している誰かがいるのか……？\n　いや、そんな人がいるとは思えないけど）"
		},
		{
			"key":"EP01_S0324_0013",
			"value":"（救急箱を持って早くラブラモンのところへ行こう！）"
		},
		{
			"key":"EP01_S0324_0014",
			"value":"トイレか～変なところだな～\nベタベタする～"
		},
		{
			"key":"EP01_S0324_0015",
			"value":"（アグモン、何か気になっているのかな？\n　カメラで試しに撮ってみるか？）"
		},
		{
			"key":"EP01_S0324_0016",
			"value":"……"
		},
		{
			"key":"EP01_S0324_0017",
			"value":"……何をやっているんだ僕は？\n今はそれどころじゃないのに……"
		}
	]
}
