{
	"scenario_text":[
		{
			"key":"EP07_S1325_0001",
			"value":"やはり、ここは敵の拠点で\n間違いないように思う"
		},
		{
			"key":"EP07_S1325_0002",
			"value":"ケモノの気配や痕跡を数多く感じる"
		},
		{
			"key":"EP07_S1325_0003",
			"value":"アルケニモンも、殺されるまでは\nここを出入りしていたのだろうな……"
		},
		{
			"key":"EP07_S1325_0004",
			"value":"……アルケニモン"
		},
		{
			"key":"EP07_S1325_0005",
			"value":"（アルケニモンが僕たちにしたことは\n　決して許せるものじゃない）"
		},
		{
			"key":"EP07_S1325_0006",
			"value":"（だけど死にたくないって叫びながら\n　やられてしまったのを見ると……）"
		},
		{
			"key":"EP07_S1325_0007",
			"value":"タクマ、アルケニモンに同情しているのか？"
		},
		{
			"key":"EP07_S1325_0008",
			"value":"う、うん、少しね"
		},
		{
			"key":"EP07_S1325_0009",
			"value":"……その優しさは美点だ\n大事にするといい"
		},
		{
			"key":"EP07_S1325_0010",
			"value":"……ファルコモン"
		},
		{
			"key":"EP07_S1325_0011",
			"value":"恐らくここが敵の拠点で間違いないだろう\n気を抜くなよ"
		}
	]
}
