{
	"scenario_text":[
		{
			"key":"EP02_S0090_0001",
			"value":"や、やった……\nあんな強そうなヤツをやっつけたぞ！！"
		},
		{
			"key":"EP02_S0090_0002",
			"value":"す、すごいよ、みんな……！"
		},
		{
			"key":"EP02_S0090_0003",
			"value":"一体、どーなってんの！？"
		},
		{
			"key":"EP02_S0090_0004",
			"value":"色々、わけがあってね……"
		},
		{
			"key":"EP02_S0090_0005",
			"value":"お前らだって、そいつら……"
		},
		{
			"key":"EP02_S0090_0006",
			"value":"ああ、こっちも色々あって"
		},
		{
			"key":"EP02_S0090_0007",
			"value":"この子、ロップモンとはすっかりお友達なの"
		},
		{
			"key":"EP02_S0090_0008",
			"value":"……僕には懐いてないようだけどね"
		},
		{
			"key":"EP02_S0090_0009",
			"value":"シュウジさんが\nこの子に辛く当たるからだよ～"
		},
		{
			"key":"EP02_S0090_0010",
			"value":"うぅ……"
		},
		{
			"key":"EP02_S0090_0011",
			"value":"こんなに可愛いのに……"
		},
		{
			"key":"EP02_S0090_0012",
			"value":"ふふ……フハハハハ！"
		},
		{
			"key":"EP02_S0090_0014",
			"value":"えっ……！？\nう、うわあああ！"
		},
		{
			"key":"EP02_S0090_0101",
			"value":"ハハハ……ガフッ！　ゴホッ、ゴホッ"
		},
		{
			"key":"EP02_S0090_0102",
			"value":"あー……くそ、なかなかやるじゃねーか"
		},
		{
			"key":"EP02_S0090_0103",
			"value":"そんな！　あれだけやってまだ動けるのか！？"
		},
		{
			"key":"EP02_S0090_0104",
			"value":"こいつめちゃくちゃ頑丈だよ～！"
		},
		{
			"key":"EP02_S0090_0105",
			"value":"くっ！　だが、諦めるわけには……！"
		},
		{
			"key":"EP02_S0090_0106",
			"value":"うぅ～……アオイは私が守るんだからぁ！"
		},
		{
			"key":"EP02_S0090_0107",
			"value":"お前ら……そんなボロボロなのに"
		},
		{
			"key":"EP02_S0090_0108",
			"value":"戦おうと、してくれるのね……"
		},
		{
			"key":"EP02_S0090_0109",
			"value":"（いや、本当はもう限界以上まで出し尽くしたはずだ）"
		},
		{
			"key":"EP02_S0090_0110",
			"value":"（これ以上は、もう……）"
		},
		{
			"key":"EP02_S0090_0111",
			"value":"チ……この数相手じゃ、分が悪いか"
		},
		{
			"key":"EP02_S0090_0112",
			"value":"あ……逃げた、のか？"
		},
		{
			"key":"EP02_S0090_0113",
			"value":"た、助かったぁ……"
		},
		{
			"key":"EP02_S0090_0114",
			"value":"（なんとか生き残れたんだな、僕たち）"
		},
		{
			"key":"EP02_S0090_Q1",
			"value":"（とりあえず……）"
		},
		{
			"key":"EP02_S0090_Q1_A1",
			"value":"ここから離れよう"
		},
		{
			"key":"EP02_S0090_Q1_A2",
			"value":"ヤツを追おう"
		},
		{
			"key":"EP02_S0090_Q1_A3",
			"value":"少し休もう"
		},
		{
			"key":"EP02_S0090_0115",
			"value":"みんな、疲れてるだろうけど\nまずはここから離れよう"
		},
		{
			"key":"EP02_S0090_0116",
			"value":"ここが安全だって決まったわけじゃないんだ……！"
		},
		{
			"key":"EP02_S0090_0117",
			"value":"うぁ～、そりゃそうだけど\nまだちょっとムリだよ～！"
		},
		{
			"key":"EP02_S0090_0118",
			"value":"ヤツを追おうか。脅威は早いうちに消さないと"
		},
		{
			"key":"EP02_S0090_0119",
			"value":"ごめん、タクマ～……\nボクもう、疲れちゃったよ～"
		},
		{
			"key":"EP02_S0090_0120",
			"value":"俺も、限界だ……\nすまない……"
		},
		{
			"key":"EP02_S0090_0121",
			"value":"今すぐなんて動けるワケないでしょ！？\nなに考えてんのよ！"
		},
		{
			"key":"EP02_S0090_0122",
			"value":"うん……そうだよね\nごめん……"
		},
		{
			"key":"EP02_S0090_0123",
			"value":"みんな、早く安全な場所に帰りたいだろうけど\n少し休ませて……立つのも、しんどい"
		},
		{
			"key":"EP02_S0090_0124",
			"value":"あー、うん。全然ヘーキだよ\nあきらかにへとへとだもんね……"
		},
		{
			"key":"EP02_S0090_0125",
			"value":"まぁ、さすがにこの状況で\n文句なんかいわねーよ……"
		},
		{
			"key":"EP02_S0090_0126",
			"value":"ありがとう……少し休んだら\nすぐ帰るから……"
		},
		{
			"key":"EP02_S0090_0127",
			"value":"ねぇ……\n教授は、どうなったの……？"
		},
		{
			"key":"EP02_S0090_0128",
			"value":"うっ……"
		},
		{
			"key":"EP02_S0090_0129",
			"value":"（言いにくくて、言うのを躊躇ってるうちに\n　先に言われちゃった）"
		},
		{
			"key":"EP02_S0090_0130",
			"value":"お、おい、見ろよ……下"
		},
		{
			"key":"EP02_S0090_0131",
			"value":"あ……霧が"
		},
		{
			"key":"EP02_S0090_0061",
			"value":"うぅぅ、霧……オソロシイ……"
		},
		{
			"key":"EP02_S0090_0201",
			"value":"た、タクマ……早く離れよう？\n霧は、危ないよ……"
		},
		{
			"key":"EP02_S0090_0202",
			"value":"う、うん……"
		},
		{
			"key":"EP02_S0090_0132",
			"value":"（なんて濃さだ。ただ見てるだけでも\n　背筋が震えてくる）"
		},
		{
			"key":"EP02_S0090_0133",
			"value":"……ひょっとしてさ、\n教授、まだ生きてるんじゃねーの？"
		},
		{
			"key":"EP02_S0090_0134",
			"value":"え……？"
		},
		{
			"key":"EP02_S0090_0135",
			"value":"教授が落ちたのって、霧が出る前じゃん\nだったら、あの霧には触れてねーかもじゃん"
		},
		{
			"key":"EP02_S0090_0066",
			"value":"死んだとは限んねーだろ……\nきっと……なあ、そうだろ！？"
		},
		{
			"key":"EP02_S0090_0067",
			"value":"確かに、確証はない\n死体を見たわけでもない"
		},
		{
			"key":"EP02_S0090_0068",
			"value":"しかし、仮に霧が無かったとしても\nこの高さからでは……"
		},
		{
			"key":"EP02_S0090_0136",
			"value":"そんなのわかんねーだろ！"
		},
		{
			"key":"EP02_S0090_0137",
			"value":"オレ、下に降りて捜してくる！"
		},
		{
			"key":"EP02_S0090_0138",
			"value":"待て、ミノル！"
		},
		{
			"key":"EP02_S0090_0139",
			"value":"止めんなよ！"
		},
		{
			"key":"EP02_S0090_0140",
			"value":"いや……僕も行く\nちゃんと確かめたい"
		},
		{
			"key":"EP02_S0090_0141",
			"value":"私も行くわ！\n無事な可能性があるなら助けないと！"
		},
		{
			"key":"EP02_S0090_0142",
			"value":"私も手伝う！"
		},
		{
			"key":"EP02_S0090_0143",
			"value":"き、君たちだけでは心配だな！\nぼ、僕も、い、引率しよう！"
		},
		{
			"key":"EP02_S0090_0144",
			"value":"お、オレも行くからな！"
		},
		{
			"key":"EP02_S0090_0145",
			"value":"わかった……\nみんなで教授を捜しに行こう！"
		}
	]
}
