{
	"scenario_text":[
		{
			"key":"EP04_S1400_0001",
			"value":"ああ、カイト……こんな所にいたのか？"
		},
		{
			"key":"EP04_S1400_0002",
			"value":"ああ、お前たちと一緒にいるのも\n何だかその……申し訳なくてな"
		},
		{
			"key":"EP04_S1400_0003",
			"value":"カイトももう僕らの仲間なんだ、\n遠慮することなんてないよ"
		},
		{
			"key":"EP04_S1400_0004",
			"value":"そうはいかねえ。オレがあの女の正体に気づいてれば\nあんなことにはならなかったんだ"
		},
		{
			"key":"EP04_S1400_0005",
			"value":"そんなのカイトが気にすることじゃないよ\n全員無事だったんだし"
		},
		{
			"key":"EP04_S1400_0006",
			"value":"そうだぜカイト\n結果オーライだ！"
		},
		{
			"key":"EP04_S1400_0007",
			"value":"いや、あの時、一歩間違えてたら\nリョウは死んでたかもしれねえんだ"
		},
		{
			"key":"EP04_S1400_0008",
			"value":"あんな目に遭わせちまったのは\n本当に、悪かったと思ってる……"
		},
		{
			"key":"EP04_S1400_0009",
			"value":"けど、あの時オレがちゃんと\nアイツの正体を見破ってれば……"
		},
		{
			"key":"EP04_S1400_0010",
			"value":"そうすりゃ、あんなことには……"
		},
		{
			"key":"EP04_S1400_0011",
			"value":"それこそ、カイト１人のせいなんかじゃないよ"
		},
		{
			"key":"EP04_S1400_0012",
			"value":"すっかり騙された僕たちだって悪いんだ\n誰もカイトを責めたりなんてしないよ"
		},
		{
			"key":"EP04_S1400_0013",
			"value":"誰も責めなくたって、\nオレが納得いかねえ！"
		},
		{
			"key":"EP04_S1400_0014",
			"value":"オレはこれまでもずっと、自分勝手に\n好きなようにやってきた"
		},
		{
			"key":"EP04_S1400_0015",
			"value":"でもそれは、全て自分で落とし前を付ける\n自信があったからだ……"
		},
		{
			"key":"EP04_S1400_0016",
			"value":"オレが巻き込んでいながら、あの場じゃ、\nオレは何の役にも立てなかった……"
		},
		{
			"key":"EP04_S1400_0017",
			"value":"クソっ、自分で自分が許せねぇ！"
		},
		{
			"key":"EP04_S1400_0018",
			"value":"だから、そこはカイトのせいじゃねーって！\nあんなの、どうしようもねーだろ！？"
		},
		{
			"key":"EP04_S1400_0019",
			"value":"そうだよ……不可抗力すぎる"
		},
		{
			"key":"EP04_S1400_0020",
			"value":"それでも……謝りたかったんだ\nもっとできることがあったかもしれねぇって……"
		},
		{
			"key":"EP04_S1400_0021",
			"value":"だから……すまなかった"
		},
		{
			"key":"EP04_S1400_0022",
			"value":"（カイトって、突っ走ってばっかりだと\n　思ってたけど）"
		},
		{
			"key":"EP04_S1400_0023",
			"value":"（本当は、正義感が強くていいやつだし\n　案外素直で、実は常識的なとこもあるんだよな……）"
		},
		{
			"key":"EP04_S1400_Q1",
			"value":"（僕も、カイトに何か言わないと……！）"
		},
		{
			"key":"EP04_S1400_Q1_A1",
			"value":"いいやつだな"
		},
		{
			"key":"EP04_S1400_Q1_A2",
			"value":"案外素直だよな"
		},
		{
			"key":"EP04_S1400_Q1_A3",
			"value":"実は常識あるよな"
		},
		{
			"key":"EP04_S1400_0028",
			"value":"いいやつだな"
		},
		{
			"key":"EP04_S1400_0029",
			"value":"カイトって、実はいいやつだよな"
		},
		{
			"key":"EP04_S1400_0030",
			"value":"なんだよ急に？"
		},
		{
			"key":"EP04_S1400_0031",
			"value":"だって、筋が通らないって思ったから\n謝ってくれたんだろ？"
		},
		{
			"key":"EP04_S1400_0032",
			"value":"それに、なんだかんだ言って\n僕らのこと、心配してくれてるから"
		},
		{
			"key":"EP04_S1400_0033",
			"value":"なんか、いいやつだよなーと思って"
		},
		{
			"key":"EP04_S1400_0034",
			"value":"別に……オレはただ\nこっちの事情に巻き込むわけにはいかねぇって……"
		},
		{
			"key":"EP04_S1400_0035",
			"value":"そう言ってるだけだ"
		},
		{
			"key":"EP04_S1400_0036",
			"value":"ったく、素直じゃねーな"
		},
		{
			"key":"EP04_S1400_0037",
			"value":"案外素直だよな"
		},
		{
			"key":"EP04_S1400_0038",
			"value":"カイトって、案外素直なところあるよな"
		},
		{
			"key":"EP04_S1400_0039",
			"value":"ああ……？\nなんだそれ、気持ちわりーこと言うな"
		},
		{
			"key":"EP04_S1400_0040",
			"value":"そうだぜタクマ\nこいつの場合は、単にアホなだけだからな"
		},
		{
			"key":"EP04_S1400_0041",
			"value":"いや、お前に言われたくねーよ"
		},
		{
			"key":"EP04_S1400_0042",
			"value":"（とか何とか言って\n　ドラクモンの言葉にはいつも耳を貸してるし）"
		},
		{
			"key":"EP04_S1400_0043",
			"value":"（素直なところ、あると思うけどなぁ）"
		},
		{
			"key":"EP04_S1400_0044",
			"value":"（あんまり言うと、もっと怒られそうだから\n　やめとこう……）"
		},
		{
			"key":"EP04_S1400_0045",
			"value":"実は常識あるよな"
		},
		{
			"key":"EP04_S1400_0046",
			"value":"カイトって、実は何気に常識的なとこあるよな"
		},
		{
			"key":"EP04_S1400_0047",
			"value":"な、何だよいきなり……？"
		},
		{
			"key":"EP04_S1400_0048",
			"value":"ちょっと突っ走りやすいところあるし\n怒りっぽくて、口も悪いから誤解されやすそうだけど……"
		},
		{
			"key":"EP04_S1400_0049",
			"value":"妹のために、どうすればいいのかって\nいつも考えてるの……偉いと思うよ"
		},
		{
			"key":"EP04_S1400_0050",
			"value":"そんなんじゃ……ねぇ……！\nオレは……！"
		},
		{
			"key":"EP04_S1400_0051",
			"value":"カイト？　どうした？"
		},
		{
			"key":"EP04_S1400_0052",
			"value":"な、なんでもねーよ！"
		},
		{
			"key":"EP04_S1400_0053",
			"value":"けど……ありがとな、タクマ"
		},
		{
			"key":"EP04_S1400_0054",
			"value":"って、オレの話はいいんだよ！"
		},
		{
			"key":"EP04_S1400_0055",
			"value":"それよりタクマ、みんなちゃんと集まるんだろうな？\nオレは昼までしか、待たねーからな"
		},
		{
			"key":"EP04_S1400_0056",
			"value":"わ、わかってるって……！"
		},
		{
			"key":"EP04_S1400_0057",
			"value":"だいたいオレは、チンタラおしゃべりしてる\n場合じゃねーんだよ……！"
		},
		{
			"key":"EP04_S1400_0058",
			"value":"きゅ、急に怒り出したな……"
		},
		{
			"key":"EP04_S1400_0059",
			"value":"どうせ照れ隠しだろ\nったく、ほんと素直じゃねー"
		},
		{
			"key":"EP04_S1400_0060",
			"value":"おい、聞こえてんぞ"
		},
		{
			"key":"EP04_S1400_0061",
			"value":"マジでのんびりするつもりはねーからな\n敵のバケモノや、正体不明の霧のこともあるからな"
		},
		{
			"key":"EP04_S1400_0062",
			"value":"（確かに……カイトの言う通り\n　心配事はつきないよな）"
		},
		{
			"key":"EP04_S1400_0063",
			"value":"そうだ……そういえば何なんだ？\nあの霧から出てきた、気味の悪い手は？"
		},
		{
			"key":"EP04_S1400_0064",
			"value":"僕も気になってたんだ\nドラクモンたちは、何か知らないの？"
		},
		{
			"key":"EP04_S1400_0065",
			"value":"う～ん、そこはその、\n俺も何とも言えねーっていうか……"
		},
		{
			"key":"EP04_S1400_0066",
			"value":"知らないんだな？"
		},
		{
			"key":"EP04_S1400_0067",
			"value":"面目ない"
		},
		{
			"key":"EP04_S1400_0068",
			"value":"気にするな。お前なりにオレを、\n慰めてくれようとしたんだな。ありがとよ"
		},
		{
			"key":"EP04_S1400_0069",
			"value":"（何だかんだで、カイトとドラクモンも\n　良いコンビみたいだな……）"
		},
		{
			"key":"EP04_S1400_0200",
			"value":"しっかしよぉ、ホント、何なんだよここは……"
		},
		{
			"key":"EP04_S1400_0201",
			"value":"ワケわかんねー文字化けメールは届くし\nそのくせこっちから連絡はできねえしよぉ"
		},
		{
			"key":"EP04_S1400_0202",
			"value":"カイトにも届いてたんだ"
		},
		{
			"key":"EP04_S1400_0203",
			"value":"お前もか？"
		},
		{
			"key":"EP04_S1400_0204",
			"value":"うん……他のみんなにもね\n電波塔に行けばどうにかなると思ってたんだけど……"
		},
		{
			"key":"EP04_S1400_0205",
			"value":"くそっ、そんな状況でミウは一人ぼっちかよ\n早く助けに行ってやんねえと……！"
		},
		{
			"key":"EP04_S1400_0206",
			"value":"か、カイト！　昼までは待って、ね！？"
		},
		{
			"key":"EP04_S1400_0207",
			"value":"わかってる……ちっ"
		},
		{
			"key":"EP04_S1400_0070",
			"value":"霧から出た、気味の悪い手のこともあるし\nあんまりのんびりしてらんねぇ……"
		},
		{
			"key":"EP04_S1400_0071",
			"value":"昼までに全員集まらなかったら\nオレは、１人で行くからな"
		}
	]
}
