{
	"scenario_text":[
		{
			"key":"EP05_S1923_0002",
			"value":"大変！　私たちでみんなを守らなきゃ！"
		},
		{
			"key":"EP05_S1923_0003",
			"value":"うん！　一緒に悪いヤツを倒しちゃおう！"
		},
		{
			"key":"EP05_S1923_0004",
			"value":"ミウは元気そうだね"
		},
		{
			"key":"EP05_S1923_0005",
			"value":"もちろん！　いつだってミウは元気よ！"
		},
		{
			"key":"EP05_S1923_0006",
			"value":"シュウジとかお兄ちゃんとか\n色々とあるけど……"
		},
		{
			"key":"EP05_S1923_0007",
			"value":"でもミウは大丈夫！　強い子だもん！"
		},
		{
			"key":"EP05_S1923_0008",
			"value":"そっか……シャコモン、ミウのこと守ってあげてね"
		},
		{
			"key":"EP05_S1923_0009",
			"value":"まかせて！"
		},
		{
			"key":"EP05_S1923_0010",
			"value":"ミウは強い子だから平気よ！\n安心してね！"
		}
	]
}
