{
	"scenario_text":[
		{
			"key":"EP02_S1206_0001",
			"value":"Is there food here, Takuma?"
		},
		{
			"key":"EP02_S1206_0002",
			"value":"The professor might have some food left.\nBut I can’t find any."
		},
		{
			"key":"EP02_S1206_0003",
			"value":"It’ll be all right! There’s gotta be food\nsomewhere!"
		},
		{
			"key":"EP02_S1206_0004",
			"value":"Thanks, Agumon.\nWe’ll keep looking."
		},
		{
			"key":"EP02_S1206_0005",
			"value":"Is this food, Takuma?"
		},
		{
			"key":"EP02_S1206_0006",
			"value":"No, I don’t think we can eat that."
		},
		{
			"key":"EP02_S1206_0007",
			"value":"Oh, man..."
		},
		{
			"key":"EP02_S1206_0008",
			"value":"But we can use it for something else!\nThanks, Agumon!"
		},
		{
			"key":"EP02_S1206_0009",
			"value":"Heheh..."
		},
		{
			"key":"EP02_S1206_0010",
			"value":"Takuma, I don’t see anything here."
		},
		{
			"key":"EP02_S1206_0011",
			"value":"Well, let me think.\nI’ll check somewhere else."
		},
		{
			"key":"EP02_S1206_0012",
			"value":"Aye aye!"
		}
	]
}
