{
	"scenario_text":[
		{
			"key":"EP11_S9104_0001",
			"value":"あ、あいつらは……！"
		},
		{
			"key":"EP11_S9104_0002",
			"value":"おい、アイツはいたか！？"
		},
		{
			"key":"EP11_S9104_0003",
			"value":"いや、いない……くそぉ、あの裏切り者\nどこに行きやがった！"
		},
		{
			"key":"EP11_S9104_0004",
			"value":"ねぐらの近くにいたんだ\nまだそう遠くへは行ってないだろ"
		},
		{
			"key":"EP11_S9104_0005",
			"value":"（裏切り者？　誰のことだ？\n　いや、それよりねぐらって言ったか？）"
		},
		{
			"key":"EP11_S9104_0006",
			"value":"あいつらは乱暴者なんだ\nいつも、イタズラばっかりするんだ"
		},
		{
			"key":"EP11_S9104_0007",
			"value":"なら、襲われないように\nこのまま隠れていようか"
		},
		{
			"key":"EP11_S9104_0008",
			"value":"あ。お前、なにもんだ？"
		},
		{
			"key":"EP11_S9104_0009",
			"value":"（しまった、見つかった！）"
		},
		{
			"key":"EP11_S9104_0010",
			"value":"ん、コイツは違うな\n裏切り者じゃない"
		},
		{
			"key":"EP11_S9104_0011",
			"value":"オレ知ってるぞ！\nコイツ、ピエモン様を倒したヤツだ！"
		},
		{
			"key":"EP11_S9104_0012",
			"value":"なに！？　だったら、とりあえずぶっ倒せ！"
		},
		{
			"key":"EP11_S9104_0013",
			"value":"くっ、仕方ない\nやるぞ、アグモン！"
		},
		{
			"key":"EP11_S9104_0014",
			"value":"おうっ！"
		}
	]
}
