{
	"scenario_text":[
		{
			"key":"EP04_S1033_0001",
			"value":"あの……タクマくん\n今朝はいろいろとありがとう"
		},
		{
			"key":"EP04_S1033_0002",
			"value":"え？　僕、何かしたっけ？"
		},
		{
			"key":"EP04_S1033_0003",
			"value":"私が落ち込んでるの、サキさんや\nラブラモンたちと一緒に励ましてくれたでしょ？"
		},
		{
			"key":"EP04_S1033_0004",
			"value":"私……あんなに泣いちゃって\nちょっと恥ずかしかったな"
		},
		{
			"key":"EP04_S1033_0005",
			"value":"気にすることないよ\n落ち込んでたのは、僕も一緒だし"
		},
		{
			"key":"EP04_S1033_0006",
			"value":"ただ、今はやれることをやらなきゃって\n思ってるだけだから"
		},
		{
			"key":"EP04_S1033_0007",
			"value":"そうね。今は、ミウちゃんを助けることが\n第一だものね"
		},
		{
			"key":"EP04_S1033_0008",
			"value":"うん"
		},
		{
			"key":"EP04_S1033_0009",
			"value":"ところで、昨日テントモンがミウちゃんは\nキラキラしたところに逃げたって言ってたけど……"
		},
		{
			"key":"EP04_S1033_0010",
			"value":"あれは遊園地のことで、合ってる……のよね？"
		},
		{
			"key":"EP04_S1033_0011",
			"value":"え、どうして？"
		},
		{
			"key":"EP04_S1033_0012",
			"value":"ラブラモンやアグモンたちの言うことって\n少し独特な時があるから、心配になっちゃって"
		},
		{
			"key":"EP04_S1033_0013",
			"value":"（確かに、アグモンもたまに\n　よくわからないこと言ってたりするもんな）"
		},
		{
			"key":"EP04_S1033_0014",
			"value":"大丈夫、間違いないよ\n電波塔から見たときに、観覧車みたいなのがあったし"
		},
		{
			"key":"EP04_S1033_0015",
			"value":"そう……そうね！\n私、少し心配しすぎてたみたい"
		},
		{
			"key":"EP04_S1033_0016",
			"value":"遊園地までは、まだまだ距離があるのかしら"
		},
		{
			"key":"EP04_S1033_0017",
			"value":"そうだなぁ……\nまだそれらしいものは全然見えないからなぁ"
		},
		{
			"key":"EP04_S1033_0018",
			"value":"到着まで、まだだいぶ\nかかるかもしれないってことよね"
		},
		{
			"key":"EP04_S1033_0019",
			"value":"でも、方角は間違ってないはずなんだし\n大丈夫よね……！"
		},
		{
			"key":"EP04_S1033_0020",
			"value":"大変かもしれないけど、頑張って\nミウちゃんを捜さないと……ね"
		},
		{
			"key":"EP04_S1033_0021",
			"value":"出発まで、タクマくんも\nしっかり休んでね"
		}
	]
}
