{
	"scenario_text":[
		{
			"key":"EP12_S4051_0001",
			"value":"カイト\nもうやめよう"
		},
		{
			"key":"EP12_S4051_0002",
			"value":"僕はカイトに、世界を滅ぼさせたりしない\nそれがカイトのためだって信じてる"
		},
		{
			"key":"EP12_S4051_0003",
			"value":"ふざけんじゃねー！\nそれのどこがオレのためだ！"
		},
		{
			"key":"EP12_S4051_0004",
			"value":"世界を守る？　バカバカしい！\n結局テメーらが死にたくないだけじゃねーか！"
		},
		{
			"key":"EP12_S4051_0005",
			"value":"うん、そうだよ。死にたくないし\nカイトに誰かを殺させたくもない"
		},
		{
			"key":"EP12_S4051_0006",
			"value":"急に別の世界に迷い込んで\nたくさんの理不尽な目に遭って"
		},
		{
			"key":"EP12_S4051_0007",
			"value":"それでも一緒に乗り越えてきたじゃないか\n僕は、カイトを仲間だって思ってる"
		},
		{
			"key":"EP12_S4051_0008",
			"value":"仲間なんかじゃない！！\nオレはテメーらも何もかも、全て潰すんだ！"
		},
		{
			"key":"EP12_S4051_0009",
			"value":"仲間だよ\nどんな風になったって見捨てたりしない"
		},
		{
			"key":"EP12_S4051_0010",
			"value":"本当におめでたいヤツだな！\nオレはテメーを殺そうとしたんだぞ！"
		},
		{
			"key":"EP12_S4051_0011",
			"value":"でもその前には、僕たちをずっと\n仲間として助けてくれたよね？"
		},
		{
			"key":"EP12_S4051_0012",
			"value":"それは……\nテメーらと一緒にミウがいたから！"
		},
		{
			"key":"EP12_S4051_0013",
			"value":"違うよ。カイト自身が、ミウじゃなくて\n僕たちにしてくれたことだ"
		},
		{
			"key":"EP12_S4051_0014",
			"value":"カイトは僕たちを\nたくさん助けてくれたんだ"
		},
		{
			"key":"EP12_S4051_0015",
			"value":"冷静に周りを見て、次にどうしたらいいか\n考えて意見を出してくれた"
		},
		{
			"key":"EP12_S4051_0016",
			"value":"ドラクモンと一緒に、僕たちを\n守るために戦ってくれた！"
		},
		{
			"key":"EP12_S4051_0017",
			"value":"カイトは頼りになる仲間だった\nだから僕たちだって、カイトに頼られたかったよ！"
		},
		{
			"key":"EP12_S4051_0018",
			"value":"な……"
		},
		{
			"key":"EP12_S4051_0019",
			"value":"ミウがいなくなって、つらくて苦しかった時\nううん、それだけじゃない"
		},
		{
			"key":"EP12_S4051_0020",
			"value":"もっと些細なことでもいい、なんだって\n頼ってくれてよかったんだ"
		},
		{
			"key":"EP12_S4051_0021",
			"value":"カイト、もうやめよう\nミウがいなくなった過去は変えられないけど"
		},
		{
			"key":"EP12_S4051_0022",
			"value":"それでもカイトは、一人じゃないんだ"
		},
		{
			"key":"EP12_S4051_0023",
			"value":"……バカ言うな"
		},
		{
			"key":"EP12_S4051_0024",
			"value":"カイト……！"
		},
		{
			"key":"EP12_S4051_0025",
			"value":"何もかも今更だ！"
		},
		{
			"key":"EP12_S4051_0026",
			"value":"オレはドラクモンを犠牲に\n復讐の力を手に入れたんだからな！"
		},
		{
			"key":"EP12_S4051_0027",
			"value":"あ……"
		},
		{
			"key":"EP12_S4051_0028",
			"value":"今更……引き下がれねーんだよぉぉぉ！！！"
		}
	]
}
