{
	"scenario_text":[
		{
			"key":"EP03_S1500_0001",
			"value":"さて、どうしたもんかなぁ"
		},
		{
			"key":"EP03_S1500_0002",
			"value":"やっぱり、教授のことで\nみんな沈んでるねぇ……"
		},
		{
			"key":"EP03_S1500_0003",
			"value":"これからどうすればいいのか、\nみんなわかんなくなっちゃったからな……"
		},
		{
			"key":"EP03_S1500_0004",
			"value":"子供だけで、大人がいなくなるのは、\n色々大変なんだ……"
		},
		{
			"key":"EP03_S1500_0005",
			"value":"これから、かぁ……\nう～ん、どうなんだろうね？"
		},
		{
			"key":"EP03_S1500_0006",
			"value":"そもそも、今のタクマたちが\nどんなコトになってるのか……"
		},
		{
			"key":"EP03_S1500_0007",
			"value":"ボクにはまだ\nちゃんとわかってないんだよな～"
		},
		{
			"key":"EP03_S1500_0008",
			"value":"そうか……今のぼくたちの状況か……"
		},
		{
			"key":"EP03_S1500_0009",
			"value":"う～ん、改めてアグモンたちに\nそれを説明しようと思うと、難しいな……"
		},
		{
			"key":"EP03_S1500_Q1",
			"value":"ようするに今のぼくたちは……"
		},
		{
			"key":"EP03_S1500_Q1_A1",
			"value":"ある種の試練を受けてる"
		},
		{
			"key":"EP03_S1500_Q1_A2",
			"value":"最悪な世界に来てしまった"
		},
		{
			"key":"EP03_S1500_Q1_A3",
			"value":"まだ、何とも言えないな"
		},
		{
			"key":"EP03_S1500_0010",
			"value":"ある種の試練を受けてるんだ、\nぼくはそう思う"
		},
		{
			"key":"EP03_S1500_0011",
			"value":"試練……？"
		},
		{
			"key":"EP03_S1500_0012",
			"value":"辛いこともあるけど、\nそれを乗り越えればきっと道は拓ける……"
		},
		{
			"key":"EP03_S1500_0013",
			"value":"ぼくはそう信じてる"
		},
		{
			"key":"EP03_S1500_0014",
			"value":"わ～、なんかカッコいい～！\nさっすがタクマだ～！"
		},
		{
			"key":"EP03_S1500_0015",
			"value":"（何かの受け売りだけどね……これ）"
		},
		{
			"key":"EP03_S1500_0016",
			"value":"最悪な世界に来てしまった……\n正直な感想を言うと、その一言だな"
		},
		{
			"key":"EP03_S1500_0017",
			"value":"教授も死ぬし、変な怪物に狙われるし……\nぼくたちだって、命が幾つあっても足りない"
		},
		{
			"key":"EP03_S1500_0018",
			"value":"最悪……なんだ……\nボクの世界……"
		},
		{
			"key":"EP03_S1500_0019",
			"value":"あ、うん……そうだな、ゴメン"
		},
		{
			"key":"EP03_S1500_0020",
			"value":"どうなんだろう……\nまだ、何とも言えないな"
		},
		{
			"key":"EP03_S1500_0021",
			"value":"危険だってのは確かだよ？\nでもそれだけじゃない"
		},
		{
			"key":"EP03_S1500_0022",
			"value":"状況を判断するための材料が、\nまだまだゼンゼン足りないんだ……"
		},
		{
			"key":"EP03_S1500_0023",
			"value":"何がどうなってるのか、\n右も左もわからない……"
		},
		{
			"key":"EP03_S1500_0024",
			"value":"そうやって、ぐるぐるさまよってる\n段階なんだよ、まだ……"
		},
		{
			"key":"EP03_S1500_0025",
			"value":"せめて、アグモンがもっと\n色々説明してくれたらなぁ……"
		},
		{
			"key":"EP03_S1500_0026",
			"value":"ゴメンねタクマ、ボクはその……\nむつかしいコト全然わかんないんだ"
		},
		{
			"key":"EP03_S1500_0027",
			"value":"仮テキスト\n（アグモンは遠目に見える電波塔にについて質問する）"
		},
		{
			"key":"EP03_S1500_0028",
			"value":"仮テキスト\n（タクマは電波塔が気になりつつもみんなの他を探す）"
		}
	]
}
