{
	"scenario_text":[
		{
			"key":"EP10_S9111_0001",
			"value":"ここだよ"
		},
		{
			"key":"EP10_S9111_0002",
			"value":"へぇ～、いかにもな感じじゃねえか"
		},
		{
			"key":"EP10_S9111_0003",
			"value":"キュ、キュゥ……"
		},
		{
			"key":"EP10_S9111_0004",
			"value":"なんか、クネモンが滅茶苦茶ビビッてんだけど……"
		},
		{
			"key":"EP10_S9111_0005",
			"value":"ハルくん、中には入ったの？"
		},
		{
			"key":"EP10_S9111_0006",
			"value":"入ったけど、何もなかったよ"
		},
		{
			"key":"EP10_S9111_0007",
			"value":"ここでグダグダしててもしょうがねえよ\n先に進もうぜ"
		},
		{
			"key":"EP10_S9111_0008",
			"value":"なんか引っかかるんだよなぁ……"
		},
		{
			"key":"EP10_S9111_0009",
			"value":"タクマー、リョウー\n早くー"
		},
		{
			"key":"EP10_S9111_0010",
			"value":"今行くー！"
		},
		{
			"key":"EP10_S9111_0011",
			"value":"ほら、行こう"
		},
		{
			"key":"EP10_S9111_0012",
			"value":"あ、ああ……"
		},
		{
			"key":"EP10_S9111_0013",
			"value":"中に何もないって……\nじゃあ、なんでクネモンはこんなビビッてんだ……？"
		}
	]
}
