{
	"SLG_partnertalk":[
		{
			"key":"PT01_S901_11_01",
			"value":"今は戦いに集中しないと・・・"
		},
		{
			"key":"PT01_S000_11_01",
			"value":"このままいけば勝てるぞ！"
		},
		{
			"key":"PT01_S000_12_01",
			"value":"どうかもう少しだけ踏ん張ってくれ！"
		},
		{
			"key":"PT01_S903_11_01",
			"value":"アオイさん、落ちついて対処しよう\nそうすれば勝てるよ"
		},
		{
			"key":"PT01_S903_11_02",
			"value":"そ、そうね……\nありがとう、冷静になるわ"
		},
		{
			"key":"PT01_S903_12_01",
			"value":"アオイさん、しっかり\nみんなで一緒に突破しよう！"
		},
		{
			"key":"PT01_S903_12_02",
			"value":"ええ、そうね\nみんなでならいけるはずよね……！"
		},
		{
			"key":"PT01_S903_13_01",
			"value":"アオイさん、僕たちでこのピンチを乗り切ろう！"
		},
		{
			"key":"PT01_S903_13_02",
			"value":"そうねタクマくん……\n私たちならやれるはず……！！"
		},
		{
			"key":"PT01_S904_11_01",
			"value":"ミノル、大丈夫いけるよ！"
		},
		{
			"key":"PT01_S904_11_02",
			"value":"そ、そうだよな……！"
		},
		{
			"key":"PT01_S904_12_01",
			"value":"……行くよミノル\n２人でなら何だってできるよ"
		},
		{
			"key":"PT01_S904_12_02",
			"value":"ああ、そうだったぜ……\nさすがオレの相棒！"
		},
		{
			"key":"PT01_S904_13_01",
			"value":"ミノル、頼りにしてるぞ"
		},
		{
			"key":"PT01_S904_13_02",
			"value":"任せろ、タクマ！\nファルコモンと一緒のオレは、頼りになる男だぜ！"
		},
		{
			"key":"PT01_S906_11_01",
			"value":"やっぱ怖いよね\nでも僕たちならきっと勝てるよ"
		},
		{
			"key":"PT01_S906_11_02",
			"value":"べ、別にビビってねーし！\nふん、オレらが勝つに決まってるだろっ"
		},
		{
			"key":"PT01_S906_12_01",
			"value":"敵もなかなかやるな……\nリョウ、油断するなよ"
		},
		{
			"key":"PT01_S906_12_02",
			"value":"それはこっちのセリフだ\nヘマして死ぬんじゃねぇぞ"
		},
		{
			"key":"PT01_S906_13_01",
			"value":"リョウ、しっかりついてこいよ！"
		},
		{
			"key":"PT01_S906_13_02",
			"value":"お前こそ、出遅れんなよ！"
		},
		{
			"key":"PT01_S905_11_01",
			"value":"落ち着いて戦えば負けない\n……そうですよね、シュウジさん？"
		},
		{
			"key":"PT01_S905_11_02",
			"value":"あ、ああ……\nみんな、気を強く持つんだ！"
		},
		{
			"key":"PT01_S905_12_01",
			"value":"シュウジさんはひとりじゃない\n僕たちがついてます！"
		},
		{
			"key":"PT01_S905_12_02",
			"value":"そう言ってもらえると心強いよ\n本当、ありがとう"
		},
		{
			"key":"PT01_S905_13_01",
			"value":"シュウジさん！\nここは気合いを入れて行きましょう！"
		},
		{
			"key":"PT01_S905_13_02",
			"value":"そうだねタクマ……\nここが勝負どころだな！"
		},
		{
			"key":"PT01_S907_11_01",
			"value":"サキ、前を向いて\nまだまだ負けちゃいない！"
		},
		{
			"key":"PT01_S907_11_02",
			"value":"そうだよね、これからだよね……！"
		},
		{
			"key":"PT01_S907_12_01",
			"value":"サキ、もうひと踏ん張りだ！\n一気に押し切ろう！"
		},
		{
			"key":"PT01_S907_12_02",
			"value":"オッケー\nさっさと終わらせちゃいましょ！"
		},
		{
			"key":"PT01_S907_13_01",
			"value":"サキ……僕たちならこの戦いを必ず勝てるだろう……ね？"
		},
		{
			"key":"PT01_S907_13_02",
			"value":"うんタクマ……あなたと２人で……\n必勝だね！！"
		},
		{
			"key":"PT01_S902_11_01",
			"value":"勝手に動くなら\n勝手に手伝うからな！"
		},
		{
			"key":"PT01_S902_11_02",
			"value":"ちっ、お節介ヤローが……"
		},
		{
			"key":"PT01_S902_12_01",
			"value":"こんなところじゃ終われない、\nだろ？　カイト！！"
		},
		{
			"key":"PT01_S902_12_02",
			"value":"当たり前だ、こんな場所で\nつまずいてらんねえ！"
		},
		{
			"key":"PT01_S902_13_01",
			"value":"カイト！\n背中は任せたぞ！！"
		},
		{
			"key":"PT01_S902_13_02",
			"value":"わかったタクマ！\nオレに任せろ！！"
		},
		{
			"key":"PT01_S908_11_01",
			"value":"ミウ……恐くないか？\n大丈夫かい？"
		},
		{
			"key":"PT01_S908_11_02",
			"value":"う、うん……ウチ……頑張るから！！"
		},
		{
			"key":"PT01_S908_12_01",
			"value":"ミウ、ここはキミに任せてもいいかな？"
		},
		{
			"key":"PT01_S908_12_02",
			"value":"うん！　ウチらの力、見せてあげる！！"
		},
		{
			"key":"PT01_S908_13_01",
			"value":"ミウ、キミがいてくれて、本当に助かるよ"
		},
		{
			"key":"PT01_S908_13_02",
			"value":"ウチもタクマさんがいてくれるから……\nだから安心して立ち向かえるんだよ！！"
		},
		{
			"key":"PT01_S911_11_01",
			"value":"教授、しっかりしてください！"
		},
		{
			"key":"PT01_S911_11_02",
			"value":"うむ、すまんなタクマくん……\nいささか弱気になっていた様だな"
		},
		{
			"key":"PT01_S911_12_01",
			"value":"教授！　一緒に頑張りましょう！！"
		},
		{
			"key":"PT01_S911_12_02",
			"value":"もちろんだタクマくん！\n我々が力を合わせれば負ける戦いなどない！"
		},
		{
			"key":"PT01_S912_11_01",
			"value":"ミユキ……平気か？　怯えてないか？\nだったら僕を信じて……頼ってくれていいよ"
		},
		{
			"key":"PT01_S912_11_02",
			"value":"ありがとうタクマさん……うん……\n今の言葉で勇気、沸いてきたかも！"
		},
		{
			"key":"PT01_S912_12_01",
			"value":"ミユキ！！\nここは僕たちでなんとかするぞ！！"
		},
		{
			"key":"PT01_S912_12_02",
			"value":"ええタクマさん、２人で凌ぎましょう！！"
		},
		{
			"key":"PT01_S004_11_01",
			"value":"アグモン、ヤバくなったら言ってくれ"
		},
		{
			"key":"PT01_S004_11_02",
			"value":"心配してくれんのか～？\nありがとうタクマ！"
		},
		{
			"key":"PT01_S004_12_01",
			"value":"こいつは……気合を入れてかからないとな！"
		},
		{
			"key":"PT01_S004_12_02",
			"value":"もっちろんだよ！　任せて！"
		},
		{
			"key":"PT01_S004_13_01",
			"value":"いくぞ、アグモン！"
		},
		{
			"key":"PT01_S004_13_02",
			"value":"お～ぅ！"
		},
		{
			"key":"PT01_S004_21_01",
			"value":"タクマ、元気だせ！"
		},
		{
			"key":"PT01_S004_21_02",
			"value":"う、うん……ありがとう、アグモン"
		},
		{
			"key":"PT01_S004_22_01",
			"value":"ボクのツメはどうかな！？"
		},
		{
			"key":"PT01_S004_22_02",
			"value":"よし、やってみよう！"
		},
		{
			"key":"PT01_S004_23_01",
			"value":"いくよ、タクマ！"
		},
		{
			"key":"PT01_S004_23_02",
			"value":"ああ！頼むぞ！"
		},
		{
			"key":"PT01_S105_11_01",
			"value":"慎重に行けば勝てる！"
		},
		{
			"key":"PT01_S105_11_02",
			"value":"ああ、任せろタクマ！"
		},
		{
			"key":"PT01_S105_12_01",
			"value":"グレイモン！\n全力で行くぞ！"
		},
		{
			"key":"PT01_S105_12_02",
			"value":"おう、わかったタクマ！"
		},
		{
			"key":"PT01_S105_21_01",
			"value":"グレイモン！\nこの状況を打開するぞ！"
		},
		{
			"key":"PT01_S105_21_02",
			"value":"タクマ、その台詞を待っていたぞ！"
		},
		{
			"key":"PT01_S120_11_01",
			"value":"よし、このまま押し切ろう！"
		},
		{
			"key":"PT01_S120_11_02",
			"value":"おー！　オイラにまかせて！"
		},
		{
			"key":"PT01_S120_12_01",
			"value":"ティラノモン、僕たちでここは決めるぞ！"
		},
		{
			"key":"PT01_S120_12_02",
			"value":"よっしゃあ！\nガンガンいくぞー！！"
		},
		{
			"key":"PT01_S120_21_01",
			"value":"どうだティラノモン？\nまだまだやれそうか？"
		},
		{
			"key":"PT01_S120_21_02",
			"value":"もちろんタクマ！\nオイラまだまだ絶好調！！"
		},
		{
			"key":"PT01_S121_11_01",
			"value":"僕たちでどうにかするぞ！"
		},
		{
			"key":"PT01_S121_11_02",
			"value":"おう、縦横無尽の動きを見せてやる！"
		},
		{
			"key":"PT01_S121_12_01",
			"value":"タスクモン！\n突破していくぞ！"
		},
		{
			"key":"PT01_S121_12_02",
			"value":"おう！　オレの力を見せてやる！！"
		},
		{
			"key":"PT01_S121_21_01",
			"value":"タスクモン、ここが勝負のしどころだ！"
		},
		{
			"key":"PT01_S121_21_02",
			"value":"わかってるってタクマ！\nカタをつけてやる！！"
		},
		{
			"key":"PT01_S203_11_01",
			"value":"メタルグレイモン！\n一緒に頑張ろう！"
		},
		{
			"key":"PT01_S203_11_02",
			"value":"よーし、それじゃ全力で行くぞ！！"
		},
		{
			"key":"PT01_S203_12_01",
			"value":"ここを凌げば勝利も見えてくる！"
		},
		{
			"key":"PT01_S203_12_02",
			"value":"そうだなタクマ、その通りだ！"
		},
		{
			"key":"PT01_S203_21_01",
			"value":"メタルグレイモン！\nやれることは全てやるぞ！"
		},
		{
			"key":"PT01_S203_21_02",
			"value":"タクマの気合い、伝わってくるぞ！"
		},
		{
			"key":"PT01_S220_11_01",
			"value":"トリケラモン、この戦い、勝てるぞ！"
		},
		{
			"key":"PT01_S220_11_02",
			"value":"ああ、オレも勝利しか信じていない！"
		},
		{
			"key":"PT01_S220_12_01",
			"value":"よーしトリケラモン、ここは冷静になる場面だ！"
		},
		{
			"key":"PT01_S220_12_02",
			"value":"当然だタクマ、\n血の気だけでは戦いには勝てないからな！"
		},
		{
			"key":"PT01_S220_21_01",
			"value":"僕たちの絆があれば……\nどんな敵にも負けない！！"
		},
		{
			"key":"PT01_S220_21_02",
			"value":"オレとタクマの絆か……\nうん、そうだな！！"
		},
		{
			"key":"PT01_S211_11_01",
			"value":"メガドラモン！\n破壊し尽くすぞ！"
		},
		{
			"key":"PT01_S211_11_02",
			"value":"破壊か！\nオレの好きな言葉だぜ！！"
		},
		{
			"key":"PT01_S211_12_01",
			"value":"徹底的に敵を痛めつける……\nメガドラモン、いいね？"
		},
		{
			"key":"PT01_S211_12_02",
			"value":"オレに打って付けの指示だな……\nわかったタクマ！！"
		},
		{
			"key":"PT01_S211_21_01",
			"value":"お前の力があれば、勝てるはずだ……\nそうだよな、メガドラモン"
		},
		{
			"key":"PT01_S211_21_02",
			"value":"ああ、アテにしてくれていいぜ、タクマ！！"
		},
		{
			"key":"PT01_S210_11_01",
			"value":"スカルグレイモン……任せてもいいのか……？"
		},
		{
			"key":"PT01_S210_11_02",
			"value":"ああ……"
		},
		{
			"key":"PT01_S210_12_01",
			"value":"スカルグレイモン……\nお前の闘争本能に期待してるぞ！"
		},
		{
			"key":"PT01_S210_12_02",
			"value":"うむ……"
		},
		{
			"key":"PT01_S210_21_01",
			"value":"俺たちがここでなんとかする……\nいいね、スカルグレイモン？"
		},
		{
			"key":"PT01_S210_21_02",
			"value":"おう……"
		},
		{
			"key":"PT01_S303_11_01",
			"value":"究極の勇者の力か……\nウォーグレイモン、行くぞ！！"
		},
		{
			"key":"PT01_S303_11_02",
			"value":"ああ、タクマ、この戦い、オレに任せてもらおう！！"
		},
		{
			"key":"PT01_S303_12_01",
			"value":"ウォーグレイモン！\nみんなを守ってくれ！！"
		},
		{
			"key":"PT01_S303_12_02",
			"value":"わかったタクマ、敵を倒してみんなを守る！！"
		},
		{
			"key":"PT01_S303_21_01",
			"value":"タクマ！\nオレの力を見せてやる！"
		},
		{
			"key":"PT01_S303_21_02",
			"value":"ウォーグレイスモン！\n期待しているぞ！！"
		},
		{
			"key":"PT01_S303_22_01",
			"value":"タクマ……お前の熱い想い……\nオレにも感じられるぞ……"
		},
		{
			"key":"PT01_S303_22_02",
			"value":"僕もだウォーグレイモン……\nお前の勇気が伝わってくる！"
		},
		{
			"key":"PT01_S319_11_01",
			"value":"ディノレクスモン、頑張ってくれ！"
		},
		{
			"key":"PT01_S319_11_02",
			"value":"もちろんだタクマ！\nここはオレがなんとかする！！"
		},
		{
			"key":"PT01_S319_12_01",
			"value":"ディノレクスモン、その獰猛さで\n敵を蹴散らしてくれ！！"
		},
		{
			"key":"PT01_S319_12_02",
			"value":"任せてくれ、タクマ！\n一気に行くぞ！！"
		},
		{
			"key":"PT01_S319_21_01",
			"value":"タクマ、手加減はなしでいいな？"
		},
		{
			"key":"PT01_S319_21_02",
			"value":"うん、全力を出し切ってくれ！！"
		},
		{
			"key":"PT01_S319_22_01",
			"value":"タクマ、敵の中核を叩くぞ！"
		},
		{
			"key":"PT01_S319_22_02",
			"value":"わかったディノレクスモン！"
		},
		{
			"key":"PT01_S320_11_01",
			"value":"ムゲンドラモン！\n敵を撃破していくぞ！！"
		},
		{
			"key":"PT01_S320_11_02",
			"value":"ああ、徹底的に潰してくれる……！！"
		},
		{
			"key":"PT01_S320_12_01",
			"value":"ムゲンドラモン……お前が負けるはずがない……\n期待しているよ！"
		},
		{
			"key":"PT01_S320_12_02",
			"value":"今からその期待に応えようじゃないか！\nここからは手加減はナシだ！！"
		},
		{
			"key":"PT01_S320_21_01",
			"value":"タクマ！\n片っ端からブチのめすぞ！"
		},
		{
			"key":"PT01_S320_21_02",
			"value":"わかったよムゲンドラモン！\nやってくれ！！"
		},
		{
			"key":"PT01_S320_22_01",
			"value":"タクマ！\nひとつ気合いを入れてくれ！"
		},
		{
			"key":"PT01_S320_22_02",
			"value":"うん！　ムゲンドラモン！\n全力で敵を倒してくれ！！"
		},
		{
			"key":"PT01_S402_11_01",
			"value":"オメガモン！\n力を合わせて頑張ろう！"
		},
		{
			"key":"PT01_S402_11_02",
			"value":"ああ、いくつもの魂が私に力を与えてくれる！\n行くぞタクマ！！"
		},
		{
			"key":"PT01_S402_12_01",
			"value":"オメガモン……行くよ！！"
		},
		{
			"key":"PT01_S402_12_02",
			"value":"ああ……戦いを終わらせるぞ、タクマ！！"
		},
		{
			"key":"PT01_S402_21_01",
			"value":"タクマ！　共にこの局面を乗り切ろう！\nそして勝利を手にする！！"
		},
		{
			"key":"PT01_S402_21_02",
			"value":"オメガモン……凄い気合いだ……\nよーし、やるぞお！！"
		},
		{
			"key":"PT01_S402_22_01",
			"value":"タクマ……お前のために、力の限り戦う！！"
		},
		{
			"key":"PT01_S402_22_02",
			"value":"オメガモン……僕たちの願いを……\n一緒に叶えよう！！"
		},
		{
			"key":"PT03_S903_11_01",
			"value":"話してる時間はないわ……"
		},
		{
			"key":"PT03_S903_12_01",
			"value":"ケガしないように、気を付けてね！"
		},
		{
			"key":"PT03_S000_11_01",
			"value":"あと少しだけ、頑張って！"
		},
		{
			"key":"PT03_S000_12_01",
			"value":"負けないで！\n君ならきっと勝てる！"
		},
		{
			"key":"PT03_S901_11_01",
			"value":"タクマくん、私たちもいるから\n無茶はしないで"
		},
		{
			"key":"PT03_S901_11_02",
			"value":"ありがとう、みんなで\nこの局面乗り切ろう！"
		},
		{
			"key":"PT03_S901_12_01",
			"value":"こんなところで終われないわ\n力を合わせて前へ進みましょう！"
		},
		{
			"key":"PT03_S901_12_02",
			"value":"うん、そうだね\n僕たちは、絶対に勝つ！"
		},
		{
			"key":"PT03_S901_13_01",
			"value":"タクマくん、一緒に頑張りましょう！"
		},
		{
			"key":"PT03_S901_13_02",
			"value":"ああ、わかった！"
		},
		{
			"key":"PT03_S901_21_01",
			"value":"混乱の元凶を断たないと……\n身勝手な連中に、鉄槌を……"
		},
		{
			"key":"PT03_S901_21_02",
			"value":"ア、アオイさん……そ、そうだね……"
		},
		{
			"key":"PT03_S904_11_01",
			"value":"ミノルくん、元気出して\nあなたに暗い顔は似合わないわ"
		},
		{
			"key":"PT03_S904_11_02",
			"value":"お、おうっ\nアオイさんの言う通りだよな！"
		},
		{
			"key":"PT03_S904_12_01",
			"value":"ミノルくん、気を付けて、慎重に行きましょう！"
		},
		{
			"key":"PT03_S904_12_02",
			"value":"わかってるって！"
		},
		{
			"key":"PT03_S904_13_01",
			"value":"ミノルくん、疲れてない？\n大丈夫？"
		},
		{
			"key":"PT03_S904_13_02",
			"value":"心配してくれてサンキュー！\nけどなんともないから！！"
		},
		{
			"key":"PT03_S904_21_01",
			"value":"ミノルくん……敵を殲滅するわ\n手伝ってちょうだい……"
		},
		{
			"key":"PT03_S904_21_02",
			"value":"あ、あっと……わ、わかったよ"
		},
		{
			"key":"PT03_S906_11_01",
			"value":"リョウくん、震えてるの？\n深呼吸して落ち着きましょう"
		},
		{
			"key":"PT03_S906_11_02",
			"value":"う、うるさい！　オレに構うなっ\n……すーはー……ふー……"
		},
		{
			"key":"PT03_S906_12_01",
			"value":"もう少しの辛抱だから、頑張りましょう！"
		},
		{
			"key":"PT03_S906_12_02",
			"value":"そーだな、ここが踏ん張りどころってやつだな！"
		},
		{
			"key":"PT03_S905_11_01",
			"value":"シュウジさん、頑張って！"
		},
		{
			"key":"PT03_S905_11_02",
			"value":"励ましの言葉、ありがとう\n何だか力が湧いてきたよ"
		},
		{
			"key":"PT03_S905_12_01",
			"value":"シュウジさん、まだ希望は残ってる……\nだから諦めないで！"
		},
		{
			"key":"PT03_S905_12_02",
			"value":"そうだな、こんなところでへこたれてちゃいけない！"
		},
		{
			"key":"PT03_S907_11_01",
			"value":"サキさん、下がっていいよ\n次は私が頑張るから"
		},
		{
			"key":"PT03_S907_11_02",
			"value":"心配してくれてありがと\nでもまだまだ頑張れるわ！"
		},
		{
			"key":"PT03_S907_12_01",
			"value":"サキさん、２人でピンチを乗り切ろうね！"
		},
		{
			"key":"PT03_S907_12_02",
			"value":"もっちろん！\nアオイちゃんとだったら、できるよ！"
		},
		{
			"key":"PT03_S902_11_01",
			"value":"それ以上、一人で無茶しないで\nもっと私達を頼ったらどうかな"
		},
		{
			"key":"PT03_S902_11_02",
			"value":"ふん……余計なお世話だ"
		},
		{
			"key":"PT03_S902_12_01",
			"value":"カイトくん、用心して……敵は強いわ"
		},
		{
			"key":"PT03_S902_12_02",
			"value":"わかってるって……\nヘマはしねえように注意する！"
		},
		{
			"key":"PT03_S908_11_01",
			"value":"ミウちゃん、大丈夫？　恐くない？"
		},
		{
			"key":"PT03_S908_11_02",
			"value":"うん……恐いは恐いけど……\nウチ、なんとかする！"
		},
		{
			"key":"PT03_S908_12_01",
			"value":"ミウちゃん、一緒に頑張りましょうね！"
		},
		{
			"key":"PT03_S908_12_02",
			"value":"もちろんだよアオイさん！"
		},
		{
			"key":"PT03_S911_11_01",
			"value":"教授、気を引き締めていきましょう！"
		},
		{
			"key":"PT03_S911_11_02",
			"value":"うむ、アオイくん\n油断は禁物だな！"
		},
		{
			"key":"PT03_S911_12_01",
			"value":"教授、大丈夫ですか？"
		},
		{
			"key":"PT03_S911_12_02",
			"value":"う、うむ……\nすまんな、心配をかけさせてしまって"
		},
		{
			"key":"PT03_S912_11_01",
			"value":"ミユキちゃん、平気？　戦える！？"
		},
		{
			"key":"PT03_S912_11_02",
			"value":"大丈夫よ、私は平気だから"
		},
		{
			"key":"PT03_S912_12_01",
			"value":"ミユキちゃん、しっかり！\nまだ戦いは終わってないから！"
		},
		{
			"key":"PT03_S912_12_02",
			"value":"ありがとう、アオイさん\nそうね、戦いはまだこれからね"
		},
		{
			"key":"PT03_S002_11_01",
			"value":"ラブラモン、どうか無理しないで……！"
		},
		{
			"key":"PT03_S002_11_02",
			"value":"心配いらないわ！\nアオイはそこで見てて！"
		},
		{
			"key":"PT03_S002_12_01",
			"value":"ラブラモン、大丈夫？\n戦えそう？"
		},
		{
			"key":"PT03_S002_12_02",
			"value":"もちろんアオイ！\n問題ないわ！！"
		},
		{
			"key":"PT03_S002_13_01",
			"value":"ラブラモン、みんなと一緒に戦いましょう！"
		},
		{
			"key":"PT03_S002_13_02",
			"value":"そうねアオイ！\nやってみるわ！"
		},
		{
			"key":"PT03_S002_21_01",
			"value":"敵から目をそらさないで！\n立ち向かうのよ、アオイ……！"
		},
		{
			"key":"PT03_S002_21_02",
			"value":"え、ええ、分かったわ……！"
		},
		{
			"key":"PT03_S002_22_01",
			"value":"アオイ、みんなを守りましょうね！"
		},
		{
			"key":"PT03_S002_22_02",
			"value":"ええラブラモン！"
		},
		{
			"key":"PT03_S002_23_01",
			"value":"アオイと一緒なら、どんなピンチも平気よ！"
		},
		{
			"key":"PT03_S002_23_02",
			"value":"私もよ、ラブラモン！"
		},
		{
			"key":"PT03_S002_31_01",
			"value":"アオイ、大丈夫？\n心が荒れているように思えるけど？"
		},
		{
			"key":"PT03_S002_31_02",
			"value":"そ、そんなことないわ……\n安心して、ラブラモン"
		},
		{
			"key":"PT03_S132_11_01",
			"value":"あなたのことを信じてる、\nだから無事に勝って！"
		},
		{
			"key":"PT03_S132_11_02",
			"value":"心配するな\nワタシの力、そこで見てるがいい"
		},
		{
			"key":"PT03_S132_12_01",
			"value":"ドーベルモン、あなたの力でみんなを助けて！"
		},
		{
			"key":"PT03_S132_12_02",
			"value":"わかったアオイ\nその願い、確かに受け取った！"
		},
		{
			"key":"PT03_S132_21_01",
			"value":"ドーベルモン、あまりムチャをしないでね"
		},
		{
			"key":"PT03_S132_21_02",
			"value":"ありがとうアオイ\n慎重に戦うよう心がける！"
		},
		{
			"key":"PT03_S221_11_01",
			"value":"ケルベロモン、用心して戦ってね！"
		},
		{
			"key":"PT03_S221_11_02",
			"value":"ああ、ワタシは常に慎重だ……\n心配するな、アオイ"
		},
		{
			"key":"PT03_S221_12_01",
			"value":"ケルベロモン、みんなで助け合って、\nピンチを乗り切りましょう！"
		},
		{
			"key":"PT03_S221_12_02",
			"value":"そうだなアオイ、チームワークが大切だな！"
		},
		{
			"key":"PT03_S221_21_01",
			"value":"この世界に平穏を取り戻しましょう……\nケルベロモン！"
		},
		{
			"key":"PT03_S221_21_02",
			"value":"わかったアオイ、全力を尽くそう！！"
		},
		{
			"key":"PT03_S327_11_01",
			"value":"アヌビモン……\n究極の力で平和に導きましょう！"
		},
		{
			"key":"PT03_S327_11_02",
			"value":"承知した……"
		},
		{
			"key":"PT03_S327_12_01",
			"value":"アヌビモン、一緒に頑張りましょう！"
		},
		{
			"key":"PT03_S327_12_02",
			"value":"ああ、アオイ……\nキミと一緒なら、ワタシも心強い"
		},
		{
			"key":"PT03_S327_21_01",
			"value":"アオイ！　しっかり敵を見定めて！\n焦りは禁物！！"
		},
		{
			"key":"PT03_S327_21_02",
			"value":"そうね、焦りは最大の敵……\nわかったわ、アヌビモン！！"
		},
		{
			"key":"PT03_S327_22_01",
			"value":"アオイ……その一途な想い……\nよく伝わってくるぞ……"
		},
		{
			"key":"PT03_S327_22_02",
			"value":"お願いアヌビモン、みんなを守って……！"
		},
		{
			"key":"PT03_S321_11_01",
			"value":"プルートモン……信じても……いいのよね？"
		},
		{
			"key":"PT03_S321_11_02",
			"value":"もちろんだアオイ……\nワタシはキミの味方だ"
		},
		{
			"key":"PT03_S321_12_01",
			"value":"プルートモン！　用心して！\n敵は侮れないわ！"
		},
		{
			"key":"PT03_S321_12_02",
			"value":"ああ、わかるよアオイ……\nあの敵は強力だ！"
		},
		{
			"key":"PT03_S321_21_01",
			"value":"アオイ、ワタシを信じて！"
		},
		{
			"key":"PT03_S321_21_02",
			"value":"ええ、プルートモン！\n頼りにしてるわ！！"
		},
		{
			"key":"PT03_S321_22_01",
			"value":"アオイ、この世界を平穏に導くには、\nあなたの願いが必要……"
		},
		{
			"key":"PT03_S321_22_02",
			"value":"わかったわプルートモン……\n強い願いね……！！"
		},
		{
			"key":"PT04_S904_11_01",
			"value":"喋ってる場合じゃねーよな……"
		},
		{
			"key":"PT04_S000_11_01",
			"value":"ありがとな、もうちょっと頑張ってくれ……！"
		},
		{
			"key":"PT04_S000_12_01",
			"value":"お前ならやれる！　いっけえええ！"
		},
		{
			"key":"PT04_S901_11_01",
			"value":"きついけど頑張ろうぜ……！"
		},
		{
			"key":"PT04_S901_11_02",
			"value":"ああ、突破しよう"
		},
		{
			"key":"PT04_S901_12_01",
			"value":"オレもいるってこと、忘れんなよ！"
		},
		{
			"key":"PT04_S901_12_02",
			"value":"頼りにしてるよ、ミノル！"
		},
		{
			"key":"PT04_S901_13_01",
			"value":"おう、行こうぜ！　タクマ！"
		},
		{
			"key":"PT04_S901_13_02",
			"value":"ああ！"
		},
		{
			"key":"PT04_S903_11_01",
			"value":"ここを突破したら、\nおいしいごはんが待ってるぜ！　ファイト！"
		},
		{
			"key":"PT04_S903_11_02",
			"value":"がんばる！　\n……って、ご飯作るの私じゃない！"
		},
		{
			"key":"PT04_S903_12_01",
			"value":"ここが頑張りどころだ！\n踏ん張ろーぜ！！"
		},
		{
			"key":"PT04_S903_12_02",
			"value":"ええ、そうね！"
		},
		{
			"key":"PT04_S903_13_01",
			"value":"２人で良いところ見せつけてやろーぜ！"
		},
		{
			"key":"PT04_S903_13_02",
			"value":"いいわよ、ミノルくん！"
		},
		{
			"key":"PT04_S906_11_01",
			"value":"超ピーンチ！　こうなったら\n２人で編み出した必殺技を……"
		},
		{
			"key":"PT04_S906_11_02",
			"value":"んなもんねーだろ！\nちっ、やってやるっ！"
		},
		{
			"key":"PT04_S906_12_01",
			"value":"ヒーローらしく、ビシっと決めちゃいましょーか！"
		},
		{
			"key":"PT04_S906_12_02",
			"value":"いいぜミノル！\nオレたちが突破口を開いてやる！"
		},
		{
			"key":"PT04_S905_11_01",
			"value":"へへっ、シュウジさん\nここでオレという秘密兵器を投入っすよ！"
		},
		{
			"key":"PT04_S905_11_02",
			"value":"今までも充分ミノルには頼ってたけど……\nありがとう、一緒に頑張ろうか"
		},
		{
			"key":"PT04_S905_12_01",
			"value":"リーダーらしく、ズバっとやっちゃってくださいな！"
		},
		{
			"key":"PT04_S905_12_02",
			"value":"な、なんだかざっくりとしたお願いだけど、\nや、やってみるよ！！"
		},
		{
			"key":"PT04_S907_11_01",
			"value":"ここでオレ、颯爽登場！"
		},
		{
			"key":"PT04_S907_11_02",
			"value":"なんかウザい！　でもありがとっ！"
		},
		{
			"key":"PT04_S907_12_01",
			"value":"サキ、思いっきりオレを\n頼ってもらっちゃいましょうか？"
		},
		{
			"key":"PT04_S907_12_02",
			"value":"はいはい、頼りにしてるわよ、ミノル"
		},
		{
			"key":"PT04_S902_11_01",
			"value":"そろそろオレの助けが恋しくなったりしない？"
		},
		{
			"key":"PT04_S902_11_02",
			"value":"いらねーよ、クソ、見てろ！"
		},
		{
			"key":"PT04_S902_12_01",
			"value":"カイト、たまには正義のヒーローを\n譲ってやってもいいんだぜ？"
		},
		{
			"key":"PT04_S902_12_02",
			"value":"いらねえっつーの！\nオレはオレのやり方でやる！！"
		},
		{
			"key":"PT04_S908_11_01",
			"value":"ミウ、大丈夫か？\nちょっと心配だぜ……"
		},
		{
			"key":"PT04_S908_11_02",
			"value":"はあ……ミノルさんに心配されちゃったよ\nうん、けどありがとうね！"
		},
		{
			"key":"PT04_S908_12_01",
			"value":"ミウ、オレと組んで\n正義のヒロインになるってのはどーだい？"
		},
		{
			"key":"PT04_S908_12_02",
			"value":"うーん、ウチのキャラと違うけど……\nまあいっか！　いいよ、ミノルさん！！"
		},
		{
			"key":"PT04_S911_11_01",
			"value":"教授？　もしかしてビビってます？"
		},
		{
			"key":"PT04_S911_11_02",
			"value":"ああ、恐怖は感じているさ……\nしかし私はそれを克服する！"
		},
		{
			"key":"PT04_S911_12_01",
			"value":"教授、頼りにしてますぜ！"
		},
		{
			"key":"PT04_S911_12_02",
			"value":"うむ、大人の責任というものを果たす……\n見ててくれ、ミノルくん！"
		},
		{
			"key":"PT04_S912_11_01",
			"value":"ミユキ！　オレのこと、アテにしててくれよな！"
		},
		{
			"key":"PT04_S912_11_02",
			"value":"わかったわミノルさん！"
		},
		{
			"key":"PT04_S912_12_01",
			"value":"ミユキ！　ここはヒーローに任せてもらおうか？"
		},
		{
			"key":"PT04_S912_12_02",
			"value":"ミノルさんがヒーロー……？\nうふっ……そうね、わかったわ！"
		},
		{
			"key":"PT04_S001_11_01",
			"value":"ファルコモン、頑張ってくれ！"
		},
		{
			"key":"PT04_S001_11_02",
			"value":" ミノルに手を出させてなるものか！"
		},
		{
			"key":"PT04_S001_12_01",
			"value":"頼むぜ、ファルコモン！"
		},
		{
			"key":"PT04_S001_12_02",
			"value":"承知！　ミノルが望むなら\n全力で応えよう！"
		},
		{
			"key":"PT04_S001_13_01",
			"value":"ファルコモンの出番だぜ"
		},
		{
			"key":"PT04_S001_13_02",
			"value":"ミノルの力が、俺の力となる\n……だから、これはミノルの力でもある！"
		},
		{
			"key":"PT04_S001_21_01",
			"value":"俺がついてるぞ、ミノル！"
		},
		{
			"key":"PT04_S001_21_02",
			"value":"サンキュー大丈夫だ、\nまだオレはやれるぜ……！"
		},
		{
			"key":"PT04_S001_22_01",
			"value":"下をむくな、ミノル\n本来のミノルはそんな臆病じゃない"
		},
		{
			"key":"PT04_S001_22_02",
			"value":"さあ、やるぞ……っつ！"
		},
		{
			"key":"PT04_S001_23_01",
			"value":"いざ、参るぞ！"
		},
		{
			"key":"PT04_S001_23_02",
			"value":"大丈夫だって！　オレとファルコモンなら！"
		},
		{
			"key":"PT04_S110_11_01",
			"value":"お前なら突破できるって信じてるぜ！"
		},
		{
			"key":"PT04_S110_11_02",
			"value":"ああ、任せておけ！"
		},
		{
			"key":"PT04_S110_12_01",
			"value":"ディアトリモン！　いいとこ見せてやろーぜ！"
		},
		{
			"key":"PT04_S110_12_02",
			"value":"そうだなミノル！"
		},
		{
			"key":"PT04_S110_21_01",
			"value":"ディアトリモン！\nオレのヒーローパワーを受け取ってくれ！"
		},
		{
			"key":"PT04_S110_21_02",
			"value":"うむ、確かに受け取ったぞ！"
		},
		{
			"key":"PT04_S208_11_01",
			"value":"ヤタガラモン！\n正義の力を見せてやれ！"
		},
		{
			"key":"PT04_S208_11_02",
			"value":"わかったミノル！"
		},
		{
			"key":"PT04_S208_12_01",
			"value":"ヤタガラモン！\nオレとお前でやってやろうぜ！"
		},
		{
			"key":"PT04_S208_12_02",
			"value":"ああ、お前の力が必要だ、ミノル！！"
		},
		{
			"key":"PT04_S208_21_01",
			"value":"そろそろケリを着けてやろーか！\nヤタガラモン！！"
		},
		{
			"key":"PT04_S208_21_02",
			"value":"うむ、頃合いといったところだな、ミノル！！"
		},
		{
			"key":"PT04_S305_11_01",
			"value":"ヴァロドゥルモン！\n究極のヒーローはオレたちだ！"
		},
		{
			"key":"PT04_S305_11_02",
			"value":"ふふ……相変わらずだな、ミノル！"
		},
		{
			"key":"PT04_S305_12_01",
			"value":"ヴァロドゥルモン！\nこーなったらいくとこまでいこーぜ！！"
		},
		{
			"key":"PT04_S305_12_02",
			"value":"ああミノル！\nキミとどこまでも！！"
		},
		{
			"key":"PT04_S305_21_01",
			"value":"ミノル！\nキミの勇気をわけてくれ！！"
		},
		{
			"key":"PT04_S305_21_02",
			"value":"ああ、ヴァロドゥルモンモン！\nいくらでもわけてやるぜ！！"
		},
		{
			"key":"PT04_S305_22_01",
			"value":"ミノル！\nキミこそ真のヒーローだ！！"
		},
		{
			"key":"PT04_S305_22_02",
			"value":"ヴァロドゥルモン……くうっ！\nお前こそヒーローだぜ！！"
		},
		{
			"key":"PT06_S906_11_01",
			"value":"やらなきゃやられるっ……！"
		},
		{
			"key":"PT06_S906_12_01",
			"value":"どーせオレのことなんてどうでもいいんだろ？\nオレのこと、みんな嫌ってるんだろ……？"
		},
		{
			"key":"PT06_S000_11_01",
			"value":"オレがついてるから、安心しな！"
		},
		{
			"key":"PT06_S000_12_01",
			"value":"頼むぜ……頑張ってくれよお……！"
		},
		{
			"key":"PT06_S901_11_01",
			"value":"いつまで戦ってんだよっ\nさっさと終わらせろよな！"
		},
		{
			"key":"PT06_S901_11_02",
			"value":"うん、頑張るよ"
		},
		{
			"key":"PT06_S901_12_01",
			"value":"仕方ねえから応援してやる！\nだからもっと気合い入れて戦えよ"
		},
		{
			"key":"PT06_S901_12_02",
			"value":"ありがとう\n心強いよ、リョウ！"
		},
		{
			"key":"PT06_S901_13_01",
			"value":"タクマ、オレがついてるからな、\n安心して戦ってくれ！！"
		},
		{
			"key":"PT06_S901_13_02",
			"value":"ありがとうリョウ！\n頼りにしてる！！"
		},
		{
			"key":"PT06_S903_11_01",
			"value":"そ、そんなに無茶すんなって\n一旦下がってもいいじゃねえか"
		},
		{
			"key":"PT06_S903_11_02",
			"value":"もしかして心配してくれてるの？\nありがとう、頑張るわ"
		},
		{
			"key":"PT06_S903_12_01",
			"value":"アオイ、ここは用心するんだ\nいいな？"
		},
		{
			"key":"PT06_S903_12_02",
			"value":"そうね、わかったわリョウくん"
		},
		{
			"key":"PT06_S904_11_01",
			"value":"ちっ、もたついてんじゃねえよ！\nああもう、手伝ってやるよ！"
		},
		{
			"key":"PT06_S904_11_02",
			"value":"わ、わりぃ……助かるよ"
		},
		{
			"key":"PT06_S904_12_01",
			"value":"ミノル！　ヒーローになるんじゃなかったのか？"
		},
		{
			"key":"PT06_S904_12_02",
			"value":"その通りだ！\nああ、やってやるよ！！"
		},
		{
			"key":"PT06_S905_11_01",
			"value":"お前が弱気だと\nこっちも不安になるんだよ、頼むぜ！"
		},
		{
			"key":"PT06_S905_11_02",
			"value":"ありがとう、気持ちが切り替えられたよ\n不安にさせてすまなかったね"
		},
		{
			"key":"PT06_S905_12_01",
			"value":"シュウジ、しっかりしてくれよな！\nお前がリーダーなんだから！！"
		},
		{
			"key":"PT06_S905_12_02",
			"value":"そうだな、リョウ\n僕がしっかりしないとな！"
		},
		{
			"key":"PT06_S907_11_01",
			"value":"おい、もっと後ろに下がれよ！\n防御は最大の攻撃って言うだろ"
		},
		{
			"key":"PT06_S907_11_02",
			"value":"それ逆だから！\nあーもう、緊張ほぐれたわよ、ありがと！"
		},
		{
			"key":"PT06_S907_12_01",
			"value":"サキ、オレと一緒に生き延びようぜ！"
		},
		{
			"key":"PT06_S907_12_02",
			"value":"あったり前でしょ、リョウ！"
		},
		{
			"key":"PT06_S907_13_01",
			"value":"サキ！　慎重にいけよ！\nあくまでも慎重にな！"
		},
		{
			"key":"PT06_S907_13_02",
			"value":"うわっ……あんたにそれ言われるなんて……\nけどそうね、そうだよね！"
		},
		{
			"key":"PT06_S902_11_01",
			"value":"お前がいちばん\n突破力あるんだから頑張ってくれよ！"
		},
		{
			"key":"PT06_S902_11_02",
			"value":"こんなもんすぐ終わらせる！\nってかお前も動けよ！"
		},
		{
			"key":"PT06_S902_12_01",
			"value":"カイト！　お前が強いのはわかってるけど、\n油断するんじゃねえぞ！"
		},
		{
			"key":"PT06_S902_12_02",
			"value":"ああ、ヘマはしない！"
		},
		{
			"key":"PT06_S908_11_01",
			"value":"ミウ、不安は引っ込めな！\n敵につけいられる！"
		},
		{
			"key":"PT06_S908_11_02",
			"value":"わかってるよお！\nウチ、絶対に負けない！"
		},
		{
			"key":"PT06_S908_12_01",
			"value":"ミウ！　ここが肝心要だ！\n気を引き締めて行こうぜ！"
		},
		{
			"key":"PT06_S908_12_02",
			"value":"うん、そうだね！\nウチ、頑張るから！！"
		},
		{
			"key":"PT06_S911_11_01",
			"value":"教授、大人のあんたがビビっててどーするんだよ！？"
		},
		{
			"key":"PT06_S911_11_02",
			"value":"す、すまないリョウくん……！"
		},
		{
			"key":"PT06_S911_12_01",
			"value":"教授！　しっかり戦って勝ってやろうぜ！"
		},
		{
			"key":"PT06_S911_12_02",
			"value":"無論だリョウくん！\n負けられない戦いなのだからな！"
		},
		{
			"key":"PT06_S912_11_01",
			"value":"ミユキ！　信じてるからな！"
		},
		{
			"key":"PT06_S912_11_02",
			"value":"ええ、リョウさん……\nありがとう！"
		},
		{
			"key":"PT06_S912_12_01",
			"value":"大丈夫か？\n不安はないか。ミユキ！？"
		},
		{
			"key":"PT06_S912_12_02",
			"value":"うん、大丈夫……\nちゃんと戦ってみせるから！"
		},
		{
			"key":"PT06_S008_31_01",
			"value":"チッ……気色悪ィ……"
		},
		{
			"key":"PT06_S008_31_02",
			"value":"………………"
		},
		{
			"key":"PT06_S008_11_01",
			"value":"なんだか、ほっとけねーじゃねえか……！"
		},
		{
			"key":"PT06_S008_11_02",
			"value":"キュー！"
		},
		{
			"key":"PT06_S008_12_01",
			"value":"……認めてやるって言ってんだろ\nお前にも覚悟があるってことを"
		},
		{
			"key":"PT06_S008_12_02",
			"value":"………………"
		},
		{
			"key":"PT06_S008_13_01",
			"value":"いくぜ、相棒！\nオレたちの本気を見せてやれ！"
		},
		{
			"key":"PT06_S008_13_02",
			"value":" ――ッ！！"
		},
		{
			"key":"PT06_S008_21_01",
			"value":"キューキューッ！！"
		},
		{
			"key":"PT06_S008_21_02",
			"value":"お前、オレを励まして……？\nああ大丈夫だ、やってやるさ"
		},
		{
			"key":"PT06_S008_22_01",
			"value":"キューキュッキューッ！！"
		},
		{
			"key":"PT06_S008_22_02",
			"value":"頑張れって？\n言われなくてもわかってるぜ！"
		},
		{
			"key":"PT06_S008_23_01",
			"value":"キューキュー！"
		},
		{
			"key":"PT06_S008_23_02",
			"value":"そうだな、クネモン！\nここが肝心な場面ってオレにもわかるぜ"
		},
		{
			"key":"PT06_S111_11_01",
			"value":"諦めんな　お前ならできるって\n根拠はねぇけどな……！"
		},
		{
			"key":"PT06_S111_11_02",
			"value":"キーキー！"
		},
		{
			"key":"PT06_S111_12_01",
			"value":"フライモン！\nしっかりしろ！　頑張れ！！"
		},
		{
			"key":"PT06_S111_12_02",
			"value":"キーキキー！"
		},
		{
			"key":"PT06_S111_21_01",
			"value":"どうしたフライモン！\nお前の力ってそんなもんか！？"
		},
		{
			"key":"PT06_S111_21_02",
			"value":"キキッキキー！"
		},
		{
			"key":"PT06_S223_11_01",
			"value":"ジュエルビーモン、アテにしてっからな！"
		},
		{
			"key":"PT06_S223_11_02",
			"value":"わかったリョウ！\n全力で戦ってやるぜ！"
		},
		{
			"key":"PT06_S223_12_01",
			"value":"オレたちでこのピンチを切り抜けるぞ！\nジュエルビーモン！"
		},
		{
			"key":"PT06_S223_12_02",
			"value":"ああ、僕とお前のコンビで逆転だ！！"
		},
		{
			"key":"PT06_S223_21_01",
			"value":"ジュエルビーモン！\nここからが見せ場だぜ！"
		},
		{
			"key":"PT06_S223_21_02",
			"value":"そうだなリョウ！\n目にもの見せてやる！！"
		},
		{
			"key":"PT06_S324_11_01",
			"value":"バンチョースティングモン！\n究極の力で敵をブチのめしてやろうぜ！"
		},
		{
			"key":"PT06_S324_11_02",
			"value":"いいぜリョウ！\nオレの誇りにかけて、敵に勝つ！！"
		},
		{
			"key":"PT06_S324_12_01",
			"value":"オレたちのプライドを見せつけてやろうぜ！\nバンチョースティングモン！"
		},
		{
			"key":"PT06_S324_12_02",
			"value":"その心意気だ、リョウ！！"
		},
		{
			"key":"PT06_S324_21_01",
			"value":"リョウ、一緒に頑張ろうぜ！"
		},
		{
			"key":"PT06_S324_21_02",
			"value":"そうだな、アテにしてるぞ\nバンチョースティングモン！"
		},
		{
			"key":"PT06_S324_22_01",
			"value":"リョウ、お前とコンビを組めて嬉しいぜ！"
		},
		{
			"key":"PT06_S324_22_02",
			"value":"オレもだバンチョースティングモン！\nお前は最高の相棒だ！！"
		},
		{
			"key":"PT05_S905_11_01",
			"value":"今は私語厳禁だ……"
		},
		{
			"key":"PT05_S905_12_01",
			"value":"放っておいてくれ！\n今は一人になりたいんだ……"
		},
		{
			"key":"PT05_S000_11_01",
			"value":"全力で立ち向かおう！"
		},
		{
			"key":"PT05_S000_12_01",
			"value":"ここは僕がしっかりしないと……"
		},
		{
			"key":"PT05_S901_11_01",
			"value":"どんな相手でも勝てないなんてことはない、\nそう信じようよ"
		},
		{
			"key":"PT05_S901_11_02",
			"value":"ええ、そうですね\n突破口はあるはずですよね"
		},
		{
			"key":"PT05_S901_12_01",
			"value":"タクマ、自分ひとりで背負う必要はないからね"
		},
		{
			"key":"PT05_S901_12_02",
			"value":"ありがとうございます\n気が楽になりました"
		},
		{
			"key":"PT05_S901_13_01",
			"value":"タクマ、アテにしているぞ！"
		},
		{
			"key":"PT05_S901_13_02",
			"value":"わかりました！\nなんとかやってみます！"
		},
		{
			"key":"PT05_S903_11_01",
			"value":"ちゃんと君をフォローするよ、\nだから冷静になるんだ"
		},
		{
			"key":"PT05_S903_11_02",
			"value":"ありがとうございます、\n気負いすぎてました……！"
		},
		{
			"key":"PT05_S903_12_01",
			"value":"この局面は君に任せてもいいかな？"
		},
		{
			"key":"PT05_S903_12_02",
			"value":"はい、もちろんです！！"
		},
		{
			"key":"PT05_S904_11_01",
			"value":"ミノル、ぼ、僕がついてるから\nしっかりするんだ……！"
		},
		{
			"key":"PT05_S904_11_02",
			"value":"心配させちゃってスンマセン、\nオレ、頑張るっす……！"
		},
		{
			"key":"PT05_S904_12_01",
			"value":"ミノル、できれば手伝ってくれないか？"
		},
		{
			"key":"PT05_S904_12_02",
			"value":"おう！　ヒーローはなんだってやるぜ！"
		},
		{
			"key":"PT05_S906_11_01",
			"value":"リョウ、生き残りたければ\n前を見るんだ！"
		},
		{
			"key":"PT05_S906_11_02",
			"value":"ううっ、ちくしょぉっ！\nやればいいんだろ、やれば！"
		},
		{
			"key":"PT05_S906_12_01",
			"value":"リョウ！\nここは君をアテにしてもよかったかな？"
		},
		{
			"key":"PT05_S906_12_02",
			"value":"ああ、任せておきなって！"
		},
		{
			"key":"PT05_S907_11_01",
			"value":"苦しい時は、いつでも言ってくれ\n僕が力になるよ"
		},
		{
			"key":"PT05_S907_11_02",
			"value":"ありがと！\nでもまだ頑張れるわ！"
		},
		{
			"key":"PT05_S907_12_01",
			"value":"サキ君、ちょっとお願いしてもいいかな？"
		},
		{
			"key":"PT05_S907_12_02",
			"value":"はいはーい！\n私でよろしければ、なんでも！"
		},
		{
			"key":"PT05_S907_13_01",
			"value":"サキ君、僕に力を貸してくれないか？"
		},
		{
			"key":"PT05_S907_13_02",
			"value":"いいわよ！\n全力で貸しちゃうから！"
		},
		{
			"key":"PT05_S902_11_01",
			"value":"カイト、一緒に協力して\nこの戦況を打破しようよ"
		},
		{
			"key":"PT05_S902_11_02",
			"value":"フン、頼りねえと思ったか？\nそりゃ誤解を与えちまったな"
		},
		{
			"key":"PT05_S902_12_01",
			"value":"カイト、すまないが力を貸してはくれないか？"
		},
		{
			"key":"PT05_S902_12_02",
			"value":"いいぜシュウジ！\nやってやろーじゃねーか！！"
		},
		{
			"key":"PT05_S908_11_01",
			"value":"ミウちゃん、僕が力になる……\n安心してくれ"
		},
		{
			"key":"PT05_S908_11_02",
			"value":"ありがとう、シュウジさん……"
		},
		{
			"key":"PT05_S908_12_01",
			"value":"ミウちゃん、一緒に力を合わせよう！"
		},
		{
			"key":"PT05_S908_12_02",
			"value":"いいよ！\nウチ、頑張る！"
		},
		{
			"key":"PT05_S911_11_01",
			"value":"教授！\n弱気じゃダメですよ！"
		},
		{
			"key":"PT05_S911_11_02",
			"value":"す、すまんシュウジくん……\nう、うむ……勇気が大切だな"
		},
		{
			"key":"PT05_S911_12_01",
			"value":"教授、作戦にご協力してはいただけませんか？"
		},
		{
			"key":"PT05_S911_12_02",
			"value":"当然だシュウジくん、共に戦おう！"
		},
		{
			"key":"PT05_S912_11_01",
			"value":"ミユキちゃん、僕がついてるから、\n勇気を振り絞るんだ"
		},
		{
			"key":"PT05_S912_11_02",
			"value":"シュウジさん……\n心配かけて、ごめんなさい"
		},
		{
			"key":"PT05_S912_12_01",
			"value":"よし、ミユキちゃん\nここは君に任せた！"
		},
		{
			"key":"PT05_S912_12_02",
			"value":"わかったわシュウジさん！"
		},
		{
			"key":"PT05_S010_31_01",
			"value":"正体がわからないような相手を信じて\n行動なんて、できるもんか！"
		},
		{
			"key":"PT05_S010_31_02",
			"value":"……"
		},
		{
			"key":"PT05_S010_11_01",
			"value":"こいつ、手強い……"
		},
		{
			"key":"PT05_S010_11_02",
			"value":"ねぇシュウジ、逃げよう？\nこのままだとボクもシュウジも死んじゃうよ……"
		},
		{
			"key":"PT05_S010_12_01",
			"value":"ロップモン！　力を貸してくれ！"
		},
		{
			"key":"PT05_S010_12_02",
			"value":"うん！　任せてよ！"
		},
		{
			"key":"PT05_S010_13_01",
			"value":"力を合わせて立ち向かおう"
		},
		{
			"key":"PT05_S010_13_02",
			"value":"なんだか胸の奥がポカポカして、力が溢れてくるよ！"
		},
		{
			"key":"PT05_S010_21_01",
			"value":"シュウジ！　頑張って！"
		},
		{
			"key":"PT05_S010_21_02",
			"value":"ああ、わかってる！"
		},
		{
			"key":"PT05_S010_22_01",
			"value":"シュウジ！　ボクに力をちょうだい！"
		},
		{
			"key":"PT05_S010_22_02",
			"value":"ロップモン！\n僕はキミの勝利を信じる！！"
		},
		{
			"key":"PT05_S010_23_01",
			"value":"ボクがシュウジを守るんだ……\nボクが！！"
		},
		{
			"key":"PT05_S010_23_02",
			"value":"ありがとうロップモン！\nけど僕も敵に立ち向かう！！"
		},
		{
			"key":"PT05_S123_11_01",
			"value":"トゥルイエモン、やれそうか？"
		},
		{
			"key":"PT05_S123_11_02",
			"value":"ああ、こっちは絶好調だよ！"
		},
		{
			"key":"PT05_S123_12_01",
			"value":"トゥルイエモン！\n頑張ってくれ！"
		},
		{
			"key":"PT05_S123_12_02",
			"value":"オッケー、シュウジ！"
		},
		{
			"key":"PT05_S123_21_01",
			"value":"トゥルイエモン、キミがこの戦いの要だ！"
		},
		{
			"key":"PT05_S123_21_02",
			"value":"わかったシュウジ！"
		},
		{
			"key":"PT05_S124_11_01",
			"value":"ウェンディモン……し、信じてもいいのか？\n君のことを……僕は……                                                                                                                                                                                                                                                                                                                                                                                                                                                                                                                                                                                           "
		},
		{
			"key":"PT05_S124_11_02",
			"value":"ぐるるるる……"
		},
		{
			"key":"PT05_S124_12_01",
			"value":"ウェンディモン、行くぞ！"
		},
		{
			"key":"PT05_S124_12_02",
			"value":"ぐる……\nぐるる……"
		},
		{
			"key":"PT05_S124_21_01",
			"value":"さあウェンディモン！\n作戦通りにやっていこう！"
		},
		{
			"key":"PT05_S124_21_02",
			"value":"ぐる、ぐるるる……"
		},
		{
			"key":"PT05_S222_11_01",
			"value":"アンティラモン、頑張ってくれ！"
		},
		{
			"key":"PT05_S222_11_02",
			"value":"ああ、シュウジ……わかってる"
		},
		{
			"key":"PT05_S222_12_01",
			"value":"作戦を遂行するぞ\nいいなアンティラモン！"
		},
		{
			"key":"PT05_S222_12_02",
			"value":"わかったシュウジ！\n指示を頼む！"
		},
		{
			"key":"PT05_S222_21_01",
			"value":"アンティラモン！\n敵をこれ以上調子に乗せるな！"
		},
		{
			"key":"PT05_S222_21_02",
			"value":"そうだなシュウジ！\nここはワタシが歯止めをかけよう！"
		},
		{
			"key":"PT05_S323_11_01",
			"value":"究極の天使の力か……\n期待しているぞ、ケルビモン！"
		},
		{
			"key":"PT05_S323_11_02",
			"value":"うむ、シュウジ……\n見ていてくれ……"
		},
		{
			"key":"PT05_S323_12_01",
			"value":"ケルビモン！\nこの世界の破壊を食い止めるぞ！"
		},
		{
			"key":"PT05_S323_12_02",
			"value":"よし……それでは行くぞ、シュウジ！"
		},
		{
			"key":"PT05_S323_21_01",
			"value":"シュウジ、遂にここまで来たな……"
		},
		{
			"key":"PT05_S323_21_02",
			"value":"ああ、長かったな、ケルビモン……\nありがとう、僕はキミに感謝する！"
		},
		{
			"key":"PT05_S323_22_01",
			"value":"シュウジ！　キミの魂の発現を見せてくれ！"
		},
		{
			"key":"PT05_S323_22_02",
			"value":"わかったケルビモン！\nうおおおおお！　これでどうだあ！"
		},
		{
			"key":"PT07_S907_11_01",
			"value":"とにかくまずは目の前の敵に集中！"
		},
		{
			"key":"PT07_S000_11_01",
			"value":"その調子！"
		},
		{
			"key":"PT07_S000_12_01",
			"value":"頑張りましょう！"
		},
		{
			"key":"PT07_S901_11_01",
			"value":"まさかここで諦めるつもり？\nタクマはそんな奴じゃないわよね"
		},
		{
			"key":"PT07_S901_11_02",
			"value":"ああ……\n僕は何度でも立ち上がるさ……！"
		},
		{
			"key":"PT07_S901_12_01",
			"value":"テンション低いわねぇ\n背筋を伸ばしてシャキッとする！"
		},
		{
			"key":"PT07_S901_12_02",
			"value":"そうだよね、\n気持ちで負けたら終わりだよね"
		},
		{
			"key":"PT07_S901_13_01",
			"value":"タクマ！　あなたのこと、信じてるから！"
		},
		{
			"key":"PT07_S901_13_02",
			"value":"ありがとうサキ！\n期待に応えられるように頑張るよ！！"
		},
		{
			"key":"PT07_S903_11_01",
			"value":"私たちは勝つ！\n他のことは考えないの！"
		},
		{
			"key":"PT07_S903_11_02",
			"value":"うん、サキさん……\n少し気が楽になったわ"
		},
		{
			"key":"PT07_S903_12_01",
			"value":"アオイちゃん、ファイト！！"
		},
		{
			"key":"PT07_S903_12_02",
			"value":"ありがとうサキさん！"
		},
		{
			"key":"PT07_S904_11_01",
			"value":"そろそろカッコいいところ見せてよね～？"
		},
		{
			"key":"PT07_S904_11_02",
			"value":"お、おうよ！\n期待して待っててくれ！"
		},
		{
			"key":"PT07_S904_12_01",
			"value":"ミノル！　ヒーローらしく活躍しちゃって！"
		},
		{
			"key":"PT07_S904_12_02",
			"value":"おうよ任せろ！\nオレがなんとかする！！"
		},
		{
			"key":"PT07_S906_11_01",
			"value":"雑魚にビビってるんじゃないわよ"
		},
		{
			"key":"PT07_S906_11_02",
			"value":"わわ、分かってるっての……！"
		},
		{
			"key":"PT07_S906_12_01",
			"value":"リョウ、大丈夫？\n頑張れそう？"
		},
		{
			"key":"PT07_S906_12_02",
			"value":"もちろん！\nお前の前でカッコ悪いとこ見せらんねーぜ！！"
		},
		{
			"key":"PT07_S906_13_01",
			"value":"リョウ！\nあんたにしかできないことってあるよね！！"
		},
		{
			"key":"PT07_S906_13_02",
			"value":"当然だって！\n今からそいつを見せてやる！"
		},
		{
			"key":"PT07_S905_11_01",
			"value":"自信持って！　頼りにしてるからね！"
		},
		{
			"key":"PT07_S905_11_02",
			"value":"不安にさせてごめんね\nもう大丈夫だよ"
		},
		{
			"key":"PT07_S905_12_01",
			"value":"シュウジさん、\nリーダーシップ、発揮しちゃっていいですよ！"
		},
		{
			"key":"PT07_S905_12_02",
			"value":"ああ、任せてくれ！"
		},
		{
			"key":"PT07_S905_13_01",
			"value":"とうとうここまできましたね、\nシュウジさん！"
		},
		{
			"key":"PT07_S905_13_02",
			"value":"ああ、君がいてくれたおかげだよ、サキ君！"
		},
		{
			"key":"PT07_S902_11_01",
			"value":"カイトが手こずるなんて珍しいわね\nサポートしよっか？"
		},
		{
			"key":"PT07_S902_11_02",
			"value":"へっ、いらねぇよ、\nオレ一人で充分だ……！"
		},
		{
			"key":"PT07_S902_12_01",
			"value":"カイト、あんたなら絶対勝てるから！\n私が保証する！"
		},
		{
			"key":"PT07_S902_12_02",
			"value":"お前のお墨付きなんていらねーよ！\nけど、サンキューな！！"
		},
		{
			"key":"PT07_S908_11_01",
			"value":"ミウちゃん、ファイト！\n私が応援してるよ！！"
		},
		{
			"key":"PT07_S908_11_02",
			"value":"うん、ありがとうサキさん！"
		},
		{
			"key":"PT07_S908_12_01",
			"value":"ミウちゃん！\nサクサクっとやっつけちゃお！"
		},
		{
			"key":"PT07_S908_12_02",
			"value":"いいよ～！\nサクサクっとだね！"
		},
		{
			"key":"PT07_S911_11_01",
			"value":"教授！　ファイト！！\nいじいじしてちゃダメだよ！"
		},
		{
			"key":"PT07_S911_11_02",
			"value":"あ、ああ……いじいじか……\nそうだな、弱気になってはいかんな"
		},
		{
			"key":"PT07_S911_12_01",
			"value":"教授、なんとなくですけど、\n敵が弱いっぽく感じません？"
		},
		{
			"key":"PT07_S911_12_02",
			"value":"ああ、私もそう感じていたところだ\nこれはチャンスかもな！"
		},
		{
			"key":"PT07_S912_11_01",
			"value":"ミユキちゃん！\n戦いって恐いけど、一緒に頑張ろ！"
		},
		{
			"key":"PT07_S912_11_02",
			"value":"ええ、そうね！"
		},
		{
			"key":"PT07_S912_12_01",
			"value":"ミユキちゃん……苦労かけてゴメンね……\nこれまで辛かったよね"
		},
		{
			"key":"PT07_S912_12_02",
			"value":"ううん、サキさんのせいじゃないから……\n悪いのは、全て敵よ！"
		},
		{
			"key":"PT07_S006_11_01",
			"value":"キツくなったら言うのよ！"
		},
		{
			"key":"PT07_S006_11_02",
			"value":"心配してくれてありがと！\n私がんばる！"
		},
		{
			"key":"PT07_S006_12_01",
			"value":"フローラモン、頑張ってね！"
		},
		{
			"key":"PT07_S006_12_02",
			"value":"もっちろん！\n任せてくれるかな？"
		},
		{
			"key":"PT07_S006_13_01",
			"value":"フローラモン、あなたと出会えて、本当によかった！"
		},
		{
			"key":"PT07_S006_13_02",
			"value":"私もそーだよ！\nサキ！！"
		},
		{
			"key":"PT07_S006_21_01",
			"value":"私、ちょうがんばる！\nだから、安心してね！"
		},
		{
			"key":"PT07_S006_21_02",
			"value":"ありがと……\nフローラモンって、超いい子だね！"
		},
		{
			"key":"PT07_S006_22_01",
			"value":"サキ、しっかりして！"
		},
		{
			"key":"PT07_S006_22_02",
			"value":"心配してくれてありがとう！\nでも大丈夫だよ！"
		},
		{
			"key":"PT07_S006_23_01",
			"value":"サキ、私に元気をくれる？"
		},
		{
			"key":"PT07_S006_23_02",
			"value":"おー！\nフローラモン、エイエイオー！！"
		},
		{
			"key":"PT07_S107_11_01",
			"value":"もうひと頑張りしてくれるかな！"
		},
		{
			"key":"PT07_S107_11_02",
			"value":"もちろん！\nまかせてまかせてー！"
		},
		{
			"key":"PT07_S107_12_01",
			"value":"ベジーモン、見てくれはアレだけど……\n接しやすいかも？"
		},
		{
			"key":"PT07_S107_12_02",
			"value":"うふふーん、嬉しい！\nよーやくアタシの良さに気付いてくれたのね！"
		},
		{
			"key":"PT07_S107_21_01",
			"value":"ベジーモン！\nいっちょやっちゃってくれる！"
		},
		{
			"key":"PT07_S107_21_02",
			"value":"ナイス丸投げ！\nやっちゃえ、やっちゃえ！"
		},
		{
			"key":"PT07_S206_11_01",
			"value":"ねえブロッサモン！\nそろそろ見せ場っぽいかも！"
		},
		{
			"key":"PT07_S206_11_02",
			"value":"アタシの大活躍の時間帯ねえ！"
		},
		{
			"key":"PT07_S206_12_01",
			"value":"ブロッサモン！\nあなた最高のパートナーだね！"
		},
		{
			"key":"PT07_S206_12_02",
			"value":"アタシもサキが大好き！"
		},
		{
			"key":"PT07_S206_21_01",
			"value":"頑張れブロッサモン！\nあなたなら負けない！"
		},
		{
			"key":"PT07_S206_21_02",
			"value":"もちろんだよ！\nアタシとサキのコンビなんだもの！"
		},
		{
			"key":"PT07_S325_11_01",
			"value":"ケレスモンメディウム、\nこの状況を変えてやりましょう！"
		},
		{
			"key":"PT07_S325_11_02",
			"value":"いいわよサキ、ワタシに任せて"
		},
		{
			"key":"PT07_S325_12_01",
			"value":"綺麗……ケレスモンメディウム……\nとっても綺麗……"
		},
		{
			"key":"PT07_S325_12_02",
			"value":"うふ……ありがとうサキ……"
		},
		{
			"key":"PT07_S325_21_01",
			"value":"サキ、頑張りましょう！"
		},
		{
			"key":"PT07_S325_21_02",
			"value":"うん、そうだね！！"
		},
		{
			"key":"PT07_S325_22_01",
			"value":"サキ、私と共に、この悪夢を終わらせましょう……"
		},
		{
			"key":"PT07_S325_22_02",
			"value":"わかったわ！\n一緒に悪夢をぶっとばそう！"
		},
		{
			"key":"PT07_S333_11_01",
			"value":"ケレスモン……\nとうとうここまでの力を手に入れたの……"
		},
		{
			"key":"PT07_S333_11_02",
			"value":"全てはワタシとサキの絆の賜……\nこれまでの歩みのなせる業だ！"
		},
		{
			"key":"PT07_S333_12_01",
			"value":"ケレスモン！\nあんな連中、ブチのめしちゃって！"
		},
		{
			"key":"PT07_S333_12_02",
			"value":"任せてもらおう、このワタシに！"
		},
		{
			"key":"PT07_S333_21_01",
			"value":"サキ……感謝だ……\nキミの真心がワタシにこの進化を与えてくれた"
		},
		{
			"key":"PT07_S333_21_02",
			"value":"私も……あなたのおかげで心が強くなれた……\nありがとう……"
		},
		{
			"key":"PT07_S333_22_01",
			"value":"サキ、戦いの終わりは近い……\nだが油断はなしだぞ"
		},
		{
			"key":"PT07_S333_22_02",
			"value":"もー、ケレスモンは心配性なんだから！\n油断とか、絶対にないない！！"
		},
		{
			"key":"PT02_S902_11_01",
			"value":"喋ってる暇があったら拳を動かすぜ"
		},
		{
			"key":"PT02_S902_12_01",
			"value":"何が来ても叩きつぶす……！\nそうするだけだ！！"
		},
		{
			"key":"PT02_S000_11_01",
			"value":"ふん、やってやろーぜ！"
		},
		{
			"key":"PT02_S000_12_01",
			"value":"本当の力ってやつを、\nヤツらにぶつけてやれ！！"
		},
		{
			"key":"PT02_S901_11_01",
			"value":"おいおい何を弱気になってやがる\nお前は諦める奴じゃねーだろ"
		},
		{
			"key":"PT02_S901_11_02",
			"value":"ああ、絶対に諦めないよ\nありがとうカイト"
		},
		{
			"key":"PT02_S901_12_01",
			"value":"戦わなきゃ守れねえ、\nお前なら分かるだろ！！"
		},
		{
			"key":"PT02_S901_12_02",
			"value":"……そうだねカイト、\nうん、吹っ切れたよ"
		},
		{
			"key":"PT02_S901_13_01",
			"value":"タクマ！\nお前の本気を見せる時が来たようだぜ！"
		},
		{
			"key":"PT02_S901_13_02",
			"value":"わかったカイト！\nやってみる！！"
		},
		{
			"key":"PT02_S901_21_01",
			"value":"タクマ！　奴らをブチのめしてやろーぜ！\n手加減はなしだ！！"
		},
		{
			"key":"PT02_S901_21_02",
			"value":"そ、そうだなカイト……"
		},
		{
			"key":"PT02_S903_11_01",
			"value":"泣きそうな顔すんな\nまだ負けたわけじゃねぇだろ"
		},
		{
			"key":"PT02_S903_11_02",
			"value":"うん……\nこれからが勝負よね……！"
		},
		{
			"key":"PT02_S903_12_01",
			"value":"アオイ、ここで一気にたたみ掛けようぜ！！"
		},
		{
			"key":"PT02_S903_12_02",
			"value":"わかったわカイトくん！！"
		},
		{
			"key":"PT02_S904_11_01",
			"value":"いつになったら本気出すんだ？\nあぁ？"
		},
		{
			"key":"PT02_S904_11_02",
			"value":"うぐぐっ、そこで見てろ！\nオレだってやるときゃやるんだ……！"
		},
		{
			"key":"PT02_S904_12_01",
			"value":"ミノル！　お前の力が必要だ！"
		},
		{
			"key":"PT02_S904_12_02",
			"value":"嬉しいこと言ってくれちゃって！\nよーし、やるぞお！！"
		},
		{
			"key":"PT02_S904_21_01",
			"value":"こっちもそうそう\n悠長にはしてられねーんだ、"
		},
		{
			"key":"PT02_S904_21_02",
			"value":"ダメだ、アイツ……\n完全に頭に血が昇ってやがるぜ"
		},
		{
			"key":"PT02_S906_11_01",
			"value":"足手まといは置いていく\nそれが嫌なら、戦いに協力するんだな"
		},
		{
			"key":"PT02_S906_11_02",
			"value":"あ、ああ！　するする！\nだからそんなこと言うなっての……！"
		},
		{
			"key":"PT02_S906_12_01",
			"value":"ビビってんじゃねーぞ、リョウ！"
		},
		{
			"key":"PT02_S906_12_02",
			"value":"んなわけねーだろ！\nふざけんなって！！"
		},
		{
			"key":"PT02_S905_11_01",
			"value":"生きるか死ぬかの瀬戸際だぜ\n勝ちに行かなくてどうする！"
		},
		{
			"key":"PT02_S905_11_02",
			"value":"君の言うことも一理あるね\nああ、勝とうカイト"
		},
		{
			"key":"PT02_S905_12_01",
			"value":"年長者らしく決めてくれよな！"
		},
		{
			"key":"PT02_S905_12_02",
			"value":"そうだなカイト！\nこれで決めてみせる！！"
		},
		{
			"key":"PT02_S907_11_01",
			"value":"何黙ってるんだよ\nらしくねぇぞ、オイ"
		},
		{
			"key":"PT02_S907_11_02",
			"value":"それ励ましてんの？　そっちこそ、らしくないっての\nでもありがと　力が湧いてきた"
		},
		{
			"key":"PT02_S907_12_01",
			"value":"サキ、いっちょ良いとこ見せてくれよ！"
		},
		{
			"key":"PT02_S907_12_02",
			"value":"珍しい、あんたがそんなこと言うなんて……\nうん、わかったわ！　良いとこ見せちゃうから！！"
		},
		{
			"key":"PT02_S908_11_01",
			"value":"ミウ、お兄ちゃんがついてるからな！\n安心しろ！！"
		},
		{
			"key":"PT02_S908_11_02",
			"value":"はいはい、わかりましたって"
		},
		{
			"key":"PT02_S908_12_01",
			"value":"ミウ、お前のためなら、\nお兄ちゃんはなんでもやるからな！！"
		},
		{
			"key":"PT02_S908_12_02",
			"value":"もう、そーゆーのはいいから！\nウチの自力をよーく見てなさい！"
		},
		{
			"key":"PT02_S908_13_01",
			"value":"ミウ、オレたち二人でここは凌ぎきるぞ！"
		},
		{
			"key":"PT02_S908_13_02",
			"value":"オッケーお兄ちゃん！\n兄妹の本気、あいつらにぶつけようね！！"
		},
		{
			"key":"PT02_S911_11_01",
			"value":"教授！　ちょっと弱気になってねーか？"
		},
		{
			"key":"PT02_S911_11_02",
			"value":"そ、そうだな……いかんいかん\n大人の私がこんなことでは！"
		},
		{
			"key":"PT02_S911_12_01",
			"value":"教授、アテにしてもいいか？"
		},
		{
			"key":"PT02_S911_12_02",
			"value":"ああもちろん、私に任せてもらおう！"
		},
		{
			"key":"PT02_S912_11_01",
			"value":"さあ、連中にお前の強さをわからせてやりな！"
		},
		{
			"key":"PT02_S912_11_02",
			"value":"そうね、わかったわ！"
		},
		{
			"key":"PT02_S912_12_01",
			"value":"頑張れ！　頑張るんだ！！"
		},
		{
			"key":"PT02_S912_12_02",
			"value":"ええ、ありがとう！"
		},
		{
			"key":"PT02_S009_11_01",
			"value":"やれるよな　ドラクモン！"
		},
		{
			"key":"PT02_S009_11_02",
			"value":"当たり前だろ！\nどんな敵でもやっつけてやる！"
		},
		{
			"key":"PT02_S009_12_01",
			"value":"ドラクモン、任せたぜ！"
		},
		{
			"key":"PT02_S009_12_02",
			"value":"おう！　わかった！！"
		},
		{
			"key":"PT02_S009_13_01",
			"value":"ドラクモン、オレたちの力で一気にぶっ潰そうぜ！！"
		},
		{
			"key":"PT02_S009_13_02",
			"value":"へへ、いいぜカイト！\nここからが俺たちの本気だ！！"
		},
		{
			"key":"PT02_S009_21_01",
			"value":"おい、カイト　どうした？\nもっとがっついていこうぜ！"
		},
		{
			"key":"PT02_S009_21_02",
			"value":"フン、始めからそのつもりだぜ！"
		},
		{
			"key":"PT02_S009_22_01",
			"value":"カイト、アテにしてるからな！"
		},
		{
			"key":"PT02_S009_22_02",
			"value":"ああ、ドラクモン！"
		},
		{
			"key":"PT02_S009_23_01",
			"value":"なあカイト、どうやって敵をぶっ潰す？"
		},
		{
			"key":"PT02_S009_23_02",
			"value":"決まってるだろ、正面突破さ！！"
		},
		{
			"key":"PT02_S009_31_01",
			"value":"カイト、俺たち最強のコンビだよな！"
		},
		{
			"key":"PT02_S009_31_02",
			"value":"当たり前だドラクモン！\nオレとお前が一番だぜ！！"
		},
		{
			"key":"PT02_S122_11_01",
			"value":"遊びは終わりだ\nそろそろ決着をつけようぜ"
		},
		{
			"key":"PT02_S122_11_02",
			"value":"だな！\n次で仕留める！"
		},
		{
			"key":"PT02_S122_12_01",
			"value":"サングルゥモン！\nやれそうか！？"
		},
		{
			"key":"PT02_S122_12_02",
			"value":"誰にものを尋ねている？\n楽勝に決まってるだろ！！"
		},
		{
			"key":"PT02_S122_21_01",
			"value":"いいかサングルゥモン！\n奴らにキツい一撃を食らわせてやれ！"
		},
		{
			"key":"PT02_S122_21_02",
			"value":"わかったカイト！\nやってやるぜ！！"
		},
		{
			"key":"PT02_S219_11_01",
			"value":"ヴァンデモン、奴らに恐怖を植え付けてやれ！"
		},
		{
			"key":"PT02_S219_11_02",
			"value":"ふふ、いいでしょう……"
		},
		{
			"key":"PT02_S219_12_01",
			"value":"どうだヴァンデモン、この戦い、いけそうか？"
		},
		{
			"key":"PT02_S219_12_02",
			"value":"カイト、あなたはこれから本当の強さを\n目の当たりにするでしょう……"
		},
		{
			"key":"PT02_S219_21_01",
			"value":"ヴァンデモン！\n敵を殲滅するぞ！"
		},
		{
			"key":"PT02_S219_21_02",
			"value":"ああ、カイト……一切の容赦はなしだ……\n我々に刃向かう愚かさを後悔させてやる……！"
		},
		{
			"key":"PT02_S322_11_01",
			"value":"ベルゼブモン！\n任せてもいいか？"
		},
		{
			"key":"PT02_S322_11_02",
			"value":"ふっ……今さらだぜ、カイト"
		},
		{
			"key":"PT02_S322_12_01",
			"value":"ベルゼブモン！\n究極の力を見せてくれ！！"
		},
		{
			"key":"PT02_S322_12_02",
			"value":"おう！　わかったカイト！！"
		},
		{
			"key":"PT02_S322_21_01",
			"value":"カイト！　お前の力が必要だ！"
		},
		{
			"key":"PT02_S322_21_02",
			"value":"わかったベルゼブモン！\nオレの気合いをわけてやるぜ！！"
		},
		{
			"key":"PT02_S322_22_01",
			"value":"カイト！　ここからが本番だぜ！\nしっかりついてきな！！"
		},
		{
			"key":"PT02_S322_22_02",
			"value":"おう！　お前こそ出遅れんなよ！！"
		},
		{
			"key":"PT02_S318_11_01",
			"value":"ボルトバウタモン、お前を信じても良いのか？"
		},
		{
			"key":"PT02_S318_11_02",
			"value":"もちろんだカイト……\nこの力……お前のために使わせてもらう！"
		},
		{
			"key":"PT02_S318_12_01",
			"value":"ボルトバウタモン！\n最凶の力をぶつけてやれ！！"
		},
		{
			"key":"PT02_S318_12_02",
			"value":"ふはははは！！\n承知！！"
		},
		{
			"key":"PT02_S318_21_01",
			"value":"カイト！　戦いのカギを握っているのはお前だ！！"
		},
		{
			"key":"PT02_S318_21_02",
			"value":"そうだなボルトバウタモン！\n気合い入れていくぜ！！"
		},
		{
			"key":"PT02_S318_22_01",
			"value":"カイトよ……共に参らん……\n地獄の戦場へ……"
		},
		{
			"key":"PT02_S318_22_02",
			"value":"いいぜボルトバウタモン……\n一緒に地獄を生き延びようぜ！！"
		},
		{
			"key":"PT08_S908_11_01",
			"value":"みんなの足、引っ張らないようにしないと……"
		},
		{
			"key":"PT08_S000_11_01",
			"value":"用心して！\n敵の攻撃をよく見て！！"
		},
		{
			"key":"PT08_S000_12_01",
			"value":"頑張ろう！\nウチもついてるから！！"
		},
		{
			"key":"PT08_S901_11_01",
			"value":"タクマさん、しっかり！\nウチも頑張るから！"
		},
		{
			"key":"PT08_S901_11_02",
			"value":"ああミウ！\n一緒に立ち向かおう！！"
		},
		{
			"key":"PT08_S901_12_01",
			"value":"タクマさん、守りを固めて\n慎重に行こうね！"
		},
		{
			"key":"PT08_S901_12_02",
			"value":"そうだなミウ！\nディフェンスは重要だな！"
		},
		{
			"key":"PT08_S901_13_01",
			"value":"タクマさんと一緒なら、ウチ、\n負ける気がしない……行ける！"
		},
		{
			"key":"PT08_S901_13_02",
			"value":"僕もだミウ……キミがいれば\nどんな戦いも勝てる気がする！！"
		},
		{
			"key":"PT08_S903_11_01",
			"value":"アオイさん、ウチも頑張るから、\n元気出していこ！"
		},
		{
			"key":"PT08_S903_11_02",
			"value":"ミウちゃん……\nそうだね、怖じ気づいている場合じゃなかったわね！"
		},
		{
			"key":"PT08_S903_12_01",
			"value":"アオイさん、ウチには精霊の加護があるの！\nアオイさんにもそれをわけてあげるね！"
		},
		{
			"key":"PT08_S903_12_02",
			"value":"ミウちゃんたら……\nわかったわ、その加護の力、しっかりといただくから！"
		},
		{
			"key":"PT08_S904_11_01",
			"value":"ミノルさん！　ウチがついてるから、頑張ろうね！\n守ってあげるから！"
		},
		{
			"key":"PT08_S904_11_02",
			"value":"なに言ってんだよミウ！\n守るのはオレの方だぜ！"
		},
		{
			"key":"PT08_S904_12_01",
			"value":"ミノルさん、ウチが敵に呪いをかけるから、\n安心して戦ってね！"
		},
		{
			"key":"PT08_S904_12_02",
			"value":"な、なんか微妙に安心したくないんだけど……\nまあいいや、やってやるぜ！！"
		},
		{
			"key":"PT08_S906_11_01",
			"value":"リョウさん、ビビってる？\nウチが励ましてあげるね！　頑張ろー！！"
		},
		{
			"key":"PT08_S906_11_02",
			"value":"バ、バカ！　オレ様があんなザコに\nビビるわけねーだろ！　余裕でやっつけてやるぜ！！"
		},
		{
			"key":"PT08_S906_12_01",
			"value":"リョウさん、ウチの霊感がこのバトルの\n勝利を知らせてくれる！　だから一緒に頑張ろう！"
		},
		{
			"key":"PT08_S906_12_02",
			"value":"なにが霊感だよ、ったく……\nへへ……んなのなくても楽勝だっつーの！"
		},
		{
			"key":"PT08_S905_11_01",
			"value":"あ、シュウジさん……もしかして怖がってる？\nウチも手伝うから、ね？"
		},
		{
			"key":"PT08_S905_11_02",
			"value":"君にもわかるか、やはり……\nわかった、アテにしてるよミウちゃん！"
		},
		{
			"key":"PT08_S905_12_01",
			"value":"シュウジさん、ウチからおまじないしておくから、\nとっておきのだよ！"
		},
		{
			"key":"PT08_S905_12_02",
			"value":"な、なんだかわからないけど、ありがとう！"
		},
		{
			"key":"PT08_S907_11_01",
			"value":"サキさん、ウチも戦いは恐いけど、\n一緒にやるだけやってみようね！"
		},
		{
			"key":"PT08_S907_11_02",
			"value":"そうだねミウちゃん！\n必ず生き延びようね！！"
		},
		{
			"key":"PT08_S907_12_01",
			"value":"この世界の大いなる意思が、ウチらに味方してくれる\nだからこの戦いもきっと大丈夫だよ"
		},
		{
			"key":"PT08_S907_12_02",
			"value":"ミウちゃんの場合、この手の発言は怪しいんだよなぁ\nまあけど、信じるしかないか！！"
		},
		{
			"key":"PT08_S902_11_01",
			"value":"お兄ちゃん、ひょっとしてビビってる？\nウチが手を握ってあげようか？"
		},
		{
			"key":"PT08_S902_11_02",
			"value":"ビビってるわけねーだろ！\nオ、オレはいつだって平常運転だ！！"
		},
		{
			"key":"PT08_S902_12_01",
			"value":"お兄ちゃん、あんまり熱くならないで、冷静にね"
		},
		{
			"key":"PT08_S902_12_02",
			"value":"わかってるってミウ！\nあんなザコに正気は失わねーよ！！"
		},
		{
			"key":"PT08_S902_13_01",
			"value":"お兄ちゃん、頑張って！\nウチも応援してるから！！"
		},
		{
			"key":"PT08_S902_13_02",
			"value":"ミウ……いよおおおおおおし！！\nやるぞおおおおおおおお！！！"
		},
		{
			"key":"PT08_S911_11_01",
			"value":"教授、腰が引けてるように見えますけど、\nウチにできることとかあります？"
		},
		{
			"key":"PT08_S911_11_02",
			"value":"い、いや……すまんミウくん\n大人の私がこんなことではいかんな！"
		},
		{
			"key":"PT08_S911_12_01",
			"value":"くくくく……敵にホラーなビジョンを送ってやった……\n教授、敵はすぐに逃げ出しますよ～"
		},
		{
			"key":"PT08_S911_12_02",
			"value":"むむ、これはなにが起こるか予想がつかんな……\n守りを固めておく必要があるな……"
		},
		{
			"key":"PT08_S912_11_01",
			"value":"ミユキさん！　戦いには慣れてないかな？\nここはウチに任せて！"
		},
		{
			"key":"PT08_S912_11_02",
			"value":"ううん、ミウさん、久しぶりだから少し戸惑ってるだけ\nすぐにカンは取り戻せるから！"
		},
		{
			"key":"PT08_S912_12_01",
			"value":"ミユキさん、敵が勢いづいてる！\nディフェンスに集中しないと！"
		},
		{
			"key":"PT08_S912_12_02",
			"value":"そうねミウさん、あなたの言う通りね！"
		},
		{
			"key":"PT08_S005_11_01",
			"value":"シャコモン、ウチがついてるから、頑張って！"
		},
		{
			"key":"PT08_S005_11_02",
			"value":"は～い！\nやるだけやってみるね～！"
		},
		{
			"key":"PT08_S005_12_01",
			"value":"シャコモン、頼りにしてるからね！"
		},
		{
			"key":"PT08_S005_12_02",
			"value":"ミウ、私の活躍、期待しててね！"
		},
		{
			"key":"PT08_S005_13_01",
			"value":"シャコモン……ウチの気持ち、伝わってるよね"
		},
		{
			"key":"PT08_S005_13_02",
			"value":"当然！　ミウの熱い気持ち、\nどんどん流れ込んでくるよ！"
		},
		{
			"key":"PT08_S005_21_01",
			"value":"女王……じゃなかった、ミウ\n気を引き締めていこうね！"
		},
		{
			"key":"PT08_S005_21_02",
			"value":"うん、シャコモン……\nケガなんかしちゃダメだよ！"
		},
		{
			"key":"PT08_S005_22_01",
			"value":"ミウ、お兄ちゃんに心配されないように、\nしっかりやっていこうね！"
		},
		{
			"key":"PT08_S005_22_02",
			"value":"そうだねシャコモン！\nウチが一人前だって、わからせないとね！"
		},
		{
			"key":"PT08_S005_23_01",
			"value":"ミウ……あなたと一緒なら、恐いものなんてない！"
		},
		{
			"key":"PT08_S005_23_02",
			"value":"うん、ウチもそうだよ……！\nシャコモン！！"
		},
		{
			"key":"PT08_S106_11_01",
			"value":"シェルモン！\n強くなったキミの力、しっかり見せて！"
		},
		{
			"key":"PT08_S106_11_02",
			"value":"はいは～い！\n誰でも蹴散らしちゃうから～！"
		},
		{
			"key":"PT08_S106_12_01",
			"value":"シェルモン！\n敵をやっつけちゃって～！"
		},
		{
			"key":"PT08_S106_12_02",
			"value":"オッケー、ミウ！\nどんどんやっちゃうよ～！！"
		},
		{
			"key":"PT08_S106_21_01",
			"value":"すごい……！\nシェルモンのやる気が伝わってくる……！！"
		},
		{
			"key":"PT08_S106_21_02",
			"value":"それは絆の力！\n私とミウが絶好調の証！！"
		},
		{
			"key":"PT08_S224_11_01",
			"value":"殻を破ったマーメイモンは無敵だよ！\nそーだよねっ！！"
		},
		{
			"key":"PT08_S224_11_02",
			"value":"ええそうね！\nミウの期待に応えて見せましょう！！"
		},
		{
			"key":"PT08_S224_12_01",
			"value":"マーメイモン！\n先手必勝だよ！"
		},
		{
			"key":"PT08_S224_12_02",
			"value":"そうねミウ！\n敵の出鼻を挫くわ！！"
		},
		{
			"key":"PT08_S224_21_01",
			"value":"頑張れマーメイモン！\nウチがついてるからね！！"
		},
		{
			"key":"PT08_S224_21_02",
			"value":"ありがとうミウ！\nあなたの気持ち、よく伝わってくるわ！！"
		},
		{
			"key":"PT08_S326_11_01",
			"value":"マリンエンジェモン！\nみんなの力になってね！！"
		},
		{
			"key":"PT08_S326_11_02",
			"value":"ぴいぴい！"
		},
		{
			"key":"PT08_S326_12_01",
			"value":"マリンエンジェモン！\n最高の力を私に見せて！！"
		},
		{
			"key":"PT08_S326_12_02",
			"value":"ぷうぷう！"
		},
		{
			"key":"PT08_S326_21_01",
			"value":"ぴいぷう！"
		},
		{
			"key":"PT08_S326_21_02",
			"value":"……頑張れミウ？\nうん、わかったよ！"
		},
		{
			"key":"PT08_S326_22_01",
			"value":"ぴいぴいぷう！"
		},
		{
			"key":"PT08_S326_22_02",
			"value":"……ミウ、一緒に戦おう？\nマリンエンジェモン、もちろんだよ！！"
		},
		{
			"key":"PT11_S911_11_01",
			"value":"お喋りしている場合ではないな\n命が……かかっているのだから！"
		},
		{
			"key":"PT11_S911_12_01",
			"value":"どうすれば、私は許されるのだ……\nいや、それを望むこと自体、もう手遅れだというのか？"
		},
		{
			"key":"PT11_S000_11_01",
			"value":"いいぞ……よし、この調子でいこう！"
		},
		{
			"key":"PT11_S901_11_01",
			"value":"タクマくん、敵は強力だが、我々ならきっと\n切り抜けられるぞ"
		},
		{
			"key":"PT11_S901_11_02",
			"value":"はい、教授！\nなんとかしてみせます！"
		},
		{
			"key":"PT11_S901_12_01",
			"value":"我々が力を合わせれば、\nいかなる危機も打破できるだろう。"
		},
		{
			"key":"PT11_S901_12_02",
			"value":"そうですね教授！\n僕たちが力を合わせれば、いけるはずです！"
		},
		{
			"key":"PT11_S903_11_01",
			"value":"アオイくん、気後れするなよ\n敵はそこをつけ込んでくる"
		},
		{
			"key":"PT11_S903_11_02",
			"value":"ええ、決して怯まずこの危機にも立ち向かいます！"
		},
		{
			"key":"PT11_S903_12_01",
			"value":"アオイくん、この戦いのカギは、君が握っている"
		},
		{
			"key":"PT11_S903_12_02",
			"value":"教授……ええ、わかりました！"
		},
		{
			"key":"PT11_S904_11_01",
			"value":"ミノルくん、弱気は禁物だ……\n一緒に困難に立ち向かおう！"
		},
		{
			"key":"PT11_S904_11_02",
			"value":"そ、そうですね……ありがとうございます\nオレ……全力で頑張ります！"
		},
		{
			"key":"PT11_S904_12_01",
			"value":"なるほど、敵はそれなりの数を揃えてきたか……\nミノルくん、覚悟はいいかね？"
		},
		{
			"key":"PT11_S904_12_02",
			"value":"ええ教授……\nこの戦いに勝って、オレ、理想のヒーローになります！"
		},
		{
			"key":"PT11_S906_11_01",
			"value":"どうしたリョウくん？\n呼吸が乱れているようだが、大丈夫か？"
		},
		{
			"key":"PT11_S906_11_02",
			"value":"は、はい教授……な、なんとか平気です……\nつーか、全然平気です！"
		},
		{
			"key":"PT11_S906_12_01",
			"value":"よし、リョウくんここから一気に畳みかけよう\n覚悟はいいかね？"
		},
		{
			"key":"PT11_S906_12_02",
			"value":"もちろん！\nこっちはいつでもＯＫだ！"
		},
		{
			"key":"PT11_S905_11_01",
			"value":"シュウジくん、不安もあるだろが、\nそれに呑まれてはいかんぞ"
		},
		{
			"key":"PT11_S905_11_02",
			"value":"わかりました教授……\n出来るだけの勇気を振り絞ります！"
		},
		{
			"key":"PT11_S905_12_01",
			"value":"シュウジくん、戦いの流れはこちらにあると見た\n君のリーダーシップに期待しているよ"
		},
		{
			"key":"PT11_S905_12_02",
			"value":"はい、教授！\n僕の力でこの状況を乗り切ってみせます！"
		},
		{
			"key":"PT11_S907_11_01",
			"value":"サキくん、戦いの恐ろしさはわかるが、\n立ち向かう勇気を持つんだ！"
		},
		{
			"key":"PT11_S907_11_02",
			"value":"うん、ありがとう教授\n私……決して逃げたりしない！"
		},
		{
			"key":"PT11_S907_12_01",
			"value":"これは勝てる戦いだ\n我々の力があれば、必ずな！"
		},
		{
			"key":"PT11_S907_12_02",
			"value":"うん、教授……そうだよね\nこれまでもみんなで力を合わせて勝ってきたものね！"
		},
		{
			"key":"PT11_S902_11_01",
			"value":"カイトくんどうした？\nキミらしくもない怯えを感じるが？"
		},
		{
			"key":"PT11_S902_11_02",
			"value":"チッ……さすがは教授、見抜かれたか……\nけどもう平気だ！　怯えなんて敵ごと蹴散らしてやる！"
		},
		{
			"key":"PT11_S902_12_01",
			"value":"カイトくん、敵の動きに不穏さを感じる\n突破できそうかな？"
		},
		{
			"key":"PT11_S902_12_02",
			"value":"ああ教授、それはこっちも感じてたところだ……\nもちろん、オレたちの力で打ち砕いてやるさ！"
		},
		{
			"key":"PT11_S908_11_01",
			"value":"ミウくん、恐いだろうがここは踏ん張りどころだ\n一緒に頑張ろう！"
		},
		{
			"key":"PT11_S908_11_02",
			"value":"うん、ウチ恐いけど……\n一歩も退かない！　戦い抜く！"
		},
		{
			"key":"PT11_S908_12_01",
			"value":"なにやら戦況に動きがありそうだ……\nミウくん、気を引き締めてかかろう！"
		},
		{
			"key":"PT11_S908_12_02",
			"value":"うん、なんかヤバイっぽい感じだね……\nウチも気合い入れて行くから！！"
		},
		{
			"key":"PT11_S912_11_01",
			"value":"姉さん、大丈夫？\nちょっと弱気になってるみたいだけど……？"
		},
		{
			"key":"PT11_S912_11_02",
			"value":"ええ、けど平気……\nだって、ハルが一緒だもの！！"
		},
		{
			"key":"PT11_S912_12_01",
			"value":"昔のように一緒に戦えるなんて夢みたいだ！\n姉さん……頑張ろう！！"
		},
		{
			"key":"PT11_S912_12_02",
			"value":"ええ、ハル……あの頃みたいにね！！"
		},
		{
			"key":"PT11_S007_11_01",
			"value":"ガブモン、大丈夫か？\n戦えるか？"
		},
		{
			"key":"PT11_S007_11_02",
			"value":"フン、心配なんていらないね！\nお前の心配なんて……！"
		},
		{
			"key":"PT11_S007_21_01",
			"value":"ガブモン、頑張るんだ！\n私もついている！"
		},
		{
			"key":"PT11_S007_21_02",
			"value":"ああ、そうだな！\nハルと一緒なら、いくらでも頑張れる！"
		},
		{
			"key":"PT11_S007_31_01",
			"value":"ハル、久しぶりのバトルだけど、\n恐くないか？　平気か？"
		},
		{
			"key":"PT11_S007_31_02",
			"value":"もちろん平気だ！\nガブモンがいるのだから、恐いはずがない！"
		},
		{
			"key":"PT11_S101_11_01",
			"value":"ガルルモン、不安はないか？\n恐ろしくはないか？"
		},
		{
			"key":"PT11_S101_11_02",
			"value":"うるせえな！\nテメーじゃあるまいし、オレはなんともねえ！！"
		},
		{
			"key":"PT11_S101_21_01",
			"value":"ガルルモン！\nキミの力を存分に発揮してくれ！"
		},
		{
			"key":"PT11_S101_21_02",
			"value":"ああ、わかってる！\nオレの活躍、しっかり見守ってくれよな！！"
		},
		{
			"key":"PT11_S101_31_01",
			"value":"頑張れガルルモン！\n信じているぞ！！"
		},
		{
			"key":"PT11_S101_31_02",
			"value":"ありがとうハル！\nお前の信頼、絶対に応えてみせる！！"
		},
		{
			"key":"PT11_S218_11_01",
			"value":"ワーガルルモン……\nキミは我々のために。戦ってくれるのか？"
		},
		{
			"key":"PT11_S218_11_02",
			"value":"いいや、てめえらのためじゃねえ\nオレはオレのために戦う……それだけだ！"
		},
		{
			"key":"PT11_S218_21_01",
			"value":"ワーガルルモン、一気に突破しよう！\n攻撃あるのみだ！！"
		},
		{
			"key":"PT11_S218_21_02",
			"value":"ああもちろん！\nオレの力、よーく見ておいてくれよ！！"
		},
		{
			"key":"PT11_S218_31_01",
			"value":"ワーガルルモン、ここは慎重に行こう！\nいいかな！？"
		},
		{
			"key":"PT11_S218_31_02",
			"value":"そうだなハル！\n守りを固めておこう！"
		},
		{
			"key":"PT11_S301_11_01",
			"value":"メタルガルルモン！\nお前なら敵を翻弄できるだろう！"
		},
		{
			"key":"PT11_S301_11_02",
			"value":"任せろハル！\n速攻戦でヤツらを引っかき回してやるぜ！！"
		},
		{
			"key":"PT11_S301_12_01",
			"value":"よし、メタルガルルモン！\n究極の力を見せつけてやれ！！"
		},
		{
			"key":"PT11_S301_12_02",
			"value":"そうだな、ハル！　お前のおかげで得た力、\n増分に発揮してみせよう！！"
		},
		{
			"key":"PT11_S301_21_01",
			"value":"ハル、戦いはもっと激しくなる……\nそれでも大丈夫か？"
		},
		{
			"key":"PT11_S301_21_02",
			"value":"メタルガルルモン、なにを言っている？\nキミがいる以上、不安など皆無だ！"
		},
		{
			"key":"PT11_S301_22_01",
			"value":"ハル、オレは今最高の気分だ……\n何せ、お前と再びこうして共にいられるのだから！"
		},
		{
			"key":"PT11_S301_22_02",
			"value":"メタルガルルモン……私もだ……\n勇気というものが、いくらでも沸いてくるぞ！"
		},
		{
			"key":"PT11_S402_11_01",
			"value":"オメガモン！\n今こそ戦いに終止符を打とう！！"
		},
		{
			"key":"PT11_S402_11_02",
			"value":"そうだなハル！\nこの力で、ケリを着けてみせる！！"
		},
		{
			"key":"PT11_S402_12_01",
			"value":"オメガモン……なんて素晴らしい……！\n二つの力が一つになるなんて……！！"
		},
		{
			"key":"PT11_S402_12_02",
			"value":"いいやハル、俺たちだけじゃない、\nハルやタクマ、四つの力がひとつになったのがこの姿だ"
		},
		{
			"key":"PT11_S402_21_01",
			"value":"ハル、ここは俺たちに任せてくれ！"
		},
		{
			"key":"PT11_S402_21_02",
			"value":"ああオメガモン！\nその力、アテにしているぞ！！"
		},
		{
			"key":"PT11_S402_22_01",
			"value":"ハル、安心してくれ……\nこの力があれば、誰にも負けん！"
		},
		{
			"key":"PT11_S402_22_02",
			"value":"そうだなオメガモン……\n究極の合わさった更なる高みの力、期待させてもらうぞ"
		},
		{
			"key":"PT12_S912_11_01",
			"value":"この戦いに私の全てをかける！"
		},
		{
			"key":"PT12_S000_11_01",
			"value":"みんななら勝てる\n私にはそれがわかる……！"
		},
		{
			"key":"PT12_S901_11_01",
			"value":"タクマさん\nみんなで生き延びましょう！"
		},
		{
			"key":"PT12_S901_11_02",
			"value":"ああもちろんだ！\n必ず生き延びてみせる！"
		},
		{
			"key":"PT12_S901_12_01",
			"value":"頑張りましょう、タクマさん！\n私もできるだけのことをするから！"
		},
		{
			"key":"PT12_S901_12_02",
			"value":"そうだなミユキ！\n僕たち二人で力を合わせよう！"
		},
		{
			"key":"PT12_S903_11_01",
			"value":"アオイさん、敵は強いけど\n倒せない相手じゃないわ！"
		},
		{
			"key":"PT12_S903_11_02",
			"value":"そ、そうねミユキちゃん……\nうん……頑張りましょう！"
		},
		{
			"key":"PT12_S903_12_01",
			"value":"アオイさん、私たちの力で\nこの戦いを生き延びましょう！"
		},
		{
			"key":"PT12_S903_12_02",
			"value":"ええ、そうねミユキちゃん\nあなたと一緒なら……なんとかなりそうな気がする！"
		},
		{
			"key":"PT12_S904_11_01",
			"value":"ミノルさん、しっかりして\n弱気は禁物よ"
		},
		{
			"key":"PT12_S904_11_02",
			"value":"へへへ……年下の子に励まされるなんて、情けねえけど\nいっちょやってやるか！"
		},
		{
			"key":"PT12_S904_12_01",
			"value":"ミノルさんなら必ず生き延びられる\n私にはそう思えるの！"
		},
		{
			"key":"PT12_S904_12_02",
			"value":"へへ、気休めサンキュー！\nそれでも勇気が沸いてきたぜ！"
		},
		{
			"key":"PT12_S906_11_01",
			"value":"リョウさん、震えを止めて\n敵に見られてるわ"
		},
		{
			"key":"PT12_S906_11_02",
			"value":"う、うっせーな！　震えてなんてねーし！\nオレは最強なんだぜ！？"
		},
		{
			"key":"PT12_S906_12_01",
			"value":"リョウさんがいてくれるのなら、\nこの戦い、負けることはないわ！"
		},
		{
			"key":"PT12_S906_12_02",
			"value":"おっ！　わかってるじゃねーか！\nさすがはミユキだ！"
		},
		{
			"key":"PT12_S905_11_01",
			"value":"シュウジさん、恐いのはわかるけど、\n今は……"
		},
		{
			"key":"PT12_S905_11_02",
			"value":"ああ、恐怖を制御してみせるさ\n今の僕ならそれができるはずだ！"
		},
		{
			"key":"PT12_S905_12_01",
			"value":"シュウジさん、戦いに集中しましょう\nみんなで生き延びるために……！"
		},
		{
			"key":"PT12_S905_12_02",
			"value":"そうだね、僕はみんなを預かる立場なんだ\nだから、僕が冷静さを失ってはいけない！"
		},
		{
			"key":"PT12_S907_11_01",
			"value":"サキさん、大丈夫？\nちょっと不安そうに見えるけど"
		},
		{
			"key":"PT12_S907_11_02",
			"value":"へ、平気よこんなの……\n全っ然平気なんだから！"
		},
		{
			"key":"PT12_S907_12_01",
			"value":"サキさん、敵は見かけだけ\nあなたなら絶対に負けない！"
		},
		{
			"key":"PT12_S907_12_02",
			"value":"う、うん、そーだよね！\n私たちが負けるはずなんてないものね！"
		},
		{
			"key":"PT12_S902_11_01",
			"value":"カイトさん、もしかして弱気になってる？\nだとしたら、気持ちをしっかり持って！"
		},
		{
			"key":"PT12_S902_11_02",
			"value":"チッ、見抜かれちまってるかよ……\nああわかった、ここは気合いを入れるぜ！"
		},
		{
			"key":"PT12_S902_12_01",
			"value":"カイトさん、一緒に頑張りましょう\nあなたの力があれば、勝てる！"
		},
		{
			"key":"PT12_S902_12_02",
			"value":"ああ、そうだな、オレたちみんなで\nこの戦いにケリを着けよーぜ！！"
		},
		{
			"key":"PT12_S908_11_01",
			"value":"ミウさん、恐い？\n大丈夫、みんながついてるから！"
		},
		{
			"key":"PT12_S908_11_02",
			"value":"うん……ウチも怖がってなんていられない\nみんなと一緒に頑張る！"
		},
		{
			"key":"PT12_S908_12_01",
			"value":"ミウさん、私はもう敵のいいなりになんてならない\nだから安心して戦いましょう！"
		},
		{
			"key":"PT12_S908_12_02",
			"value":"うん！　ウチ、ミユキさんのこと信じてる！\nミユキさんは、ウチらの仲間だもん！"
		},
		{
			"key":"PT12_S911_11_01",
			"value":"ハル、怯えてるの？\n大丈夫よ、私がついてるから"
		},
		{
			"key":"PT12_S911_11_02",
			"value":"そ、その言葉、昔にも聞いたことがある……\nそう……勇気の湧いてくる魔法の言葉だ！！"
		},
		{
			"key":"PT12_S911_12_01",
			"value":"ハル、あなたは昔よりずっと強くなった\nだから平気……安心して！"
		},
		{
			"key":"PT12_S911_12_02",
			"value":"ああ、昔とは違う……\n今度は私が、姉さんを助ける番だ！"
		},
		{
			"key":"PT12_S016_11_01",
			"value":"ミユキを救うためだ……\n手段など選ぶつもりはない！"
		},
		{
			"key":"PT12_S016_21_01",
			"value":"レナモン！　敵に遅れを\n取らないようにしましょうね！"
		},
		{
			"key":"PT12_S016_21_02",
			"value":"もちろん！\nスピードなら私の得意とするところだ！"
		},
		{
			"key":"PT12_S016_31_01",
			"value":"ミユキ！　久しぶりの戦いだけど、\n私がついているから安心して！"
		},
		{
			"key":"PT12_S016_31_02",
			"value":"そうね、レナモン！\nあなたがいれば、恐いものなんてない！"
		},
		{
			"key":"PT12_S125_11_01",
			"value":"ミユキ……\nあなたを守るのは、この私……！"
		},
		{
			"key":"PT12_S125_21_01",
			"value":"キュウビモン！　頑張って！\nあなたの力を信じているから！"
		},
		{
			"key":"PT12_S125_21_02",
			"value":"その信頼に応えてみせましょう！\n見ててミユキ！！"
		},
		{
			"key":"PT12_S125_31_01",
			"value":"キュウビモン、しっかりして！"
		},
		{
			"key":"PT12_S125_31_02",
			"value":"ええ、心配かけてすまないミユキ……\nけど、もう平気だ！"
		},
		{
			"key":"PT12_S225_11_01",
			"value":"ミユキのため、この戦い……\n決して負けられない！"
		},
		{
			"key":"PT12_S225_21_01",
			"value":"タオモン！　一気に敵を突破しましょう！"
		},
		{
			"key":"PT12_S225_21_02",
			"value":"承知した！　全力を以てヤツらを屠るのみ！"
		},
		{
			"key":"PT12_S225_31_01",
			"value":"タオモン……大丈夫？\nまだ戦えそう？"
		},
		{
			"key":"PT12_S225_31_02",
			"value":"あ、ああ……私なら大丈夫\nここから一気に反撃だ！"
		},
		{
			"key":"PT12_S334_11_01",
			"value":"ミユキとの未来……\nそれが私の望みだ！"
		},
		{
			"key":"PT12_S334_21_01",
			"value":"サクヤモン、疲れてない？\n少し休もうか？"
		},
		{
			"key":"PT12_S334_21_02",
			"value":"いや、平気だミユキ……\nこの程度の敵に遅れは取らん！"
		},
		{
			"key":"PT12_S334_22_01",
			"value":"サクヤモン！　一緒に頑張りましょう！"
		},
		{
			"key":"PT12_S334_22_02",
			"value":"ああミユキ！\nキミがいれば、私はどんな敵にも決して負けない！！"
		},
		{
			"key":"PT12_S334_31_01",
			"value":"ミユキ、恐くない？\nこの戦いは過酷になりそうだし……"
		},
		{
			"key":"PT12_S334_31_02",
			"value":"ううん恐くなんてない\nだってサクヤモンがいるから！"
		},
		{
			"key":"PT12_S334_32_01",
			"value":"ミユキ！　こうやって再び戦える様になって\n本当に嬉しいわ！"
		},
		{
			"key":"PT12_S334_32_02",
			"value":"私もよ、サクヤモン！"
		},
		{
			"key":"PT12_S328_11_01",
			"value":"私はミユキが幸せならそれでいい\nそう、ミユキが幸せであれば……！"
		},
		{
			"key":"PT12_S328_21_01",
			"value":"サクヤモン、頑張って！"
		},
		{
			"key":"PT12_S328_21_02",
			"value":"ミユキの気持ち、確かに受け取った！"
		},
		{
			"key":"PT12_S328_22_01",
			"value":"サクヤモン！\n二人でこの戦いを乗り切りましょう！"
		},
		{
			"key":"PT12_S328_22_02",
			"value":"もちろんミユキ！\n共に進みましょう！"
		},
		{
			"key":"PT12_S328_31_01",
			"value":"ミユキ、必ず守り抜くから、私を信じて！"
		},
		{
			"key":"PT12_S328_31_02",
			"value":"ええ、サクヤモン！\n信じてるわ！！"
		},
		{
			"key":"PT12_S328_32_01",
			"value":"ミユキ！　私のこの力で\n敵を撃破してみせるわ！"
		},
		{
			"key":"PT12_S328_32_02",
			"value":"巫女の力……そうね、その力なら、きっと……\nうん、私にもわかるわ！！"
		},
		{
			"key":"PT01_S310_11_01",
			"value":"頑張ろう！　ファンロンモン！"
		},
		{
			"key":"PT01_S310_11_02",
			"value":"ワタシに敗北の由は無し、行くぞ！"
		},
		{
			"key":"PT01_S310_12_01",
			"value":"行くぞ、ファンロンモン！"
		},
		{
			"key":"PT01_S310_12_02",
			"value":"承知っ！　タクマ！！"
		},
		{
			"key":"PT01_S310_21_01",
			"value":"汝が諦めぬ限り、ワタシは全力を尽くそうぞ！"
		},
		{
			"key":"PT01_S310_21_02",
			"value":"ファンロンモン……まだ、いけるな？\nよし、皆のためにやるぞ！！"
		},
		{
			"key":"PT01_S310_22_01",
			"value":"全ては、タクマの意のままに！"
		},
		{
			"key":"PT01_S310_22_02",
			"value":"ファンロンモン……ありがとう！"
		},
		{
			"key":"PT03_S307_11_01",
			"value":"バイフーモン！　私は信じてるわ！"
		},
		{
			"key":"PT03_S307_11_02",
			"value":"もちろんだアオイ……\nワタシはその願いを叶えるのだ"
		},
		{
			"key":"PT03_S307_12_01",
			"value":"バイフーモン！　相手は侮れないわ！"
		},
		{
			"key":"PT03_S307_12_02",
			"value":"心得た……\n確かにそのようだな"
		},
		{
			"key":"PT03_S307_21_01",
			"value":"アオイ、信じるのだ\n悲しみを繰り返したりはしないと"
		},
		{
			"key":"PT03_S307_21_02",
			"value":"ええ、バイフーモン！\n私も信じてるわ！！"
		},
		{
			"key":"PT03_S307_22_01",
			"value":"アオイの願いを叶えるは、我が願い\n今こそ、この力を見せようぞ！"
		},
		{
			"key":"PT03_S307_22_02",
			"value":"そうよね、バイフーモン\n私が強く願えばいいのね！"
		},
		{
			"key":"PT04_S306_11_01",
			"value":"スーツェーモン！\n平気か！？"
		},
		{
			"key":"PT04_S306_11_02",
			"value":"平気というのが、ヒーローか\n 少なくとも,汝より余裕はある"
		},
		{
			"key":"PT04_S306_12_01",
			"value":"その調子だ！　スーツェーモン\n俺たちの力の見せ所だ！"
		},
		{
			"key":"PT04_S306_12_02",
			"value":"無論だ、ミノルよ\nその気持ち、確かに受け取った！"
		},
		{
			"key":"PT04_S306_21_01",
			"value":"ミノルよ！\n今こそヒーローへの思いを解き放つのだ！"
		},
		{
			"key":"PT04_S306_21_02",
			"value":"ああ、スーツェーモン！\nいくらでも解き放ってやるぜ！！"
		},
		{
			"key":"PT04_S306_22_01",
			"value":"皆まで言うな、ミノルよ\n我々の勝利は目前だ"
		},
		{
			"key":"PT04_S306_22_02",
			"value":"スーツェーモン……くっ！\nお前の方がよっぽどヒーローだぜ！！"
		},
		{
			"key":"PT07_S309_11_01",
			"value":"お願い！　シェンウーモン\n私も一緒に戦うわ！"
		},
		{
			"key":"PT07_S309_11_02",
			"value":"サキよ、いい笑顔じゃな\n全身に力がみなぎってくるようだ"
		},
		{
			"key":"PT07_S309_12_01",
			"value":"シェンウーモン！\nぜーんぶ、やっつけちゃっていいんだからね！"
		},
		{
			"key":"PT07_S309_12_02",
			"value":"ぬう、よかろう"
		},
		{
			"key":"PT07_S309_21_01",
			"value":"長生きはしてみるものだ\nサキが力を与えてくれるようだ"
		},
		{
			"key":"PT07_S309_21_02",
			"value":"シェンウーモン、ありがとう！\n私も頑張るね"
		},
		{
			"key":"PT07_S309_22_01",
			"value":"サキよ、挫けるのではない\n我々の心の繋がりが力になるのだ！"
		},
		{
			"key":"PT07_S309_22_02",
			"value":"だから、大丈夫だって\nシェンウーモンは安心して戦って！"
		},
		{
			"key":"PT08_S308_11_01",
			"value":"チンロンモンは最強だよ！\nねっ、チンロンモン！"
		},
		{
			"key":"PT08_S308_11_02",
			"value":"そうだ、我が退くわけにはいかぬ\n我らは共に立ち向かうのだ！"
		},
		{
			"key":"PT08_S308_12_01",
			"value":"チンロンモン、やるよ！\nさっさとやっつけちゃえー！"
		},
		{
			"key":"PT08_S308_12_02",
			"value":"心得た、ミウ\n今こそ我が力を示さん！"
		},
		{
			"key":"PT08_S308_21_01",
			"value":"ミウよ、大丈夫だ\nこの世界の守護たる我が傍に居る"
		},
		{
			"key":"PT08_S308_21_02",
			"value":"がんばって、チンロンモン！\nウチも一緒に戦っているからね！"
		},
		{
			"key":"PT08_S308_22_01",
			"value":"そのとおりだ、ミウ\n多く者たちが、我らの勝利を願っているのだ！"
		},
		{
			"key":"PT08_S308_22_02",
			"value":"仲間のため……ううん、チンロンモン\nウチら自身のための戦うよ！"
		}
	]
}
